Workbook

Sheet Cover
B2: Reconciliation & Verification Tool
B3: Indian Tax & Compliance Rule Book for CA Firms – v2
B5: Appbay Technologies — reconciliation rules, statutory rules and document data model, YAML-ready
B9: Research date | C9: 13 October 2026
B10: Applicable tax period | C10: FY 2025-26 / AY 2026-27 (Income-tax Act, 1961) and Tax Year 2026-27 (Income-tax Act, 2025, in force from 1 April 2026); GST, payroll and company-law positions as at 13 Oct 2026
B11: Reconciliation rules | C11: =Contents!D6+Contents!D7+Contents!D8+Contents!D9 -> 90
B12: Statutory rules | C12: =Contents!D11+Contents!D12+Contents!D13+Contents!D14+Contents!D15+Contents!D16+Contents!D17+Contents!D18+Contents!D19+Contents!D20+Contents!D21+Contents!D22+Contents!D23+Contents!D24 -> 214
B13: Rules verified on an official source | C13: =Contents!E25 -> 77
B14: Documents / fields in data model | C14: 63 documents / 2096 fields
B15: How to read | C15: Start at Contents. Section A holds document-vs-document reconciliation rules; section B the statutory rules they rely on; section C the document data model and references. Row 5 of every rule sheet is the YAML key row.
B17: Verification status legend
B18: Verified – official source | C18: Key figures confirmed on an official government / regulator site
B19: Verified – secondary source only | C19: Confirmed on reputable secondary sources; official text not reached
B20: Partially verified | C20: Core rule confirmed; some element unconfirmed, or design choices involved
B21: Unverified – needs CA review | C21: Could not be confirmed – do not enable without CA review
B22: Ambiguous / conflicting – needs CA review | C22: Sources disagree or law reads ambiguously; positions recorded in Notes
B24: Important disclaimer
B25: This workbook is a research compilation to support software design. It is not legal or tax advice. Its completeness and legal correctness require validation by a qualified Chartered Accountant before any rule is implemented or relied on. Matching keys, tolerances and severities are implementation choices, not law. Laws, rates, thresholds and due dates change through Finance Acts, notifications and circulars; re-verify each rule for the period being processed. Rules not marked "Verified – official source" must be signed off in the Review Register before use.
B27: Go to Contents →

Sheet Contents
A1: Contents | J1: ← Contents
A2: Click a sheet name to open it. Counts are live formulas over each rule sheet.
A4: # | B4: Sheet | C4: What it contains | D4: Rules | E4: Verified – official | F4: Verified – secondary | G4: Partially verified | H4: Unverified | I4: Conflicting | J4: % official
B5: A. Reconciliation rules (document vs document)
A6: 1 | B6: Recon – GST | C6: Document-to-document GST reconciliation: sales register / e-invoice / e-way bill vs GSTR-1 vs GSTR-3B; purchase register vs GSTR-2B / IMS vs 3B Table 4; ledgers, interest, late fee, annual return, rate and place-of-supply checks. | D6: =COUNTA('Recon – GST'!A6:A2000) -> 40 | E6: =COUNTIF('Recon – GST'!E6:E2000,"Verified – official source") -> 0 | F6: =COUNTIF('Recon – GST'!E6:E2000,"Verified – secondary source only") -> 4 | G6: =COUNTIF('Recon – GST'!E6:E2000,"Partially verified") -> 30 | H6: =COUNTIF('Recon – GST'!E6:E2000,"Unverified – needs CA review") -> 6 | I6: =COUNTIF('Recon – GST'!E6:E2000,"Ambiguous / conflicting – needs CA review") -> 0 | J6: =IF(D6=0,0,E6/D6) -> 0
A7: 2 | B7: Recon – TDS & Income Tax | C7: Deductor-side TDS (ledger vs returns vs challans vs TRACES) and deductee-side income tax (26AS / AIS / TIS vs books vs ITR vs Form 3CD). | D7: =COUNTA('Recon – TDS & Income Tax'!A6:A2000) -> 25 | E7: =COUNTIF('Recon – TDS & Income Tax'!E6:E2000,"Verified – official source") -> 1 | F7: =COUNTIF('Recon – TDS & Income Tax'!E6:E2000,"Verified – secondary source only") -> 1 | G7: =COUNTIF('Recon – TDS & Income Tax'!E6:E2000,"Partially verified") -> 22 | H7: =COUNTIF('Recon – TDS & Income Tax'!E6:E2000,"Unverified – needs CA review") -> 1 | I7: =COUNTIF('Recon – TDS & Income Tax'!E6:E2000,"Ambiguous / conflicting – needs CA review") -> 0 | J7: =IF(D7=0,0,E7/D7) -> 0.04
A8: 3 | B8: Recon – Payroll | C8: Payroll register vs ECR vs EPF challan; ESIC; Professional Tax; payroll GL; s.36(1)(va); wage-definition, gratuity and bonus checks. | D8: =COUNTA('Recon – Payroll'!A6:A2000) -> 8 | E8: =COUNTIF('Recon – Payroll'!E6:E2000,"Verified – official source") -> 0 | F8: =COUNTIF('Recon – Payroll'!E6:E2000,"Verified – secondary source only") -> 3 | G8: =COUNTIF('Recon – Payroll'!E6:E2000,"Partially verified") -> 5 | H8: =COUNTIF('Recon – Payroll'!E6:E2000,"Unverified – needs CA review") -> 0 | I8: =COUNTIF('Recon – Payroll'!E6:E2000,"Ambiguous / conflicting – needs CA review") -> 0 | J8: =IF(D8=0,0,E8/D8) -> 0
A9: 4 | B9: Recon – Bank & Accounts | C9: Bank statement vs bank book (BRS), TB vs GL vs FS, ageing vs control accounts, FAR, stock statements, MSME, related parties, duplicates. | D9: =COUNTA('Recon – Bank & Accounts'!A6:A2000) -> 17 | E9: =COUNTIF('Recon – Bank & Accounts'!E6:E2000,"Verified – official source") -> 0 | F9: =COUNTIF('Recon – Bank & Accounts'!E6:E2000,"Verified – secondary source only") -> 4 | G9: =COUNTIF('Recon – Bank & Accounts'!E6:E2000,"Partially verified") -> 9 | H9: =COUNTIF('Recon – Bank & Accounts'!E6:E2000,"Unverified – needs CA review") -> 4 | I9: =COUNTIF('Recon – Bank & Accounts'!E6:E2000,"Ambiguous / conflicting – needs CA review") -> 0 | J9: =IF(D9=0,0,E9/D9) -> 0
B10: B. Statutory rules (law, rates, computations)
A11: 5 | B11: Income Tax | C11: Income-tax computation, rebate, rounding, presumptive taxation, disallowances, cash-transaction limits, capital gains. | D11: =COUNTA('Income Tax'!A6:A2000) -> 25 | E11: =COUNTIF('Income Tax'!E6:E2000,"Verified – official source") -> 13 | F11: =COUNTIF('Income Tax'!E6:E2000,"Verified – secondary source only") -> 1 | G11: =COUNTIF('Income Tax'!E6:E2000,"Partially verified") -> 11 | H11: =COUNTIF('Income Tax'!E6:E2000,"Unverified – needs CA review") -> 0 | I11: =COUNTIF('Income Tax'!E6:E2000,"Ambiguous / conflicting – needs CA review") -> 0 | J11: =IF(D11=0,0,E11/D11) -> 0.52
A12: 6 | B12: Advance Tax & Interest | C12: Advance tax liability, instalments, interest u/s 234A/234B/234C (new s.423/424/425), late fee. | D12: =COUNTA('Advance Tax & Interest'!A6:A2000) -> 8 | E12: =COUNTIF('Advance Tax & Interest'!E6:E2000,"Verified – official source") -> 7 | F12: =COUNTIF('Advance Tax & Interest'!E6:E2000,"Verified – secondary source only") -> 0 | G12: =COUNTIF('Advance Tax & Interest'!E6:E2000,"Partially verified") -> 1 | H12: =COUNTIF('Advance Tax & Interest'!E6:E2000,"Unverified – needs CA review") -> 0 | I12: =COUNTIF('Advance Tax & Interest'!E6:E2000,"Ambiguous / conflicting – needs CA review") -> 0 | J12: =IF(D12=0,0,E12/D12) -> 0.875
A13: 7 | B13: Returns & 26AS-AIS | C13: Return due dates, belated / revised / updated returns, 26AS / AIS / TIS, tax audit report. | D13: =COUNTA('Returns & 26AS-AIS'!A6:A2000) -> 7 | E13: =COUNTIF('Returns & 26AS-AIS'!E6:E2000,"Verified – official source") -> 1 | F13: =COUNTIF('Returns & 26AS-AIS'!E6:E2000,"Verified – secondary source only") -> 0 | G13: =COUNTIF('Returns & 26AS-AIS'!E6:E2000,"Partially verified") -> 4 | H13: =COUNTIF('Returns & 26AS-AIS'!E6:E2000,"Unverified – needs CA review") -> 1 | I13: =COUNTIF('Returns & 26AS-AIS'!E6:E2000,"Ambiguous / conflicting – needs CA review") -> 1 | J13: =IF(D13=0,0,E13/D13) -> 0.14285714
A14: 8 | B14: TDS | C14: TDS sections, thresholds, rates, due dates, interest, late fee, reconciliation (ss.192-206AA → ss.392-398). | D14: =COUNTA(TDS!A6:A2000) -> 49 | E14: =COUNTIF(TDS!E6:E2000,"Verified – official source") -> 28 | F14: =COUNTIF(TDS!E6:E2000,"Verified – secondary source only") -> 1 | G14: =COUNTIF(TDS!E6:E2000,"Partially verified") -> 17 | H14: =COUNTIF(TDS!E6:E2000,"Unverified – needs CA review") -> 3 | I14: =COUNTIF(TDS!E6:E2000,"Ambiguous / conflicting – needs CA review") -> 0 | J14: =IF(D14=0,0,E14/D14) -> 0.57142857
A15: 9 | B15: TCS | C15: TCS on goods, licences, motor vehicles / luxury goods, LRS, tour packages (s.206C → s.394). | D15: =COUNTA(TCS!A6:A2000) -> 9 | E15: =COUNTIF(TCS!E6:E2000,"Verified – official source") -> 6 | F15: =COUNTIF(TCS!E6:E2000,"Verified – secondary source only") -> 0 | G15: =COUNTIF(TCS!E6:E2000,"Partially verified") -> 3 | H15: =COUNTIF(TCS!E6:E2000,"Unverified – needs CA review") -> 0 | I15: =COUNTIF(TCS!E6:E2000,"Ambiguous / conflicting – needs CA review") -> 0 | J15: =IF(D15=0,0,E15/D15) -> 0.66666667
A16: 10 | B16: GST | C16: GSTIN, registration, place of supply, rates (GST 2.0), returns, ITC, reversals, RCM, interest, late fees, due dates. | D16: =COUNTA(GST!A6:A2000) -> 33 | E16: =COUNTIF(GST!E6:E2000,"Verified – official source") -> 6 | F16: =COUNTIF(GST!E6:E2000,"Verified – secondary source only") -> 5 | G16: =COUNTIF(GST!E6:E2000,"Partially verified") -> 21 | H16: =COUNTIF(GST!E6:E2000,"Unverified – needs CA review") -> 1 | I16: =COUNTIF(GST!E6:E2000,"Ambiguous / conflicting – needs CA review") -> 0 | J16: =IF(D16=0,0,E16/D16) -> 0.18181818
A17: 11 | B17: Payroll | C17: Labour Codes, EPF/EPS/EDLI, ESI, Professional Tax, LWF, gratuity, bonus, minimum wages, perquisites, s.36(1)(va). | D17: =COUNTA(Payroll!A6:A2000) -> 37 | E17: =COUNTIF(Payroll!E6:E2000,"Verified – official source") -> 12 | F17: =COUNTIF(Payroll!E6:E2000,"Verified – secondary source only") -> 9 | G17: =COUNTIF(Payroll!E6:E2000,"Partially verified") -> 14 | H17: =COUNTIF(Payroll!E6:E2000,"Unverified – needs CA review") -> 2 | I17: =COUNTIF(Payroll!E6:E2000,"Ambiguous / conflicting – needs CA review") -> 0 | J17: =IF(D17=0,0,E17/D17) -> 0.32432432
A18: 12 | B18: Bank Reconciliation | C18: Matching, classification, BRS statement, stale cheques. | D18: =COUNTA('Bank Reconciliation'!A6:A2000) -> 5 | E18: =COUNTIF('Bank Reconciliation'!E6:E2000,"Verified – official source") -> 1 | F18: =COUNTIF('Bank Reconciliation'!E6:E2000,"Verified – secondary source only") -> 3 | G18: =COUNTIF('Bank Reconciliation'!E6:E2000,"Partially verified") -> 1 | H18: =COUNTIF('Bank Reconciliation'!E6:E2000,"Unverified – needs CA review") -> 0 | I18: =COUNTIF('Bank Reconciliation'!E6:E2000,"Ambiguous / conflicting – needs CA review") -> 0 | J18: =IF(D18=0,0,E18/D18) -> 0.2
A19: 13 | B19: Trial Balance | C19: Arithmetic, suspense, opening-balance continuity, ledger agreement, abnormal balances. | D19: =COUNTA('Trial Balance'!A6:A2000) -> 5 | E19: =COUNTIF('Trial Balance'!E6:E2000,"Verified – official source") -> 0 | F19: =COUNTIF('Trial Balance'!E6:E2000,"Verified – secondary source only") -> 4 | G19: =COUNTIF('Trial Balance'!E6:E2000,"Partially verified") -> 1 | H19: =COUNTIF('Trial Balance'!E6:E2000,"Unverified – needs CA review") -> 0 | I19: =COUNTIF('Trial Balance'!E6:E2000,"Ambiguous / conflicting – needs CA review") -> 0 | J19: =IF(D19=0,0,E19/D19) -> 0
A20: 14 | B20: Ledger Scrutiny | C20: Cash scrutiny and limits, analytics, duplicates, dates, related parties, GST/TDS on expenses, ageing, confirmations. | D20: =COUNTA('Ledger Scrutiny'!A6:A2000) -> 14 | E20: =COUNTIF('Ledger Scrutiny'!E6:E2000,"Verified – official source") -> 0 | F20: =COUNTIF('Ledger Scrutiny'!E6:E2000,"Verified – secondary source only") -> 3 | G20: =COUNTIF('Ledger Scrutiny'!E6:E2000,"Partially verified") -> 5 | H20: =COUNTIF('Ledger Scrutiny'!E6:E2000,"Unverified – needs CA review") -> 6 | I20: =COUNTIF('Ledger Scrutiny'!E6:E2000,"Ambiguous / conflicting – needs CA review") -> 0 | J20: =IF(D20=0,0,E20/D20) -> 0
A21: 15 | B21: Financial Statements | C21: Schedule III classification, ageing, ratios, rounding, inventory reconciliation. | D21: =COUNTA('Financial Statements'!A6:A2000) -> 7 | E21: =COUNTIF('Financial Statements'!E6:E2000,"Verified – official source") -> 0 | F21: =COUNTIF('Financial Statements'!E6:E2000,"Verified – secondary source only") -> 1 | G21: =COUNTIF('Financial Statements'!E6:E2000,"Partially verified") -> 5 | H21: =COUNTIF('Financial Statements'!E6:E2000,"Unverified – needs CA review") -> 0 | I21: =COUNTIF('Financial Statements'!E6:E2000,"Ambiguous / conflicting – needs CA review") -> 1 | J21: =IF(D21=0,0,E21/D21) -> 0
A22: 16 | B22: MSME | C22: Classification, MSMED Act s.15/16 interest, MSME Form 1, s.43B(h). | D22: =COUNTA(MSME!A6:A2000) -> 4 | E22: =COUNTIF(MSME!E6:E2000,"Verified – official source") -> 1 | F22: =COUNTIF(MSME!E6:E2000,"Verified – secondary source only") -> 0 | G22: =COUNTIF(MSME!E6:E2000,"Partially verified") -> 3 | H22: =COUNTIF(MSME!E6:E2000,"Unverified – needs CA review") -> 0 | I22: =COUNTIF(MSME!E6:E2000,"Ambiguous / conflicting – needs CA review") -> 0 | J22: =IF(D22=0,0,E22/D22) -> 0.25
A23: 17 | B23: Company Law (MCA) | C23: Annual filings, other forms, late fees, small-company classification. | D23: =COUNTA('Company Law (MCA)'!A6:A2000) -> 4 | E23: =COUNTIF('Company Law (MCA)'!E6:E2000,"Verified – official source") -> 1 | F23: =COUNTIF('Company Law (MCA)'!E6:E2000,"Verified – secondary source only") -> 1 | G23: =COUNTIF('Company Law (MCA)'!E6:E2000,"Partially verified") -> 2 | H23: =COUNTIF('Company Law (MCA)'!E6:E2000,"Unverified – needs CA review") -> 0 | I23: =COUNTIF('Company Law (MCA)'!E6:E2000,"Ambiguous / conflicting – needs CA review") -> 0 | J23: =IF(D23=0,0,E23/D23) -> 0.25
A24: 18 | B24: Audit | C24: Audit trail, CARO 2020, tax audit, depreciation, accounting framework, Act transition. | D24: =COUNTA(Audit!A6:A2000) -> 7 | E24: =COUNTIF(Audit!E6:E2000,"Verified – official source") -> 0 | F24: =COUNTIF(Audit!E6:E2000,"Verified – secondary source only") -> 3 | G24: =COUNTIF(Audit!E6:E2000,"Partially verified") -> 4 | H24: =COUNTIF(Audit!E6:E2000,"Unverified – needs CA review") -> 0 | I24: =COUNTIF(Audit!E6:E2000,"Ambiguous / conflicting – needs CA review") -> 0 | J24: =IF(D24=0,0,E24/D24) -> 0
B25: Total rules | D25: =D6+D7+D8+D9+D11+D12+D13+D14+D15+D16+D17+D18+D19+D20+D21+D22+D23+D24 -> 304 | E25: =E6+E7+E8+E9+E11+E12+E13+E14+E15+E16+E17+E18+E19+E20+E21+E22+E23+E24 -> 77 | F25: =F6+F7+F8+F9+F11+F12+F13+F14+F15+F16+F17+F18+F19+F20+F21+F22+F23+F24 -> 43 | G25: =G6+G7+G8+G9+G11+G12+G13+G14+G15+G16+G17+G18+G19+G20+G21+G22+G23+G24 -> 158 | H25: =H6+H7+H8+H9+H11+H12+H13+H14+H15+H16+H17+H18+H19+H20+H21+H22+H23+H24 -> 24 | I25: =I6+I7+I8+I9+I11+I12+I13+I14+I15+I16+I17+I18+I19+I20+I21+I22+I23+I24 -> 2 | J25: =IF(D25=0,0,E25/D25) -> 0.25328947
B27: C. Data model & reference sheets
B28: Cover | C28: Title, research date, tax period, legend, disclaimer
B29: Document Pair Matrix | C29: Which documents each reconciliation rule compares – drives which files a client must upload
B30: Documents | C30: 63 documents with legal basis, formats, how obtained, due dates and the rules that use them
B31: Document Fields | C31: 2096 canonical fields (official labels, JSON paths, types, validations), incl. derived and design fields
B32: Field Map | C32: How each field reference in the rules resolves to a canonical field
B33: Act Transition | C33: Income-tax Act 1961 → 2025 section and form map
B34: Calculators | C34: Eleven worked examples with live formulas and checks
B35: Review Register | C35: Every rule not fully verified on an official source, with sign-off columns
B36: Superseded Provisions | C36: Old vs new positions and effective dates
B37: Open Questions | C37: Unresolved points requiring CA or business decision
B38: Rule Sources | C38: 951 citations, one row per rule–source pair
B39: Sources Consulted | C39: 501 pages consulted
... B41: Methodology | C41: Scope, rounds, source hierarchy, statuses, limitations

Sheet Recon – GST
A1: Recon – GST | AI1: ← Contents
A2: Document-to-document GST reconciliation: sales register / e-invoice / e-way bill vs GSTR-1 vs GSTR-3B; purchase register vs GSTR-2B / IMS vs 3B Table 4; ledgers, interest, late fee, annual return, rate and place-of-supply checks. Row 5 holds the YAML key for each column. Research date 13 October 2026. Every rule needs CA validation before use.
A3: Rules on sheet: | C3: =COUNTA(A6:A2000) -> 40
A4: Rule ID | B4: Rule type | C4: Category | D4: Rule name | E4: Verification status | F4: Purpose | G4: Document A | H4: Document B | I4: Document C | J4: Period basis | K4: Legal provision | L4: Applicability | M4: Effective from | N4: Effective to | O4: Prerequisites | P4: Match keys (A.field = B.field; canonical names) | Q4: Key normalisation | R4: Aggregation level | S4: Compare fields (A.field vs B.field) | T4: Tolerance | U4: Difference formula | V4: Step-by-step logic | W4: Mismatch categories (CODE: meaning) | X4: Severity by category | Y4: Editable parameters (key=value) | Z4: Input validations | AA4: Exception record output | AB4: Worked dataset & result | AC4: Positive test case(s) | AD4: Negative / edge test case(s) | AE4: Common real-world causes | AF4: Software action / remedy | AG4: Pseudocode | AH4: Sources (title | URL | ref, one per line) | AI4: Notes, verification, conflicts
A5: rule_id | B5: rule_type | C5: category | D5: name | E5: verification_status | F5: purpose | G5: doc_a | H5: doc_b | I5: doc_c | J5: period_basis | K5: legal_provision | L5: applicability | M5: effective_from | N5: effective_to | O5: prerequisites | P5: match_keys | Q5: key_normalisation | R5: aggregation | S5: compare_fields | T5: tolerance | U5: formula | V5: logic_steps | W5: mismatch_categories | X5: severity_by_category | Y5: params | Z5: validations | AA5: expected_output | AB5: sample_data_and_result | AC5: test_positive | AD5: test_negative | AE5: common_discrepancies | AF5: software_action | AG5: pseudocode | AH5: sources | AI5: notes
A6: RC-GST-001 | B6: reconciliation_rule | C6: GST – Outward supplies – Books vs return | D6: Sales register vs GSTR-1/IFF/GSTR-1A – B2B invoices (Table 4A/4B/4C, 6B, 6C) | E6: Partially verified | F6: Make sure every B2B tax invoice in the books is reported in GSTR-1, IFF or GSTR-1A for the right period, with the right GSTIN, value and tax heads, and that nothing is reported in the return that is not in the books. | G6: SALES_REG | H6: GSTR1 | I6: GSTR1A | J6: tax period (month); quarter for QRMP (IFF months 1-2 + GSTR-1 quarter) | K6: CGST Act s.37(1) (outward supply details), s.37(3) (rectification, time limit 30 Nov following FY or annual return, whichever earlier), s.37(5) (3-year bar, FA 2023 w.e.f. 01.10.2023 – N.28/2023-CT); CGST Rule 59 (GSTR-1, IFF); GSTR-1A inserted by N.12/2024-CT dt 10.07.2024 (optional, once per period, from July 2024 tax period); s.31 & Rule 46 (tax invoice contents, serial no. up to 16 characters unique for FY). | L6: All regular taxpayers filing GSTR-1 (monthly) or IFF + quarterly GSTR-1 (QRMP). B2B = supplies to GSTIN/UIN holders including SEZ (6B) and deemed exports (6C). | M6: 2017-07-01 | O6: Sales register for the period with document type, invoice no., date, buyer GSTIN, POS, taxable value, rate, IGST/CGST/SGST/cess, reverse-charge flag, SEZ/deemed-export flag. GSTR-1 JSON/Excel (b2b, sez, de sections) downloaded after filing; GSTR-1A JSON if filed; IFF JSON for QRMP months. | P6: SALES_REG.party_gstin = GSTR1.b2b_recipient_gstin; SALES_REG.voucher_no = GSTR1.b2b_invoice_no; SALES_REG.fy = fy(GSTR1.b2b_invoice_date) | Q6: Implementation choice: (1) Invoice/document number – uppercase, trim, collapse internal spaces, remove characters other than A-Z 0-9 '/' '-'; exact pass on this form. (2) Fuzzy pass key = strip '/', '-', spaces; strip leading zeros of each numeric run; strip common FY tokens (e.g. '2025-26', '25-26', '2526', 'FY26') – only if the remainder is still >= 3 characters. Law (Rule 46(b)) allows up to 16 characters, unique per FY. (3) GSTIN – uppercase, trim, validate 15-char pattern ^[0-9]{2}[A-Z]{5}[0-9]{4}[A-Z][1-9A-Z]Z[0-9A-Z]$ and check digit (see GST-001). (4) Dates – parse DD-MM-YYYY, DD/MM/YYYY, DD-MON-YY, YYYY-MM-DD, Excel serials into ISO date. (5) Amounts – Decimal, 2 dp, negative for credit notes only after doc-type mapping. Implementation choice: if the same normalised invoice no. appears for 2 buyers, match only with GSTIN; if buyer GSTIN differs but invoice no. + date + value agree, classify GSTIN_DIFF instead of two separate MISSING records. | R6: Invoice level. Sales register is item-wise – sum taxable value and each tax head per (buyer_gstin, invoice_no, rate) then per invoice. GSTR-1 b2b.inv.itms is rate-wise – sum to invoice. Merge GSTR-1 + GSTR-1A + IFF for the period; GSTR-1A record replaces the GSTR-1 record with the same key. | S6: SALES_REG.voucher_date vs GSTR1.b2b_invoice_date; SALES_REG.invoice_value vs GSTR1.b2b_invoice_value; SALES_REG.taxable_value vs GSTR1.b2b_taxable_value; SALES_REG.igst vs GSTR1.b2b_igst; SALES_REG.cgst vs GSTR1.b2b_cgst; SALES_REG.sgst_utgst vs GSTR1.b2b_sgst; SALES_REG.cess vs GSTR1.b2b_cess; SALES_REG.place_of_supply vs GSTR1.b2b_pos; SALES_REG.reverse_charge vs GSTR1.b2b_reverse_charge; SALES_REG.gst_rate vs GSTR1.b2b_rate | T6: Implementation choice (law prescribes none): Rs 1 per tax head per invoice and Rs 1 on taxable value (rounding, s.170 rounds only the final tax payable); date – exact; POS/rate/RCM flag – exact. CA may raise to Rs 10. | U6: diff_head = SALES_REG.head − GSTR1.head for head in (txval, iamt, camt, samt, csamt); value_mismatch if any |diff_head| > value_tolerance_inr; period_shift if month(SALES_REG.invoice_date) != GSTR1.return_period | V6: 1. Load sales register; keep doc_type in (Tax Invoice, SEZ with/without payment, Deemed export) and buyer GSTIN present. 2. Validate keys (see validations). 3. Aggregate both sides to invoice level. 4. Overlay GSTR-1A over GSTR-1 for the same period. 5. Pass 1 exact match on (GSTIN, normalised invoice no., FY). 6. Pass 2 fuzzy invoice no. within same GSTIN and FY, confirm with |value diff| <= tolerance and date diff <= date_window_days. 7. Pass 3 for unmatched: same invoice no.+date+value with different GSTIN -> GSTIN_DIFF. 8. For matched pairs compare fields; assign the most severe category per invoice and store one exception per differing field. 9. Search unmatched books invoices in GSTR-1 of other periods of the same FY and next FY up to the s.37(3) date -> PERIOD_SHIFT; else MISSING_IN_GSTR1. 10. Unmatched GSTR-1 records -> MISSING_IN_BOOKS. 11. Detect duplicates in each side (same key twice) -> DUPLICATE. 12. Totals: Σ books vs Σ GSTR-1 for the period must equal Σ(matched diff) + Σ(missing) – control check. | W6: MATCHED: all fields within tolerance; VALUE_DIFF: taxable value or invoice value differs; TAX_DIFF: one or more tax heads differ; HEAD_DIFF: IGST reported instead of CGST+SGST or vice versa (see RC-GST-034); RATE_DIFF: rate differs; POS_DIFF: place of supply differs; DATE_DIFF: date differs but same period; PERIOD_SHIFT: reported in another tax period; GSTIN_DIFF: same invoice reported against another GSTIN; INVNO_FORMAT: matched only on fuzzy key; RCM_FLAG_DIFF: reverse-charge flag differs; MISSING_IN_GSTR1: in books, not in any GSTR-1/1A/IFF; MISSING_IN_BOOKS: in GSTR-1 but not in books; DUPLICATE: same key appears more than once on one side; B2B_REPORTED_AS_B2C: books has GSTIN but return has it in B2CS/B2CL | X6: MATCHED=Low; INVNO_FORMAT=Low; DATE_DIFF=Low; VALUE_DIFF=High; TAX_DIFF=High; HEAD_DIFF=High; RATE_DIFF=High; POS_DIFF=High; PERIOD_SHIFT=Medium; GSTIN_DIFF=Critical; RCM_FLAG_DIFF=High; MISSING_IN_GSTR1=Critical; MISSING_IN_BOOKS=High; DUPLICATE=High; B2B_REPORTED_AS_B2C=Critical | Y6: value_tolerance_inr=1; tax_tolerance_inr=1; date_window_days=0; fuzzy_match=true; search_other_periods=true; include_gstr1a=true | Z6: Buyer GSTIN pattern + check digit; invoice no. <= 16 chars (Rule 46(b)) – warn if longer; invoice date within the period or earlier; taxable value >= 0 for invoices; IGST > 0 implies CGST=SGST=0 and vice versa; GSTR-1 file GSTIN and period equal the client's GSTIN and period being reconciled; file is the filed version (status 'Filed') not a draft. | AA6: exception_id; rule_id; client_id; gstin; period; doc_a_ref (file+row); doc_b_ref; match_key; match_pass (exact/fuzzy); category; severity; field_name; value_a; value_b; difference; tolerance_applied; suggested_action; legal_reference; status (Open/Under review/Resolved/Accepted-as-is); reviewer; review_comment; created_at; buyer_gstin; invoice_no_books; invoice_no_return; return_period_found; gstr1_or_1a_source | AB6: Books: (A) 27AAACX1234A1Z5 INV/001 05-08-2025 txval 1,00,000 CGST 9,000 SGST 9,000; (B) 29BBBCY5678B1Z2 INV/002 10-08-2025 txval 50,000 IGST 9,000; (C) 27AAACX1234A1Z5 INV/003 20-08-2025 txval 20,000 CGST 1,800 SGST 1,800; (D) 24CCCDZ9012C1Z8 INV/004 25-08-2025 txval 10,000 IGST 1,800. GSTR-1 Aug-2025: INV001 (27AAACX...) txval 1,00,000 C 9,000 S 9,000; INV/002 txval 50,000 IGST 8,100 (rate 18% vs 9,000 ⇒ 9,000−8,100 = 900); INV/004 not in Aug but in Sept GSTR-1. INV/005 27AAACX... txval 5,000 in GSTR-1 only. Result: A MATCHED (INVNO_FORMAT – 'INV/001' vs 'INV001' fuzzy); B TAX_DIFF IGST diff 900 > 1; C MISSING_IN_GSTR1 (tax 3,600 under-reported); D PERIOD_SHIFT (Aug -> Sep); INV/005 MISSING_IN_BOOKS (txval 5,000). | AC6: Books INV-10 txval 10,000.40 CGST 900.04 SGST 900.04 vs GSTR-1 INV-10 10,000 / 900 / 900 -> MATCHED (diffs 0.40, 0.04 within Rs 1). | AD6: Books invoice with buyer GSTIN '27AAACX1234A1Z0' (bad check digit) -> validation error, not matched; GSTR-1 file for another GSTIN -> rule aborts with INPUT_ERROR; books invoice no. 'INV-0007' and GSTR-1 '7' – fuzzy key '7' equals '7' but if value differs by Rs 5,000 -> not paired, both MISSING. | AE6: Invoice posted in books in a later month (back-dated); invoice cancelled in books but reported in GSTR-1; e-invoice auto-populated then edited; amendments filed in later GSTR-1 (B2BA) not overlaid; prefix/FY suffix differences between ERP and GSTR-1; buyer GSTIN changed (new registration/merger); SEZ invoices reported in B2B 4A instead of 6B; RCM supplies (4B) missed; IFF months not loaded for QRMP. | AF6: MISSING_IN_GSTR1 / TAX_DIFF (under-reported) for current period: report in GSTR-1A before filing GSTR-3B or in next GSTR-1 (B2B or B2BA) within s.37(3) time limit; if GSTR-3B already filed, pay differential via next 3B/DRC-03 with s.50 interest. MISSING_IN_BOOKS: check cancelled/duplicate invoice; amend via B2BA (reduce to nil) or issue credit note. GSTIN_DIFF: amend in B2BA – recipient's ITC is affected (Critical). Store with reviewer sign-off. | AG6: def rc_gst_001(books, g1, g1a, iff, p): ret = overlay(concat(g1, iff), g1a, key=['ctin','inum_n']) b = agg(books[books.doc_type.isin(B2B_TYPES)], ['buyer_gstin','inv_n','fy'], SUM_HEADS) r = agg(ret, ['ctin','inum_n','fy'], SUM_HEADS) pairs, ub, ur = match_exact(b, r, [('buyer_gstin','ctin'),('inv_n','inum_n'),('fy','fy')]) if p.fuzzy_match: pairs2, ub, ur = match_fuzzy(ub, ur, gstin_equal=True, key='inv_fz', confirm=lambda x,y: abs(x.txval-y.txval)<=p.value_tolerance_inr) pairs += tag(pairs2, 'INVNO_FORMAT') pairs3, ub, ur = match_on(ub, ur, ['inv_n','idt','txval']) # GSTIN_DIFF out = [] for a, x in pairs: for h in HEADS: d = a[h] - x[h] if abs(d) > p.tax_tolerance_inr: out.append(exc('TAX_DIFF' if h!='txval' else 'VALUE_DIFF', a, x, h, d)) for f in ('pos','rt','rchrg'): if a[f] != x[f]: out.append(exc(f.upper()+'_DIFF', a, x, f)) for a, x in pairs3: out.append(exc('GSTIN_DIFF', a, x)) for a in ub: hit = find_in_other_periods(a, all_returns_same_fy_and_next) out.append(exc('PERIOD_SHIFT' if hit else 'MISSING_IN_GSTR1', a, hit)) out += [exc('MISSING_IN_BOOKS', None, x) for x in ur] out += duplicates(b, 'DUPLICATE') + duplicates(r, 'DUPLICATE') return out | AH6: TaxGuru – Advisory on Form GSTR-1A | https://taxguru.in/goods-and-service-tax/advisory-form-gstr-1a.html | N.12/2024-CT; from July 2024 period; once per period; window till 3B filed; auto-populates 3B ClearTax – GST return filing rule changes from July 2025 | https://cleartax.in/s/gst-return-filing-rule-changes-from-july-2025 | GSTN advisories 07.06.2025 (3B Table 3 lock), 3-year bar Taxmann – returns cannot be filed after 3 years | https://www.taxmann.com/post/blog/gstn-warns-pending-gst-returns-cannot-be-filed-after-3-years | N.28/2023-CT; advisory 25.09.2025 | AI6: Matching keys, normalisation, tolerances and categories are implementation design. GSTR-1A start (July 2024 period, N.12/2024-CT) verified via TaxGuru reproduction of GSTN advisory. Field names follow the GSTR-1 offline JSON (ctin, inum, idt, val, pos, rchrg, itms.itm_det.txval/rt/iamt/camt/samt/csamt) as commonly published – confirm against the current GSTN API schema version. s.37(3) 30-Nov limit taken from GST-007 (statute knowledge, not re-opened).
A7: RC-GST-002 | B7: reconciliation_rule | C7: GST – Outward supplies – Books vs return | D7: Sales register vs GSTR-1 – B2C Large invoices (Table 5) | E7: Partially verified | F7: Check inter-state supplies to unregistered persons above the invoice-value threshold are reported invoice-wise in Table 5 (B2CL) with the correct POS and IGST, and are not lumped into B2CS. | G7: SALES_REG | H7: GSTR1 | J7: tax period (month) / quarter for QRMP | K7: CGST Act s.37; Rule 59(4) (invoice-wise details of inter-State supplies to unregistered persons above threshold); threshold reduced from Rs 2.5 lakh to Rs 1 lakh by N.12/2024-CT dt 10.07.2024 (GSTN advisory: portal change under development; till then continue reporting > Rs 2.5 lakh); IGST Act s.7 (inter-state), s.10 (POS goods). | L7: Suppliers making inter-state B2C supplies with invoice value above the threshold. | M7: 2024-07-10 | O7: Sales register with buyer GSTIN blank, POS state code, invoice value (incl. tax), IGST; GSTR-1 b2cl section (inum, idt, val, pos, itms). | P7: SALES_REG.voucher_no = GSTR1.b2cl_invoice_no; SALES_REG.place_of_supply = GSTR1.b2cl_pos | Q7: Implementation choice: (1) Invoice/document number – uppercase, trim, collapse internal spaces, remove characters other than A-Z 0-9 '/' '-'; exact pass on this form. (2) Fuzzy pass key = strip '/', '-', spaces; strip leading zeros of each numeric run; strip common FY tokens (e.g. '2025-26', '25-26', '2526', 'FY26') – only if the remainder is still >= 3 characters. Law (Rule 46(b)) allows up to 16 characters, unique per FY. (3) GSTIN – uppercase, trim, validate 15-char pattern ^[0-9]{2}[A-Z]{5}[0-9]{4}[A-Z][1-9A-Z]Z[0-9A-Z]$ and check digit (see GST-001). (4) Dates – parse DD-MM-YYYY, DD/MM/YYYY, DD-MON-YY, YYYY-MM-DD, Excel serials into ISO date. (5) Amounts – Decimal, 2 dp, negative for credit notes only after doc-type mapping. POS normalised to 2-digit state code (e.g. '29-Karnataka' -> '29'). | R7: Invoice level (sum items). Threshold test on invoice value including tax (Rule 59 refers to invoice value). | S7: SALES_REG.invoice_value vs GSTR1.b2cl_invoice_value; SALES_REG.taxable_value vs GSTR1.b2cl_taxable_value; SALES_REG.igst vs GSTR1.b2cl_igst; SALES_REG.place_of_supply vs GSTR1.b2cl_pos; SALES_REG.voucher_date vs GSTR1.b2cl_invoice_date | T7: Rs 1 per head (implementation choice); threshold comparison exact (strictly greater than threshold). | U7: b2cl_candidate = (buyer_gstin is blank) and (supplier_state != pos) and (invoice_value > b2cl_threshold_inr); expected_section = 'B2CL' if b2cl_candidate else 'B2CS' | V7: 1. Filter books: unregistered buyer, inter-state (POS != supplier state), not export. 2. Flag b2cl_candidate using threshold param (default Rs 1,00,000; switch to 2,50,000 if the CA confirms the portal still uses the old limit for the period). 3. Match candidates to GSTR-1 b2cl by normalised invoice no. 4. Compare fields. 5. Unmatched candidates: check if the value is included in B2CS for the same POS/rate (RC-GST-003) -> REPORTED_IN_B2CS; else MISSING_IN_GSTR1. 6. GSTR-1 b2cl records below threshold or intra-state -> WRONG_SECTION. 7. GSTR-1 b2cl records not in books -> MISSING_IN_BOOKS. | W7: MATCHED: agrees; VALUE_DIFF: value differs; TAX_DIFF: IGST differs; POS_DIFF: POS differs; REPORTED_IN_B2CS: candidate reported in B2CS summary instead of Table 5; WRONG_SECTION: below threshold or intra-state in B2CL; MISSING_IN_GSTR1: not reported anywhere; MISSING_IN_BOOKS: in GSTR-1 only | X7: MATCHED=Low; VALUE_DIFF=High; TAX_DIFF=High; POS_DIFF=Critical; REPORTED_IN_B2CS=Medium; WRONG_SECTION=Low; MISSING_IN_GSTR1=Critical; MISSING_IN_BOOKS=High | Y7: b2cl_threshold_inr=100000; value_tolerance_inr=1; threshold_basis=invoice_value_incl_tax | Z7: POS present and valid state code (01-38, 97); supplier state code from client GSTIN; buyer GSTIN blank (if present, route to RC-GST-001). | AA7: exception_id; rule_id; client_id; gstin; period; doc_a_ref (file+row); doc_b_ref; match_key; match_pass (exact/fuzzy); category; severity; field_name; value_a; value_b; difference; tolerance_applied; suggested_action; legal_reference; status (Open/Under review/Resolved/Accepted-as-is); reviewer; review_comment; created_at; pos; invoice_value; threshold_used; section_found | AB7: Supplier state 27. Books: (A) INV-50 POS 29 value 1,18,000 (txval 1,00,000 IGST 18,000); (B) INV-51 POS 33 value 59,000; (C) INV-52 POS 27 value 2,36,000 (intra-state). GSTR-1 b2cl: none; b2cs POS 29 18% txval 1,50,000. Threshold 1,00,000: A 1,18,000 > 1,00,000 and inter-state -> candidate; found inside B2CS POS 29 -> REPORTED_IN_B2CS. B 59,000 < 1,00,000 -> not candidate (B2CS). C intra-state -> not candidate. | AC7: Invoice POS 07, supplier 27, value 3,00,000, in GSTR-1 b2cl with same values -> MATCHED. | AD7: Invoice value exactly 1,00,000 -> not > threshold -> B2CS, no exception. Invoice with POS '96' (foreign) -> export, routed to RC-GST-004. | AE7: ERP still uses Rs 2.5 lakh threshold; POS taken as billing address instead of delivery address (s.10(1)(a)); invoices to unregistered SEZ/foreign treated as B2CL; B2CL reported in B2CS to save effort. | AF7: REPORTED_IN_B2CS: amend B2CS (Table 10) and report in Table 5/9A in next GSTR-1 – tax unchanged, disclosure only. POS_DIFF: correct POS via amendment; if wrong state got tax, tax may have to be paid to the correct state (IGST s.19/CGST s.77 refund route) – CA review. | AG7: def rc_gst_002(books, g1, p): sup_state = p.client_gstin[:2] c = books[(books.buyer_gstin=='') & (books.pos!=sup_state) & (books.pos!='96')] c = agg(c, ['inv_n','pos'], SUM_HEADS) c['cand'] = c.invoice_value > p.b2cl_threshold_inr pairs, ub, ur = match_exact(c[c.cand], g1.b2cl, [('inv_n','inum_n')]) out = compare(pairs, ['val','txval','iamt','pos'], p.value_tolerance_inr) for a in ub: out.append(exc('REPORTED_IN_B2CS' if in_b2cs(g1, a.pos, a.rate) else 'MISSING_IN_GSTR1', a)) for x in g1.b2cl: if x.val <= p.b2cl_threshold_inr or x.pos == sup_state: out.append(exc('WRONG_SECTION', None, x)) out += [exc('MISSING_IN_BOOKS', None, x) for x in ur if not any(i.inum_n==x.inum_n for i in books_all)] return out | AH7: TaxHeal – GSTN advisory on reporting supplies to unregistered dealers in GSTR-1/GSTR-5 | https://www.taxheal.com/?p=96273 | N.12/2024-CT dt 10.07.2024: invoice-wise threshold for inter-state B2C reduced Rs 2.5 lakh -> Rs 1 lakh; Table 5 | AI7: N.12/2024-CT reduction to Rs 1 lakh verified via TaxHeal reproduction of GSTN advisory; the advisory said portal changes were under development and asked taxpayers to continue with Rs 2.5 lakh till then – date from which the portal enforces Rs 1 lakh not confirmed, hence the threshold is a CA-editable param. Whether the threshold is on invoice value incl. tax (as in old Table 5 heading) should be confirmed by CA.
A8: RC-GST-003 | B8: reconciliation_rule | C8: GST – Outward supplies – Books vs return | D8: Sales register vs GSTR-1 – B2C Small summary (Table 7) by POS and rate | E8: Unverified – needs CA review | F8: Reconcile consolidated B2C (other than B2CL) supplies by place of supply, rate and type (intra/inter), including ECO-routed supplies. | G8: SALES_REG | H8: GSTR1 | J8: tax period (month) / quarter for QRMP | K8: CGST Act s.37; Rule 59(4)(b) (consolidated details of intra-state and inter-state B2C supplies by rate and state); Table 10 for amendments. | L8: All suppliers with B2C supplies (intra-state any value; inter-state up to B2CL threshold). | M8: 2017-07-01 | O8: Sales register B2C lines with POS and rate; credit notes to unregistered persons (domestic) are netted in B2CS per GSTN practice; GSTR-1 b2cs section (sply_ty INTRA/INTER, pos, rt, typ OE/E, etin). | P8: SALES_REG.place_of_supply = GSTR1.b2cs_pos; SALES_REG.gst_rate = GSTR1.b2cs_rate; SALES_REG.supply_type = GSTR1.b2cs_supply_type; SALES_REG.ecom_gstin = GSTR1.b2cs_ecom_gstin | Q8: POS to 2-digit code; rate to decimal with 2 dp (e.g. '18%' -> 18.00); supply_type derived (POS == supplier state -> INTRA). ECO GSTIN uppercase or blank. Implementation choice. | R8: Sum taxable value and each tax head by (pos, rate, supply_type, etin) for B2C invoices not in B2CL, net of domestic B2C credit notes and Table 10 amendments of the period. | S8: SALES_REG.Σ taxable_value by (pos, gst_rate, supply_type, ecom_gstin) for B2CS rows vs GSTR1.b2cs_taxable_value; SALES_REG.sum_igst vs GSTR1.b2cs_igst; SALES_REG.sum_cgst vs GSTR1.b2cs_cgst; SALES_REG.sum_sgst vs GSTR1.b2cs_sgst; SALES_REG.sum_cess vs GSTR1.b2cs_cess | T8: Rs 10 per (pos, rate) bucket – implementation choice (B2C lines accumulate rounding). | U8: diff = Σ_books(bucket) − Σ_gstr1(bucket); ratio = diff / Σ_books(bucket) | V8: 1. Exclude B2CL candidates (RC-GST-002 output). 2. Subtract domestic credit notes to unregistered persons in the bucket. 3. Group both sides. 4. Full outer join on bucket key. 5. Compare; buckets only on one side -> MISSING. 6. Also compare grand totals across all buckets – if totals agree but buckets differ -> RATE_OR_POS_SHIFT. | W8: MATCHED: bucket agrees; VALUE_DIFF: taxable differs; TAX_DIFF: tax differs; MISSING_IN_GSTR1: bucket in books only; MISSING_IN_BOOKS: bucket in return only; RATE_OR_POS_SHIFT: totals agree but distribution across POS/rate differs | X8: MATCHED=Low; VALUE_DIFF=High; TAX_DIFF=High; MISSING_IN_GSTR1=Critical; MISSING_IN_BOOKS=Medium; RATE_OR_POS_SHIFT=Medium | Y8: bucket_tolerance_inr=10; net_b2c_credit_notes=true | Z8: Every B2C line has POS and rate; rate in allowed list from rate master; INTRA buckets have CGST=SGST and IGST=0. | AA8: exception_id; rule_id; client_id; gstin; period; doc_a_ref (file+row); doc_b_ref; match_key; match_pass (exact/fuzzy); category; severity; field_name; value_a; value_b; difference; tolerance_applied; suggested_action; legal_reference; status (Open/Under review/Resolved/Accepted-as-is); reviewer; review_comment; created_at; pos; rate; supply_type; etin | AB8: Supplier state 27. Books B2C: POS 27 @18% txval 4,00,000 (C 36,000 S 36,000); POS 27 @5% txval 1,00,000 (C 2,500 S 2,500); POS 29 @18% txval 60,000 (IGST 10,800). GSTR-1 B2CS: 27/18 txval 4,00,000; 27/5 txval 90,000; 29/18 nil; 24/18 txval 60,000 IGST 10,800. Result: 27/18 MATCHED; 27/5 VALUE_DIFF 10,000 (tax 500); 29/18 MISSING_IN_GSTR1 and 24/18 MISSING_IN_BOOKS -> totals equal for inter-state 18% -> RATE_OR_POS_SHIFT (POS wrongly reported 24 instead of 29). | AC8: Books 27/18 txval 1,00,000.30; GSTR-1 1,00,000 -> MATCHED. | AD8: Books line with rate 12% dated 30-09-2025 for an item moved to 5% from 22-09-2025 -> also raises RC-GST-033 rate exception; here only bucket comparison. | AE8: POS wrong for online sales (billing vs shipping address); ECO supplies reported without ETIN or vice versa; credit notes to unregistered not netted; cash sales posted late. | AF8: Report differences via Table 10 (B2CS amendment) in next GSTR-1 within s.37(3) limit; short-reported tax to be paid in GSTR-3B/DRC-03 with interest. | AG8: def rc_gst_003(books, g1, b2cl_ids, p): b = books[(books.buyer_gstin=='') & (~books.inv_n.isin(b2cl_ids)) & (books.pos!='96')] b = b.assign(sply_ty=np.where(b.pos==p.client_gstin[:2],'INTRA','INTER')) kb = agg(b, ['pos','rate','sply_ty','etin'], SUM_HEADS) kr = agg(g1.b2cs, ['pos','rt','sply_ty','etin'], SUM_HEADS) j = outer_join(kb, kr) out = [] for row in j: if row.only_left: out.append(exc('MISSING_IN_GSTR1', row)) elif row.only_right: out.append(exc('MISSING_IN_BOOKS', row)) else: for h in HEADS: if abs(row[h+'_a']-row[h+'_b']) > p.bucket_tolerance_inr: out.append(exc('TAX_DIFF' if h!='txval' else 'VALUE_DIFF', row, field=h)) if abs(kb.txval.sum()-kr.txval.sum()) <= p.bucket_tolerance_inr and any(o.cat.startswith('MISSING') for o in out): out.append(exc('RATE_OR_POS_SHIFT', None)) return out | AH8: TaxHeal – GSTN advisory on reporting supplies to unregistered dealers in GSTR-1/GSTR-5 | https://www.taxheal.com/?p=96273 | N.12/2024-CT dt 10.07.2024: invoice-wise threshold for inter-state B2C reduced Rs 2.5 lakh -> Rs 1 lakh; Table 5 | AI8: Implementation design. GSTR-1 b2cs JSON fields (sply_ty, pos, rt, typ, etin, txval, iamt, camt, samt, csamt) are from the published offline-tool schema as commonly known – not opened in this session. Treatment of domestic B2C credit notes (netting in Table 7 vs CDNUR) is GSTN portal practice – CA to confirm.
A9: RC-GST-004 | B9: reconciliation_rule | C9: GST – Outward supplies – Zero-rated | D9: Sales register / shipping bills vs GSTR-1 – exports (Table 6A) and SEZ/deemed exports (6B/6C) | E9: Unverified – needs CA review | F9: Confirm export invoices are reported with correct export type (WPAY/WOPAY), shipping bill details, port code and IGST, so that IGST refund (WPAY) is not held up and LUT exports are not taxed. | G9: SALES_REG | H9: GSTR1 | I9: GSTR3B | J9: tax period (month) | K9: IGST Act s.16 (zero-rated supply; export under LUT or with payment of IGST and refund); CGST Rule 96 (refund of IGST paid on export – GSTR-1 Table 6A + shipping bill treated as refund application) and Rule 96A (LUT); CGST s.37; GSTR-3B Table 3.1(b). | L9: Exporters of goods/services and suppliers to SEZ units/developers; deemed exports. | M9: 2017-07-01 | O9: Sales register with export flag, export type, shipping bill no./date, port code, currency value, INR value, IGST; GSTR-1 exp section (exp_typ, inum, idt, val, sbpcode, sbnum, sbdt, itms); GSTR-3B 3.1(b). | P9: SALES_REG.voucher_no = GSTR1.exp_invoice_no; SALES_REG.fy = fy(GSTR1.exp_invoice_date) | Q9: Implementation choice: (1) Invoice/document number – uppercase, trim, collapse internal spaces, remove characters other than A-Z 0-9 '/' '-'; exact pass on this form. (2) Fuzzy pass key = strip '/', '-', spaces; strip leading zeros of each numeric run; strip common FY tokens (e.g. '2025-26', '25-26', '2526', 'FY26') – only if the remainder is still >= 3 characters. Law (Rule 46(b)) allows up to 16 characters, unique per FY. (3) GSTIN – uppercase, trim, validate 15-char pattern ^[0-9]{2}[A-Z]{5}[0-9]{4}[A-Z][1-9A-Z]Z[0-9A-Z]$ and check digit (see GST-001). (4) Dates – parse DD-MM-YYYY, DD/MM/YYYY, DD-MON-YY, YYYY-MM-DD, Excel serials into ISO date. (5) Amounts – Decimal, 2 dp, negative for credit notes only after doc-type mapping. Shipping bill no. – digits only; port code – uppercase 6 chars (e.g. INNSA1). | R9: Invoice level for 6A/6B/6C; period total for 3.1(b). | S9: SALES_REG.export_type vs GSTR1.exp_type; SALES_REG.taxable_value vs GSTR1.exp_taxable_value (6A) + b2b_taxable_value where b2b_invoice_type in SEWP/SEWOP/DE (6B/6C); SALES_REG.igst vs GSTR1.exp_igst (6A) + b2b_igst where b2b_invoice_type in SEWP/DE; SALES_REG.shipping_bill_no vs GSTR1.exp_shipping_bill_no; SALES_REG.shipping_bill_date vs GSTR1.exp_shipping_bill_date; SALES_REG.port_code vs GSTR1.exp_port_code; Σ(GSTR1 6A+6B+6C txval) vs GSTR3B.3_1_b.txval; Σ(6A+6B+6C iamt) vs GSTR3B.3_1_b.iamt | T9: Rs 1 per head per invoice; Rs 10 on period totals (implementation choice). Shipping bill fields exact. | U9: period_diff = Σ_gstr1_zero_rated − GSTR3B_3_1_b; wopay_tax_error = export_type=='WOPAY' and igst>0 | V9: 1. Match invoices. 2. Compare fields. 3. WOPAY with IGST > 0 or WPAY with IGST = 0 -> TYPE_TAX_CONFLICT. 4. Goods exports with blank shipping bill in GSTR-1 at filing -> SB_MISSING (may be added via amendment 9A). 5. Totals vs 3.1(b). 6. Service exports: no SB; check realisation is outside this rule. | W9: MATCHED: agrees; VALUE_DIFF: value differs; TAX_DIFF: IGST differs; TYPE_TAX_CONFLICT: export type inconsistent with IGST; SB_MISSING: shipping bill/port missing for goods; SB_DIFF: SB no./date/port differs; MISSING_IN_GSTR1; MISSING_IN_BOOKS; TOTAL_3B_DIFF: GSTR-1 zero-rated totals differ from 3B 3.1(b) | X9: MATCHED=Low; VALUE_DIFF=High; TAX_DIFF=High; TYPE_TAX_CONFLICT=Critical; SB_MISSING=High; SB_DIFF=High; MISSING_IN_GSTR1=Critical; MISSING_IN_BOOKS=High; TOTAL_3B_DIFF=High | Y9: value_tolerance_inr=1; total_tolerance_inr=10 | Z9: Exchange rate used is present; SB date >= invoice date; port code 6 characters; export type in (WPAY, WOPAY). | AA9: exception_id; rule_id; client_id; gstin; period; doc_a_ref (file+row); doc_b_ref; match_key; match_pass (exact/fuzzy); category; severity; field_name; value_a; value_b; difference; tolerance_applied; suggested_action; legal_reference; status (Open/Under review/Resolved/Accepted-as-is); reviewer; review_comment; created_at; export_type; sb_no; sb_date; port_code | AB9: Books: E-1 WPAY txval 5,00,000 IGST 90,000 SB 1234567 dt 12-08-2025 INNSA1; E-2 WOPAY txval 3,00,000 IGST 0 SB 1234570; E-3 WOPAY txval 2,00,000 (services). GSTR-1 6A: E-1 SB 1234567 but port INMAA1 -> SB_DIFF; E-2 IGST 54,000 -> TYPE_TAX_CONFLICT; E-3 matched. GSTR-3B 3.1(b) txval 10,00,000 = 5+3+2 lakh -> OK; IGST 1,44,000 vs GSTR-1 1,44,000 OK. | AC9: WPAY invoice with all SB fields equal -> MATCHED. | AD9: Goods export under WOPAY with SB filled later in 9A amendment -> after overlay of amendments, MATCHED (no SB_MISSING). | AE9: SB number entered after GSTR-1 filing; port code mismatch with ICEGATE causing refund errors; INR value at different exchange rate in books vs SB; deemed exports reported as B2B. | AF9: SB_DIFF / SB_MISSING for WPAY: amend Table 9A promptly – IGST refund under Rule 96 depends on matching with ICEGATE. TYPE_TAX_CONFLICT: CA review; LUT validity for the FY must be checked. | AG9: def rc_gst_004(books, g1, g3b, p): exp = overlay(g1.exp, g1.exp_amend, key=['inum_n']) pairs, ub, ur = match_exact(agg(books[books.is_export], ['inv_n','fy']), exp, [('inv_n','inum_n'),('fy','fy')]) out = compare(pairs, ['txval','iamt','sbnum','sbdt','sbpcode','exp_typ'], p.value_tolerance_inr) for a, x in pairs: if (x.exp_typ=='WOPAY' and x.iamt>0) or (x.exp_typ=='WPAY' and x.iamt==0): out.append(exc('TYPE_TAX_CONFLICT', a, x)) if a.is_goods and not x.sbnum: out.append(exc('SB_MISSING', a, x)) tot = sum_heads(exp) + sum_heads(g1.sez) + sum_heads(g1.de) if abs(tot.txval - g3b.t3_1_b.txval) > p.total_tolerance_inr: out.append(exc('TOTAL_3B_DIFF', tot, g3b.t3_1_b)) return out + missing(ub, ur) | AH9: GSTN advisory – auto-population of e-invoice details into GSTR-1 (ICMAI copy) | https://icmai.in/upload/Taxation/Advisory_auto-population_GSTR-1.pdf | B2B 4A/4B, EXP 6A, CDNR 9B, CDNUR(exports) auto-populated; edits blank the IRN; cancelled IRN deleted | AI9: Legal provisions (IGST s.16, Rule 96/96A) from statute knowledge – not re-opened in this session. Export invoices are auto-populated into 6A from e-invoices (GSTN advisory) – then SB details are added by the taxpayer.
A10: RC-GST-005 | B10: reconciliation_rule | C10: GST – Outward supplies – Credit/debit notes | D10: Books credit/debit notes vs GSTR-1 CDNR/CDNUR (Table 9B) | E10: Partially verified | F10: Check every credit and debit note issued in books is reported in GSTR-1 with correct GSTIN, note type, value and tax, within the s.34 time limit. | G10: SALES_REG | H10: GSTR1 | I10: GSTR1A | J10: tax period (month); time limit by FY of original supply | K10: CGST Act s.34(1)-(4) (credit/debit notes; s.34(2): CN to be declared not later than 30 November following end of FY or date of annual return, whichever earlier; proviso as amended by FA 2025 w.e.f. 01.10.2025 – no reduction of output tax unless recipient reverses ITC); s.37; Rule 53 (contents); GSTR-1 Table 9B. | L10: Suppliers issuing financial-with-GST credit notes or debit notes. | M10: 2017-07-01 | O10: Books CN/DN list with note no., date, type, original invoice no./date (optional in law but useful), party GSTIN, values; GSTR-1 cdnr (ctin, nt_num, nt_dt, ntty C/D, val, pos, itms) and cdnur (typ B2CL/EXPWP/EXPWOP). | P10: SALES_REG.party_gstin = GSTR1.cdnr_recipient_gstin; SALES_REG.voucher_no = GSTR1.cdnr_note_no; SALES_REG.note_type = GSTR1.cdnr_note_type | Q10: Implementation choice: (1) Invoice/document number – uppercase, trim, collapse internal spaces, remove characters other than A-Z 0-9 '/' '-'; exact pass on this form. (2) Fuzzy pass key = strip '/', '-', spaces; strip leading zeros of each numeric run; strip common FY tokens (e.g. '2025-26', '25-26', '2526', 'FY26') – only if the remainder is still >= 3 characters. Law (Rule 46(b)) allows up to 16 characters, unique per FY. (3) GSTIN – uppercase, trim, validate 15-char pattern ^[0-9]{2}[A-Z]{5}[0-9]{4}[A-Z][1-9A-Z]Z[0-9A-Z]$ and check digit (see GST-001). (4) Dates – parse DD-MM-YYYY, DD/MM/YYYY, DD-MON-YY, YYYY-MM-DD, Excel serials into ISO date. (5) Amounts – Decimal, 2 dp, negative for credit notes only after doc-type mapping. Note type mapped: Credit Note/CN/Sales Return -> C; Debit Note/DN/Supplementary invoice -> D (implementation choice: supplementary invoices raised as tax invoices go to RC-GST-001). | R10: Note level (sum rate-wise items). | S10: SALES_REG.voucher_date vs GSTR1.cdnr_note_date; SALES_REG.invoice_value vs GSTR1.cdnr_note_value; SALES_REG.taxable_value vs GSTR1.cdnr_taxable_value; SALES_REG.igst vs GSTR1.cdnr_igst; SALES_REG.cgst vs GSTR1.cdnr_cgst; SALES_REG.sgst_utgst vs GSTR1.cdnr_sgst; SALES_REG.place_of_supply vs GSTR1.cdnr_pos | T10: Rs 1 per head (implementation choice). Time limit – exact date (legal). | U10: cn_deadline = min(date(fy_end_year_of_original_supply, 11, 30), gstr9_filing_date); late_cn = note_type=='C' and gstr1_filing_date_of_cn > cn_deadline | V10: 1. Match notes. 2. Compare fields. 3. For CNs determine FY of original supply (from linked invoice; if not linked, ask CA – flag LINK_MISSING). 4. If CN reported after cn_deadline -> CN_TIME_BARRED (tax reduction not permitted). 5. From 01.10.2025: check recipient reversal evidence (IMS status 'Accepted' via supplier dashboard or recipient confirmation) – see RC-GST-029. 6. Unmatched books notes -> MISSING_IN_GSTR1; unmatched return notes -> MISSING_IN_BOOKS. | W10: MATCHED; VALUE_DIFF; TAX_DIFF; TYPE_DIFF: credit vs debit swapped; MISSING_IN_GSTR1; MISSING_IN_BOOKS; CN_TIME_BARRED: CN declared after s.34(2) limit; LINK_MISSING: original invoice not identified; DUPLICATE | X10: MATCHED=Low; VALUE_DIFF=High; TAX_DIFF=High; TYPE_DIFF=Critical; MISSING_IN_GSTR1=High; MISSING_IN_BOOKS=High; CN_TIME_BARRED=Critical; LINK_MISSING=Low; DUPLICATE=High | Y10: value_tolerance_inr=1; gstr9_filing_date=; require_invoice_link=false | Z10: Note date >= original invoice date; CN value <= original invoice value (warn); GSTIN valid. | AA10: exception_id; rule_id; client_id; gstin; period; doc_a_ref (file+row); doc_b_ref; match_key; match_pass (exact/fuzzy); category; severity; field_name; value_a; value_b; difference; tolerance_applied; suggested_action; legal_reference; status (Open/Under review/Resolved/Accepted-as-is); reviewer; review_comment; created_at; note_type; original_invoice_no; original_fy; cn_deadline | AB10: FY 2024-25 supplies. Books: CN-1 27AAACX... dt 15-10-2025 txval 10,000 CGST 900 SGST 900 (orig INV/2024-25/100); CN-2 dt 10-12-2025 txval 5,000 IGST 900 (orig FY 2024-25); DN-1 dt 20-10-2025 txval 2,000. GSTR-1: CN-1 in Oct-2025 matched; CN-2 in Dec-2025 GSTR-1 filed 11-01-2026; GSTR-9 FY24-25 filed 28-11-2025 -> deadline min(30-11-2025, 28-11-2025)=28-11-2025 -> CN_TIME_BARRED; DN-1 not in GSTR-1 -> MISSING_IN_GSTR1 (tax 360 at 18% short). | AC10: CN for FY 2025-26 supply reported in GSTR-1 of Oct-2026 filed 11-11-2026, GSTR-9 not filed -> within 30-11-2026 -> no time-bar exception. | AD10: Commercial credit note without GST (no tax heads) -> excluded from this rule (not a s.34 note). | AE10: Financial credit notes booked with GST but not reported; sales returns booked as negative invoices; CN reported as CDNUR when buyer is registered; time-barred CNs for discounts given after year-end; post-01.10.2025 CNs where recipient did not reverse ITC. | AF10: MISSING_IN_GSTR1 (DN): report in next GSTR-1 and pay tax with interest. CN_TIME_BARRED: reverse the tax reduction (add back liability) – pay via DRC-03 with s.50 interest; commercial adjustment only. TYPE_DIFF: amend in 9C (CDNRA). | AG10: def rc_gst_005(books, g1_all, p): n = agg(books[books.doc_type.isin(['C','D'])], ['party_gstin','note_n','ntty'], SUM_HEADS) r = overlay(g1_all.cdnr, g1_all.cdnra, key=['ctin','nt_num_n']) pairs, ub, ur = match_exact(n, r, [('party_gstin','ctin'),('note_n','nt_num_n')]) out = compare(pairs, ['txval','iamt','camt','samt','ntty','pos'], p.value_tolerance_inr) for a, x in pairs: if a.ntty=='C': if not a.orig_fy: out.append(exc('LINK_MISSING', a, x)); continue dl = min(date(a.orig_fy_end.year, 11, 30), p.gstr9_filing_date or date.max) if x.filing_date > dl: out.append(exc('CN_TIME_BARRED', a, x, deadline=dl)) return out + missing(ub, ur) | AH10: TaxGuru – Finance Act 2025 GST amendments effective 01.10.2025 | https://taxguru.in/goods-and-service-tax/gst-amendments-finance-act-2025-effective-oct-1-2025-notified.html | N.16/2025-CT; s.34(2) proviso; s.38; s.39(1) EY alert – GSTN advisory on IMS changes (23.09.2025) | https://www.ey.com/en_in/technical/alerts-hub/2025/09/gstn-issues-advisory-on-the-changes-introduced-in-the-invoice-management-system | pending CN one period; ITC reversal declaration; from Oct 2025 period | AI10: FA 2025 s.34(2) proviso (recipient reversal) verified via TaxGuru summary (GST-028). 30-November limit from statute knowledge (FA 2022) – not re-opened. FA 2026 amendment to s.15(3)/s.34(1) – commencement unverified (see gst.json open questions).
A11: RC-GST-006 | B11: reconciliation_rule | C11: GST – Outward supplies – Amendments | D11: GSTR-1 amendments (B2BA/B2CLA/EXPA/CDNRA/B2CSA) vs books revisions and s.37(3) time limit | E11: Partially verified | F11: Check that amendments reported in GSTR-1/1A tie to an actual change in the books, and that no amendment is filed after the statutory time limit. | G11: GSTR1 | H11: SALES_REG | J11: FY of original invoice | K11: CGST Act s.37(3) (rectification of errors in GSTR-1: not after 30 November following end of FY or date of annual return, whichever earlier – FA 2022); GSTR-1 Tables 9A, 9C, 10; GSTR-1A (N.12/2024-CT) for same-period corrections; s.37(5) 3-year bar. | L11: All GSTR-1 filers. | M11: 2022-10-01 | O11: All GSTR-1 files of the FY and of the next FY up to the time limit (amendment sections); books audit trail / revision log (Rule 56(1) audit-trail requirement under Companies Act for companies – implementation input). | P11: GSTR1.amend_original_invoice_no = SALES_REG.original_invoice_no; GSTR1.b2b_invoice_no = SALES_REG.voucher_no; GSTR1.b2b_recipient_gstin = SALES_REG.party_gstin | Q11: Implementation choice: (1) Invoice/document number – uppercase, trim, collapse internal spaces, remove characters other than A-Z 0-9 '/' '-'; exact pass on this form. (2) Fuzzy pass key = strip '/', '-', spaces; strip leading zeros of each numeric run; strip common FY tokens (e.g. '2025-26', '25-26', '2526', 'FY26') – only if the remainder is still >= 3 characters. Law (Rule 46(b)) allows up to 16 characters, unique per FY. (3) GSTIN – uppercase, trim, validate 15-char pattern ^[0-9]{2}[A-Z]{5}[0-9]{4}[A-Z][1-9A-Z]Z[0-9A-Z]$ and check digit (see GST-001). (4) Dates – parse DD-MM-YYYY, DD/MM/YYYY, DD-MON-YY, YYYY-MM-DD, Excel serials into ISO date. (5) Amounts – Decimal, 2 dp, negative for credit notes only after doc-type mapping. | R11: Invoice level; latest amendment wins. | S11: GSTR1.b2b_taxable_value vs SALES_REG.taxable_value; GSTR1.b2b_igst/b2b_cgst/b2b_sgst/b2b_cess vs SALES_REG.igst/cgst/sgst_utgst/cess; GSTR1.b2b_recipient_gstin vs SALES_REG.party_gstin; GSTR1.amendment_filing_date vs amendment_deadline | T11: Rs 1 per head (implementation choice); time limit exact (legal). | U11: amendment_deadline = min(date(fy_end_year_of_original, 11, 30), gstr9_filing_date); late = amendment_filing_date > amendment_deadline | V11: 1. Collect amendment records from GSTR-1 of all periods after the original. 2. Link to original by (oinum, oidt, octin). 3. Compare amended values with final books values. 4. Flag late amendments. 5. Flag books revisions (value changed after original GSTR-1 filing) with no amendment -> AMENDMENT_MISSING (covered by RC-GST-001 rerun at FY level). | W11: MATCHED: amendment equals books final; AMEND_VALUE_DIFF: amended value differs from books; AMENDMENT_LATE: filed after s.37(3) limit; AMENDMENT_MISSING: books revised but no amendment; ORIGINAL_NOT_FOUND: amendment refers to an invoice not in original GSTR-1 | X11: MATCHED=Low; AMEND_VALUE_DIFF=High; AMENDMENT_LATE=Critical; AMENDMENT_MISSING=High; ORIGINAL_NOT_FOUND=Medium | Y11: gstr9_filing_date=; value_tolerance_inr=1 | Z11: Amendment original period earlier than amendment period; original invoice exists. | AA11: exception_id; rule_id; client_id; gstin; period; doc_a_ref (file+row); doc_b_ref; match_key; match_pass (exact/fuzzy); category; severity; field_name; value_a; value_b; difference; tolerance_applied; suggested_action; legal_reference; status (Open/Under review/Resolved/Accepted-as-is); reviewer; review_comment; created_at; original_period; amendment_period; amendment_deadline | AB11: FY 2024-25 invoice INV-77 txval 1,00,000 reported Jan-2025. Books revised to 90,000 (CN not issued; invoice revised). GSTR-1 Oct-2025 (filed 11-11-2025) B2BA INV-77 txval 90,000; GSTR-9 FY 2024-25 filed 20-11-2025 -> deadline 20-11-2025; filing 11-11-2025 <= deadline -> MATCHED. Another B2BA for INV-80 filed 11-12-2025 -> AMENDMENT_LATE. | AC11: Amendment within limit and values equal -> MATCHED. | AD11: Amendment only changes POS (no value) -> compare POS; no time-limit issue if filed in time. | AE11: Downward amendments used instead of CN to avoid recipient reversal; late amendments after GSTR-9 filed; GSTIN corrections done after 30 Nov. | AF11: AMENDMENT_LATE: CA review – downward amendment may not be legally effective; upward amendment tax remains payable. AMENDMENT_MISSING: report via B2BA within time limit. | AG11: def rc_gst_006(g1_all, books, p): am = latest(concat(g1_all.b2ba, g1_all.cdnra, g1_all.expa), key=['octin','oinum_n']) out = [] for x in am: o = find_original(g1_all, x.octin, x.oinum_n) if not o: out.append(exc('ORIGINAL_NOT_FOUND', None, x)); continue dl = min(date(fy_end(o.idt).year, 11, 30), p.gstr9_filing_date or date.max) if x.filing_date > dl: out.append(exc('AMENDMENT_LATE', o, x, deadline=dl)) b = books_final(books, x.ctin, x.inum_n) if b is not None and any(abs(b[h]-x[h])>p.value_tolerance_inr for h in HEADS): out.append(exc('AMEND_VALUE_DIFF', b, x)) return out | AH11: TaxGuru – Advisory on Form GSTR-1A | https://taxguru.in/goods-and-service-tax/advisory-form-gstr-1a.html | N.12/2024-CT; from July 2024 period; once per period; window till 3B filed; auto-populates 3B Taxmann – returns cannot be filed after 3 years | https://www.taxmann.com/post/blog/gstn-warns-pending-gst-returns-cannot-be-filed-after-3-years | N.28/2023-CT; advisory 25.09.2025 | AI11: s.37(3) 30-Nov limit from statute knowledge (FA 2022 amendment), consistent with GST-007; not re-opened. Implementation design for linking.
A12: RC-GST-007 | B12: reconciliation_rule | C12: GST – Liability – Return vs return | D12: GSTR-1 + GSTR-1A/IFF vs GSTR-3B Table 3.1 liability by tax head and month (Rule 88C / hard-lock) | E12: Partially verified | F12: Make sure outward tax declared in GSTR-1/1A/IFF equals the liability declared and paid in GSTR-3B for the same period, head by head; anticipate DRC-01B intimation and reflect the July 2025 hard-lock. | G12: GSTR1 | H12: GSTR3B | I12: GSTR1A | J12: tax period (month); quarter for QRMP | K12: CGST Act s.37, s.39(1) ('subject to such conditions and restrictions' – FA 2025, w.e.f. 01.10.2025 via N.16/2025-CT), s.75(12) (self-assessed tax unpaid recoverable); Rule 88C inserted by N.26/2022-CT dt 26.12.2022 (DRC-01B: intimation where GSTR-1/IFF liability exceeds GSTR-3B by amount and percentage recommended by the Council; reply/pay within 7 days; else recovery u/s 79); Rule 59(6) (GSTR-1/IFF of next period blocked if DRC-01B not replied); GSTN advisory 07.06.2025 – GSTR-3B Table 3 auto-populated values non-editable from July 2025 tax period (corrections only via GSTR-1A); Table 3.2 non-editable from Nov 2025 tax period (advisory 05.12.2025). | L12: All GSTR-1 and GSTR-3B filers. | M12: 2022-12-26 | O12: Filed GSTR-1 (+IFF for QRMP), GSTR-1A and GSTR-3B for the period; GSTR-3B auto-populated liability PDF/JSON (system-computed) if available. | P12: GSTR1.gstin = GSTR3B.gstin; GSTR1.return_period = GSTR3B.return_period | Q12: Return period MMYYYY; QRMP: IFF months combined into the quarter. | R12: Per period per head (IGST, CGST, SGST/UTGST, cess) and per 3B row: 3.1(a) = B2B 4A + B2CL 5 + B2CS 7 + DN − CN + amendments (net) + advances 11A − 11B adjustments; 3.1(b) = 6A + 6B + 6C (zero-rated); 3.1(c) = Table 8 nil/exempt; 3.1(e) = Table 8 non-GST; 3.1.1 = ECO s.9(5) table (Table 15 per form – not re-verified). | S12: GSTR1_net.t3_1_a.{txval,iamt,camt,samt,csamt} vs GSTR3B.3_1_a; GSTR1_net.t3_1_b vs GSTR3B.3_1_b; GSTR1_net.t3_1_c vs GSTR3B.3_1_c; GSTR1_net.t3_1_e vs GSTR3B.3_1_e; GSTR1_net.inter_state_unreg_by_pos vs GSTR3B.3_2 | T12: Rs 1 per head (implementation choice). Rule 88C threshold (system intimation) – amount and % 'as recommended by Council' – not notified publicly; secondary sources cite Rs 25 lakh and 20% – kept as param for risk flag only. | U12: diff_h = GSTR1_net_h − GSTR3B_h; pct_h = diff_h / GSTR3B_h (if >0); drc01b_risk = Σ_h max(diff_h,0) > drc01b_amount_inr and pct > drc01b_pct; cumulative_diff_h = Σ over FY | V12: 1. Build GSTR-1 net liability per head and 3B row (overlay 1A, include amendments of earlier periods in the period they are reported). 2. Compare with 3B. 3. Positive diff (GSTR-1 > 3B) -> SHORT_IN_3B; negative -> EXCESS_IN_3B. 4. Compute cumulative FY diff (timing differences reverse). 5. From July 2025 periods: if 3B Table 3 values differ from GSTR-1/1A auto-populated values, data is suspect (portal locks them) -> LOCKED_VALUE_EDITED. 6. Flag DRC01B_RISK. | W12: MATCHED; SHORT_IN_3B: liability in GSTR-1 exceeds 3B; EXCESS_IN_3B: 3B liability exceeds GSTR-1; ROW_SHIFT: totals match but split across 3.1 rows differs; HEAD_SHIFT: total tax matches but IGST vs CGST/SGST split differs; TIMING_REVERSED: diff offset in a later month of same FY; DRC01B_RISK: difference beyond Rule 88C param; LOCKED_VALUE_EDITED: post-July-2025 3B differs from auto-populated value | X12: MATCHED=Low; SHORT_IN_3B=Critical; EXCESS_IN_3B=Medium; ROW_SHIFT=Medium; HEAD_SHIFT=High; TIMING_REVERSED=Low; DRC01B_RISK=Critical; LOCKED_VALUE_EDITED=High | Y12: tax_tolerance_inr=1; drc01b_amount_inr=2500000; drc01b_pct=20; lock_from_period=072025; table32_lock_from_period=112025 | Z12: Both returns are filed versions for same GSTIN & period; GSTR-1A filed before 3B (else 1A affects next period – implementation check). | AA12: exception_id; rule_id; client_id; gstin; period; doc_a_ref (file+row); doc_b_ref; match_key; match_pass (exact/fuzzy); category; severity; field_name; value_a; value_b; difference; tolerance_applied; suggested_action; legal_reference; status (Open/Under review/Resolved/Accepted-as-is); reviewer; review_comment; created_at; head; gstr3b_row; diff; cumulative_fy_diff | AB12: Aug-2025. GSTR-1: B2B 4A txval 10,00,000 IGST 90,000 CGST 45,000 SGST 45,000; B2CS txval 2,00,000 CGST 18,000 SGST 18,000; CN −1,00,000 IGST −18,000. Net 3.1(a): IGST 72,000; CGST 63,000; SGST 63,000. GSTR-3B 3.1(a): IGST 72,000; CGST 60,000; SGST 60,000 -> SHORT_IN_3B CGST 3,000, SGST 3,000 (pct 5% < 20%, no DRC01B_RISK). Sept-2025 3B CGST/SGST +3,000 extra each -> Aug marked TIMING_REVERSED with interest exposure. | AC12: GSTR-1 net CGST 50,000.40 vs 3B 50,000 -> MATCHED. | AD12: QRMP taxpayer: IFF months loaded; comparing month 1 IFF against quarterly 3B must not raise exceptions – rule runs at quarter level only. | AE12: Liability paid in 3B on books basis while GSTR-1 reported later; CN reported in GSTR-1 but not reduced in 3B; advances (11A) not in GSTR-1; ECO supplies; RCM outward supplies (4B) wrongly included in 3.1(a) – supplier does not pay; amendments of earlier periods. | AF12: SHORT_IN_3B: pay differential through next GSTR-3B or DRC-03 with s.50 interest from due date; after July 2025 correct GSTR-1 via GSTR-1A before 3B. Prepare DRC-01B Part B reply where portal intimation received (7 days). | AG12: def rc_gst_007(g1, g1a, iff, g3b, p): net = gstr1_to_3b_rows(overlay(concat(g1, iff), g1a)) # {row: {head: amt}} out = [] for row in ['3_1_a','3_1_b','3_1_c','3_1_e']: for h in ['txval','iamt','camt','samt','csamt']: d = net[row][h] - g3b[row][h] if d > p.tax_tolerance_inr: out.append(exc('SHORT_IN_3B', row=row, head=h, diff=d)) elif d < -p.tax_tolerance_inr: out.append(exc('EXCESS_IN_3B', row=row, head=h, diff=d)) pos_short = sum(max(net['3_1_a'][h]-g3b['3_1_a'][h],0) for h in TAXH) if pos_short > p.drc01b_amount_inr and pos_short/ max(tax_total(g3b),1)*100 > p.drc01b_pct: out.append(exc('DRC01B_RISK', diff=pos_short)) if period_ge(g3b.ret_period, p.lock_from_period) and g3b.autopop and g3b['3_1_a'] != g3b.autopop['3_1_a']: out.append(exc('LOCKED_VALUE_EDITED')) return reclass_head_row_shifts(out) | AH12: Rule 88C CGST Rules (Chhattisgarh GST dept copy) | https://cggst.com/wp-content/uploads/2023/07/Rule-88C-3.pdf | Rule 88C inserted by N.26/2022-CT dt 26.12.2022; threshold 'as recommended by Council' – not stated BDO – GSTN advisory: online functionality for difference in tax liability (DRC-01B) | https://www.bdo.in/en-gb/insights/alerts-updates/gstn-advisory-online-functionality-in-respect-of-the-difference-in-tax | Council-recommended predefined limit Rs 25 lakh (footnote) and 20%; GSTR-1/IFF of next period blocked if no reply Razorpay – DRC-01B guide | https://razorpay.com/learn/drc-01b-gst-liability-mismatch-guide/ | thresholds not publicly disclosed; DRC-01C 'around Rs 25 lakh / 20%' ClearTax – GST return filing rule changes from July 2025 | https://cleartax.in/s/gst-return-filing-rule-changes-from-july-2025 | GSTN advisories 07.06.2025 (3B Table 3 lock), 3-year bar CompuTax – GSTR-3B ITC locking status (09.07.2026) | https://www.computaxonline.com/blog/post/2026/07/09/gst-itc-auto-restriction-gstr-2b-gstr-3b-hard-locking | 3.1/3.2 locked from July 2025 (Advisory 606); Table 4 lock not officially confirmed TaxGuru – GSTN 4 advisories December 2025 | https://taxguru.in/goods-and-service-tax/gstn-issues-4-advisories-december-2025-clarify-key-compliance-procedures.html | 05.12.2025 Table 3.2 lock; 18.12.2025 IMS CN; 29.12.2025 ECRRS/RCM TaxGuru – Advisory on Form GSTR-1A | https://taxguru.in/goods-and-service-tax/advisory-form-gstr-1a.html | N.12/2024-CT; from July 2024 period; once per period; window till 3B filed; auto-populates 3B TaxGuru – Finance Act 2025 GST amendments effective 01.10.2025 | https://taxguru.in/goods-and-service-tax/gst-amendments-finance-act-2025-effective-oct-1-2025-notified.html | N.16/2025-CT; s.34(2) proviso; s.38; s.39(1) | AI12: Rule 88C text verified (state dept copy) – threshold is 'as recommended by Council'; BDO footnote cites Rs 25 lakh and 20% recommended; Razorpay says thresholds are not publicly disclosed. Treat Rs 25 lakh / 20% as an unverified risk parameter. Hard-lock dates from secondary reproductions of GSTN advisories (Advisory 606). Mapping of GSTR-1 tables to 3B rows is GSTN auto-population logic as generally described – CA to confirm for ECO s.9(5) rows.
A13: RC-GST-008 | B13: reconciliation_rule | C13: GST – E-invoicing | D13: E-invoice (IRN) data vs GSTR-1 and sales register; e-invoice applicability | E13: Partially verified | F13: Confirm every B2B/export invoice of an e-invoice-applicable taxpayer has a valid IRN, the IRP data equals the books and GSTR-1, and auto-populated data was not edited without reason. | G13: EINV | H13: GSTR1 | I13: SALES_REG | J13: tax period (month) | K13: CGST Rule 48(4) (e-invoice via IRP for notified class), Rule 48(5) (invoice without IRN not a valid invoice), Rule 48(6); N.13/2020-CT as amended – threshold AATO > Rs 5 crore in any FY from 2017-18 w.e.f. 01.08.2023 (N.10/2023-CT); exempt classes (SEZ units, insurers, banks/NBFCs, GTA, passenger transport, multiplex – per N.13/2020 as amended; not re-verified); GSTN advisory on auto-population of e-invoice into GSTR-1 (B2B 4A/4B, EXP 6A, CDNR 9B, CDNUR exports). | L13: Taxpayers whose AATO exceeded Rs 5 crore in any FY from 2017-18 (from 01.08.2023), for B2B supplies, exports, and CN/DN to registered persons. | M13: 2023-08-01 | O13: IRN data export (GSTR-1 dashboard 'Download details from e-invoice (Excel)' or IRP API) with IRN, ack no., ack date, doc no., doc date, doc type, buyer GSTIN, values, status (Active/Cancelled); GSTR-1 JSON with 'src' and 'irn' fields; client AATO history. | P13: EINV.seller_gstin = GSTR1.gstin; EINV.doc_type = GSTR1.section_doc_type; EINV.doc_no = GSTR1.b2b_invoice_no | exp_invoice_no | cdnr_note_no; EINV.fy = fy(GSTR1.b2b_invoice_date | exp_invoice_date | cdnr_note_date) | Q13: Implementation choice: (1) Invoice/document number – uppercase, trim, collapse internal spaces, remove characters other than A-Z 0-9 '/' '-'; exact pass on this form. (2) Fuzzy pass key = strip '/', '-', spaces; strip leading zeros of each numeric run; strip common FY tokens (e.g. '2025-26', '25-26', '2526', 'FY26') – only if the remainder is still >= 3 characters. Law (Rule 46(b)) allows up to 16 characters, unique per FY. (3) GSTIN – uppercase, trim, validate 15-char pattern ^[0-9]{2}[A-Z]{5}[0-9]{4}[A-Z][1-9A-Z]Z[0-9A-Z]$ and check digit (see GST-001). (4) Dates – parse DD-MM-YYYY, DD/MM/YYYY, DD-MON-YY, YYYY-MM-DD, Excel serials into ISO date. (5) Amounts – Decimal, 2 dp, negative for credit notes only after doc-type mapping. IRN is a 64-char hash – compare exactly (lower-case). Doc type map: INV->B2B/EXP, CRN->CDNR C, DBN->CDNR D. | R13: Document level. | S13: EINV.irn vs GSTR1.b2b_irn; EINV.buyer_gstin vs GSTR1.b2b_recipient_gstin | cdnr_recipient_gstin; EINV.doc_date vs GSTR1.b2b_invoice_date | exp_invoice_date | cdnr_note_date; EINV.val_total_invoice vs GSTR1.b2b_invoice_value | exp_invoice_value | cdnr_note_value; EINV.val_assessable vs GSTR1.b2b_taxable_value | exp_taxable_value | cdnr_taxable_value; EINV.val_igst/cgst/sgst/cess vs GSTR1 heads; EINV.irn_status vs presence in GSTR1; EINV.doc_no vs SALES_REG.voucher_no | T13: Rs 0 on values where src=e-invoice (data is copied by system) – any difference means edit; Rs 1 vs books (implementation choice). | U13: einv_applicable = max(AATO_fy for fy in FY2017-18..preceding FY) > einv_threshold_inr; edited = GSTR1.src != 'e-invoice' and EINV.status=='Active' and same doc found | V13: 1. Determine applicability from AATO history (param list). 2. Match EINV active docs to GSTR-1 docs. 3. Compare values. 4. Active IRN not in GSTR-1 -> IRN_NOT_IN_GSTR1. 5. Cancelled IRN still in GSTR-1 -> CANCELLED_IRN_REPORTED. 6. GSTR-1 B2B/EXP/CDNR doc without IRN while applicable -> NO_IRN (invalid invoice – Rule 48(5)). 7. GSTR-1 doc where IRN exists but src blank -> EDITED_AFTER_AUTOPOP. 8. Books doc vs EINV -> IRN_NOT_IN_BOOKS / BOOKS_NO_IRN. | W13: MATCHED; VALUE_DIFF: values differ; IRN_NOT_IN_GSTR1: active IRN not reported; CANCELLED_IRN_REPORTED: cancelled IRN still in GSTR-1; NO_IRN: applicable B2B/export doc without IRN; EDITED_AFTER_AUTOPOP: auto-populated doc edited (IRN blanked); BOOKS_NO_IRN: books invoice lacks IRN; IRN_NOT_IN_BOOKS: IRN with no books entry; EXEMPT_ENTITY: client in exempt class | X13: MATCHED=Low; VALUE_DIFF=High; IRN_NOT_IN_GSTR1=High; CANCELLED_IRN_REPORTED=High; NO_IRN=Critical; EDITED_AFTER_AUTOPOP=Medium; BOOKS_NO_IRN=Critical; IRN_NOT_IN_BOOKS=High; EXEMPT_ENTITY=Low | Y13: einv_threshold_inr=50000000; aato_history={}; client_exempt_class=false | Z13: IRN 64 hex characters; ack date >= doc date; doc type in (INV, CRN, DBN). | AA13: exception_id; rule_id; client_id; gstin; period; doc_a_ref (file+row); doc_b_ref; match_key; match_pass (exact/fuzzy); category; severity; field_name; value_a; value_b; difference; tolerance_applied; suggested_action; legal_reference; status (Open/Under review/Resolved/Accepted-as-is); reviewer; review_comment; created_at; irn; ack_no; ack_date; einv_status; gstr1_src | AB13: AATO FY 2024-25 Rs 7 crore -> applicable. EINV Aug-2025: INV/101 active txval 2,00,000 IGST 36,000; INV/102 cancelled; INV/103 active. GSTR-1 Aug: INV/101 src e-invoice same values -> MATCHED; INV/102 present -> CANCELLED_IRN_REPORTED; INV/103 missing -> IRN_NOT_IN_GSTR1; INV/104 B2B without IRN -> NO_IRN (invoice invalid; buyer ITC risk). | AC13: Client AATO max Rs 4.8 crore all years -> not applicable; NO_IRN rule skipped. | AD13: B2C invoices of e-invoice taxpayer (no IRN needed; dynamic QR code is separate requirement) -> not flagged NO_IRN. | AE13: Invoices raised from a second billing system without IRP integration; IRN cancelled after 24 hours not possible so CN issued instead; invoice edited in GSTR-1 after auto-population; amendments in GSTR-1 not reflected in IRP. | AF13: NO_IRN / BOOKS_NO_IRN: Critical – invoice not valid under Rule 48(5); generate IRN (subject to 30-day limit, RC-GST-009) or cancel and reissue; inform buyer. CANCELLED_IRN_REPORTED: amend GSTR-1. | AG13: def rc_gst_008(einv, g1, books, p): if p.client_exempt_class: return [exc('EXEMPT_ENTITY')] applicable = max(p.aato_history.values(), default=0) > p.einv_threshold_inr act, can = einv[einv.status=='ACT'], einv[einv.status=='CNL'] docs = concat(g1.b2b, g1.exp, g1.cdnr) pairs, ue, ug = match_exact(act, docs, [('doc_n','inum_n'),('fy','fy')]) out = compare(pairs, ['txval','iamt','camt','samt','csamt','val'], 0) out += [exc('EDITED_AFTER_AUTOPOP', a, x) for a, x in pairs if x.src != 'e-invoice'] out += [exc('IRN_NOT_IN_GSTR1', a) for a in ue] out += [exc('CANCELLED_IRN_REPORTED', c) for c in can if c.doc_n in set(docs.inum_n)] if applicable: out += [exc('NO_IRN', None, x) for x in ug if x.doc_date >= date(2023,8,1)] out += books_vs_einv(books, einv) return out | AH13: GSTN advisory – auto-population of e-invoice details into GSTR-1 (ICMAI copy) | https://icmai.in/upload/Taxation/Advisory_auto-population_GSTR-1.pdf | B2B 4A/4B, EXP 6A, CDNR 9B, CDNUR(exports) auto-populated; edits blank the IRN; cancelled IRN deleted EY – e-invoicing threshold lowered to Rs 5 crore | https://www.ey.com/en_in/alerts-hub/2023/05/cbic-lowers-turnover-threshold-for-e-invoicing-to-inr5-crores-with-effect-from-1-august-2023 | N.10/2023-CT (seen in search results) | AI13: Auto-population behaviour verified from GSTN advisory copy (ICMAI). Rs 5 crore threshold (N.10/2023-CT) seen in search results only (EY). Exempt classes from statute knowledge – CA to confirm. AATO test 'any preceding FY from 2017-18' is the common reading – CA review.
A14: RC-GST-009 | B14: reconciliation_rule | C14: GST – E-invoicing | D14: E-invoice reporting time limit (30 days for AATO >= Rs 10 crore) and invoices without IRN | E14: Verified – secondary source only | F14: Find invoices that were reported to the IRP more than 30 days after the document date by taxpayers with AATO >= Rs 10 crore (IRP rejects these; the invoice then cannot get an IRN). | G14: SALES_REG | H14: EINV | J14: tax period (month) | K14: GSTN advisory (Nov 2024) – 30-day reporting limit extended to taxpayers with AATO >= Rs 10 crore from 01.04.2025 (earlier AATO >= Rs 100 crore from 01.11.2023); Rule 48(4)-(5) CGST Rules. | L14: E-invoice taxpayers with AATO >= Rs 10 crore; documents dated on/after 01.04.2025. | M14: 2025-04-01 | O14: Sales register with document date and IRN; EINV with ack date. | P14: SALES_REG.voucher_no = EINV.doc_no; SALES_REG.doc_type (EINV codes INV|CRN|DBN) = EINV.doc_type; SALES_REG.fy = EINV.fy | Q14: Implementation choice: (1) Invoice/document number – uppercase, trim, collapse internal spaces, remove characters other than A-Z 0-9 '/' '-'; exact pass on this form. (2) Fuzzy pass key = strip '/', '-', spaces; strip leading zeros of each numeric run; strip common FY tokens (e.g. '2025-26', '25-26', '2526', 'FY26') – only if the remainder is still >= 3 characters. Law (Rule 46(b)) allows up to 16 characters, unique per FY. (3) GSTIN – uppercase, trim, validate 15-char pattern ^[0-9]{2}[A-Z]{5}[0-9]{4}[A-Z][1-9A-Z]Z[0-9A-Z]$ and check digit (see GST-001). (4) Dates – parse DD-MM-YYYY, DD/MM/YYYY, DD-MON-YY, YYYY-MM-DD, Excel serials into ISO date. (5) Amounts – Decimal, 2 dp, negative for credit notes only after doc-type mapping. | R14: Document level. | S14: SALES_REG.voucher_date vs EINV.doc_date; EINV.ack_date − EINV.doc_date vs max_days | T14: Legal: 30 days (advisory). Implementation: warn at 25 days for unreported docs. | U14: delay_days = (EINV.ack_date − EINV.doc_date).days; late = delay_days > max_report_days; unreported_age = (run_date − SALES_REG.invoice_date).days | V14: 1. Applicability: AATO >= threshold. 2. For each B2B/export doc in books, find IRN. 3. If IRN exists compute delay_days (should not exceed 30 – IRP blocks; if found, indicates back-dating) -> DOC_DATE_BACKDATED. 4. If no IRN and unreported_age > 30 -> IRN_TIME_EXPIRED; > warn_days -> IRN_DUE_SOON. 5. Compare doc date in books with IRN doc date -> DATE_DIFF. | W14: ON_TIME; DATE_DIFF: books date differs from IRN doc date; IRN_DUE_SOON: no IRN, age > warn days; IRN_TIME_EXPIRED: no IRN, age > 30 days; DOC_DATE_BACKDATED: IRN acknowledged > 30 days after doc date | X14: ON_TIME=Low; DATE_DIFF=High; IRN_DUE_SOON=High; IRN_TIME_EXPIRED=Critical; DOC_DATE_BACKDATED=High | Y14: aato_threshold_inr=100000000; max_report_days=30; warn_days=25; applies_to_doc_types=INV,CRN,DBN | Z14: Dates parse; AATO param present. | AA14: exception_id; rule_id; client_id; gstin; period; doc_a_ref (file+row); doc_b_ref; match_key; match_pass (exact/fuzzy); category; severity; field_name; value_a; value_b; difference; tolerance_applied; suggested_action; legal_reference; status (Open/Under review/Resolved/Accepted-as-is); reviewer; review_comment; created_at; delay_days; unreported_age | AB14: AATO Rs 12 crore. Books: INV-1 dt 01-08-2025 IRN ack 05-08-2025 (4 days) ON_TIME; INV-2 dt 01-08-2025 no IRN on 10-09-2025 (40 days) IRN_TIME_EXPIRED; INV-3 dt 15-08-2025 books but IRN doc date 20-08-2025 -> DATE_DIFF. | AC14: AATO Rs 9 crore -> rule not applicable. | AD14: CN dated 01-08-2025 reported 05-09-2025 (35 days): whether CN/DN are covered – param applies_to_doc_types; default includes CRN/DBN pending CA confirmation. | AE14: Invoices raised manually during system downtime; back-dated invoices; month-end cut-off. | AF14: IRN_TIME_EXPIRED: CA review – invoice cannot be registered; usually cancel in books and issue fresh invoice with current date (time of supply and interest implications to be assessed). | AG14: def rc_gst_009(books, einv, p): if p.aato < p.aato_threshold_inr: return [] out = [] for b in books[books.doc_type.isin(p.applies_to_doc_types) & (books.invoice_date>=date(2025,4,1))]: e = einv_lookup(einv, b) if e: if e.doc_date != b.invoice_date: out.append(exc('DATE_DIFF', b, e)) if (e.ack_date - e.doc_date).days > p.max_report_days: out.append(exc('DOC_DATE_BACKDATED', b, e)) else: age = (p.run_date - b.invoice_date).days if age > p.max_report_days: out.append(exc('IRN_TIME_EXPIRED', b, age=age)) elif age > p.warn_days: out.append(exc('IRN_DUE_SOON', b, age=age)) return out | AH14: Taxmann – 30-day e-invoice reporting for AATO >= Rs 10 crore | https://www.taxmann.com/post/blog/time-limit-of-30-days-for-reporting-e-invoice-on-irp-portal-for-taxpayers-with-aato-of-10-crores-and-above-gstn-update/ | from 01.04.2025 (seen in search results) | AI14: The advisory was seen only in search results (Taxmann, MahaGST copy). Whether CN/DN are covered and the AATO basis (any FY vs preceding FY) must be confirmed from the advisory text.
A15: RC-GST-010 | B15: reconciliation_rule | C15: GST – E-way bill | D15: E-invoice / sales register vs e-way bill (consignment value > Rs 50,000) | E15: Verified – secondary source only | F15: Check that goods movements above the threshold have an e-way bill whose document number, date, value, GSTINs and HSN agree with the invoice; find EWBs without invoices. | G15: SALES_REG | H15: EWB | I15: EINV | J15: tax period (month) | K15: CGST Rule 138(1) (EWB before movement of goods of consignment value > Rs 50,000), Rule 138(10) (validity), Rule 138E (blocking for non-filing of returns); s.68; s.129 (detention, penalty); EWB system changes 01.01.2025 (document not older than 180 days; extension total up to 360 days). NIC advisory 05.01.2024 to block EWB without e-invoice was withdrawn 10.01.2024. | L15: Suppliers/consignors/transporters of goods; state-specific intra-state limits may differ (master). | M15: 2018-04-01 | O15: Sales register (goods lines, HSN, delivery state); EWB download (EWB no., date, doc type, doc no., doc date, from/to GSTIN, from/to state, total value, taxable value, taxes, HSN, status active/cancelled, valid upto). | P15: SALES_REG.voucher_no = EWB.doc_no; SALES_REG.doc_type (EWB codes INV|BIL|BOE|CHL|OTH) = EWB.doc_type; SALES_REG.voucher_date = EWB.doc_date | Q15: Implementation choice: (1) Invoice/document number – uppercase, trim, collapse internal spaces, remove characters other than A-Z 0-9 '/' '-'; exact pass on this form. (2) Fuzzy pass key = strip '/', '-', spaces; strip leading zeros of each numeric run; strip common FY tokens (e.g. '2025-26', '25-26', '2526', 'FY26') – only if the remainder is still >= 3 characters. Law (Rule 46(b)) allows up to 16 characters, unique per FY. (3) GSTIN – uppercase, trim, validate 15-char pattern ^[0-9]{2}[A-Z]{5}[0-9]{4}[A-Z][1-9A-Z]Z[0-9A-Z]$ and check digit (see GST-001). (4) Dates – parse DD-MM-YYYY, DD/MM/YYYY, DD-MON-YY, YYYY-MM-DD, Excel serials into ISO date. (5) Amounts – Decimal, 2 dp, negative for credit notes only after doc-type mapping. HSN compared on first 4 digits (implementation choice) and full digits as info. | R15: Document level. Consignment value = taxable value + taxes (excl. exempt goods value) per Rule 138 Explanation – implementation reads invoice total. | S15: SALES_REG.invoice_value vs EWB.total_invoice_value; SALES_REG.taxable_value vs EWB.total_taxable_value; SALES_REG.party_gstin vs EWB.to_gstin; SALES_REG.ship_to_state vs EWB.act_to_state_code; SALES_REG.hsn_set vs EWB.hsn_set; SALES_REG.igst/cgst/sgst vs EWB taxes | T15: Rs 1 on values (implementation choice). Threshold strictly > Rs 50,000 (legal). | U15: ewb_required = is_goods and not ewb_exempt_goods and consignment_value > ewb_threshold_inr and movement_flag | V15: 1. Filter goods invoices with movement (exclude services, bill-to-ship-to where EWB raised by another party – flag). 2. Determine ewb_required. 3. Match to EWB. 4. Compare. 5. Required but no EWB -> EWB_MISSING. 6. EWB active with no invoice in books -> EWB_NO_INVOICE (possible unrecorded sale). 7. EWB cancelled but invoice exists and goods moved -> EWB_CANCELLED_INVOICE_ACTIVE. 8. Cross-check e-invoice: if EINV exists, EWB values should equal EINV. | W15: MATCHED; VALUE_DIFF; GSTIN_DIFF; STATE_DIFF; HSN_DIFF; EWB_MISSING; EWB_NO_INVOICE; EWB_CANCELLED_INVOICE_ACTIVE; NOT_REQUIRED | X15: MATCHED=Low; VALUE_DIFF=High; GSTIN_DIFF=High; STATE_DIFF=High; HSN_DIFF=Medium; EWB_MISSING=High; EWB_NO_INVOICE=Critical; EWB_CANCELLED_INVOICE_ACTIVE=Medium; NOT_REQUIRED=Low | Y15: ewb_threshold_inr=50000; state_intra_thresholds={}; value_tolerance_inr=1; hsn_compare_digits=4 | Z15: EWB no. 12 digits; doc date <= EWB date; EWB doc date within 180 days of EWB date (from 01.01.2025). | AA15: exception_id; rule_id; client_id; gstin; period; doc_a_ref (file+row); doc_b_ref; match_key; match_pass (exact/fuzzy); category; severity; field_name; value_a; value_b; difference; tolerance_applied; suggested_action; legal_reference; status (Open/Under review/Resolved/Accepted-as-is); reviewer; review_comment; created_at; ewb_no; ewb_date; ewb_status; valid_upto | AB15: Books: INV-201 goods 70,800 (txval 60,000 IGST 10,800) to 29 GSTIN; INV-202 goods 45,000; INV-203 goods 1,18,000. EWB: EWB for INV-201 total 70,800 -> MATCHED; INV-202 45,000 <= 50,000 -> NOT_REQUIRED; INV-203 no EWB -> EWB_MISSING; EWB for doc INV-299 total 2,00,000 not in books -> EWB_NO_INVOICE. | AC15: Invoice 50,001 with EWB values equal -> MATCHED. | AD15: Service invoice 5,00,000 -> excluded (EWB applies to goods). | AE15: EWB generated on proforma/delivery challan; EWB raised by transporter; values changed after EWB; cancelled invoices with live EWB; stock transfers to other GSTIN of same PAN not in sales register. | AF15: EWB_NO_INVOICE: Critical – check for unrecorded supply or cancelled sale; EWB_MISSING: explain (customer pick-up within limit / exempt goods) or note penalty exposure s.129. | AG15: def rc_gst_010(books, ewb, einv, p): g = agg(books[books.is_goods], ['inv_n','doc_type','invoice_date'], SUM_HEADS+['invoice_value']) g['req'] = g.invoice_value > p.ewb_threshold_inr act = ewb[ewb.status=='ACTIVE'] pairs, ub, ue = match_exact(g, act, [('inv_n','doc_no_n'),('doc_type','doc_type')]) out = compare(pairs, ['invoice_value','taxable_value','buyer_gstin','ship_to_state'], p.value_tolerance_inr) out += [exc('HSN_DIFF', a, x) for a, x in pairs if set(h[:p.hsn_compare_digits] for h in a.hsn_set) != set(h[:p.hsn_compare_digits] for h in x.hsn_set)] out += [exc('EWB_MISSING', a) for a in ub if a.req] out += [exc('EWB_NO_INVOICE', None, x) for x in ue] return out | AH15: ClearTax – time limit for e-way bill generation | https://cleartax.in/s/time-limit-for-e-way-bill-generation | Rs 50,000; 180-day document age; 360-day extension ClearTax – blocking EWB generation without e-invoice | https://cleartax.in/s/blocking-e-way-bill-generation-without-e-invoice | NIC advisory 05.01.2024 withdrawn 10.01.2024 | AI15: State-specific intra-state thresholds not verified – maintain master. EWB auto-population from e-invoice is NIC practice.
A16: RC-GST-011 | B16: reconciliation_rule | C16: GST – Outward supplies – HSN | D16: GSTR-1 Table 12 HSN summary vs invoice-level totals (B2B/B2C split, HSN digits) | E16: Partially verified | F16: Check that the HSN summary equals the invoice-level supplies reported in the same GSTR-1 and the books, split correctly into B2B and B2C tabs, with the required HSN digits and valid HSN codes. | G16: GSTR1 | H16: SALES_REG | J16: tax period (month) / quarter | K16: CGST Rule 46 (HSN on invoice) read with N.78/2020-CT dt 15.10.2020 (w.e.f. 01.04.2021: AATO up to Rs 5 crore – 4 digits (B2B mandatory); above Rs 5 crore – 6 digits); Rule 59 / GSTR-1 Table 12; GSTN Phase-III advisory (Jan 2025) – Table 12 split into B2B and B2C tabs with HSN dropdown; GSTN advisory 01.05.2025 – Phase-III applicable from May 2025 return period. | L16: All GSTR-1 filers. | M16: 2021-04-01 | O16: GSTR-1 hsn section (hsn_b2b and hsn_b2c tabs from May 2025: hsn_sc, desc, uqc, qty, rt, txval, iamt, camt, samt, csamt); GSTR-1 invoice-level sections; sales register with HSN, UQC, qty; HSN master (valid codes). | P16: GSTR1.hsn_code = SALES_REG.hsn_sac; GSTR1.hsn_rate = SALES_REG.gst_rate; GSTR1.hsn_section = SALES_REG.b2b_or_b2c | Q16: HSN digits only, no spaces/dots; compare at reporting digit level (4 or 6) – implementation choice; UQC mapped to GST UQC list; rate to 2 dp. | R16: Sum by (tab, HSN, rate) – books lines; and Σ of GSTR-1 invoice-level sections (B2B 4A/4B/6B/6C + CDNR for B2B tab; B2CL + B2CS + CDNUR + exports for B2C tab – per portal logic) vs Σ Table 12. | S16: GSTR1.hsn_taxable_value vs SALES_REG.Σ taxable_value by (hsn_sac, gst_rate, b2b_or_b2c); GSTR1.hsn_igst/hsn_cgst/hsn_sgst/hsn_cess vs SALES_REG.sum_tax_heads; GSTR1.hsn_quantity vs SALES_REG.sum_qty; Σ GSTR1.hsn_b2b_taxable_value.txval vs Σ GSTR1.b2b_sections_taxable_value.txval; Σ GSTR1.hsn_b2c_taxable_value.txval vs Σ GSTR1.b2c_sections_taxable_value.txval | T16: Rs 1 per HSN-rate line on values; Rs 10 on tab totals (implementation choice); qty – exact after UQC conversion. | U16: tab_diff = Σ Table12_tab.txval − Σ invoice_sections_tab.txval; digits_ok = len(hsn) >= (6 if AATO > 5 cr else 4) | V16: 1. Build expected HSN summary from books (tab assignment: buyer GSTIN present -> B2B). 2. Compare to Table 12 per (tab, HSN, rate). 3. Compare tab totals to invoice-level sections in the same GSTR-1. 4. Digit check by AATO. 5. Validity check against HSN master (dropdown codes). 6. Services: SAC 99xx – same digits rule. | W16: MATCHED; HSN_VALUE_DIFF: value per HSN differs; HSN_TAX_DIFF; QTY_DIFF; TAB_TOTAL_DIFF: Table 12 tab total differs from invoice-level totals; TAB_MISCLASS: B2B value reported in B2C tab or vice versa; DIGITS_SHORT: fewer digits than required; HSN_INVALID: not in master; HSN_MISSING_IN_T12; HSN_EXTRA_IN_T12 | X16: MATCHED=Low; HSN_VALUE_DIFF=Medium; HSN_TAX_DIFF=Medium; QTY_DIFF=Low; TAB_TOTAL_DIFF=High; TAB_MISCLASS=Medium; DIGITS_SHORT=High; HSN_INVALID=High; HSN_MISSING_IN_T12=Medium; HSN_EXTRA_IN_T12=Medium | Y16: aato_inr=; value_tolerance_inr=1; tab_tolerance_inr=10; phase3_from_period=052025 | Z16: HSN numeric; UQC in allowed list; rate in rate master. | AA16: exception_id; rule_id; client_id; gstin; period; doc_a_ref (file+row); doc_b_ref; match_key; match_pass (exact/fuzzy); category; severity; field_name; value_a; value_b; difference; tolerance_applied; suggested_action; legal_reference; status (Open/Under review/Resolved/Accepted-as-is); reviewer; review_comment; created_at; tab; hsn; rate; uqc | AB16: AATO Rs 8 crore (6 digits required). Books B2B: HSN 847130 18% txval 5,00,000; 8471 18% txval 1,00,000 (4 digits) -> DIGITS_SHORT. Table 12 B2B: 847130 txval 6,00,000 (included the 4-digit line) -> HSN_VALUE_DIFF +1,00,000 on 847130 and HSN_MISSING_IN_T12 for 8471. Invoice-level B2B total 6,00,000 = Table 12 B2B total 6,00,000 -> tab totals OK. | AC16: AATO Rs 3 crore, B2B HSN 8471 4 digits -> digits OK. | AD16: Period April 2025 (pre Phase-III) – single Table 12: tab comparison skipped, total-level comparison only. | AE16: ERP item master with 4-digit HSN; services coded with goods HSN; CN not netted in Table 12; B2C supplies in B2B tab; UQC 'OTH' for everything. | AF16: Correct item master; amend Table 12 in next GSTR-1 (HSN amendment). DIGITS_SHORT is a compliance gap (penalty exposure under s.125 general penalty – CA view). | AG16: def rc_gst_011(g1, books, p): req = 6 if p.aato_inr > 5e7 else 4 exp = agg(books.assign(tab=np.where(books.buyer_gstin!='','B2B','B2C')), ['tab','hsn','rate'], SUM_HEADS+['qty']) t12 = agg(g1.hsn, ['tab','hsn_sc','rt'], SUM_HEADS+['qty']) out = compare_outer(exp, t12, keys=[('tab','tab'),('hsn','hsn_sc'),('rate','rt')], tol=p.value_tolerance_inr, cats=('HSN_VALUE_DIFF','HSN_MISSING_IN_T12','HSN_EXTRA_IN_T12')) for tab in ('B2B','B2C'): d = t12[t12.tab==tab].txval.sum() - invoice_sections_total(g1, tab) if abs(d) > p.tab_tolerance_inr: out.append(exc('TAB_TOTAL_DIFF', tab=tab, diff=d)) out += [exc('DIGITS_SHORT', r) for r in t12 if len(r.hsn_sc) < req] out += [exc('HSN_INVALID', r) for r in t12 if r.hsn_sc not in HSN_MASTER] return out | AH16: TaxHeal – 4/6 digit HSN rule (N.78/2020-CT) | https://www.taxheal.com/?p=97083 | AATO <= 5 cr: 4 digits; > 5 cr: 6 digits Taxo – Phase-III HSN advisory (Jan 2025) | https://taxo.online/latest-news/09-01-2025-advisory-issued-relating-implementation-of-phase-iii-for-mentioning-of-hsn-codes-in-gstr-1-gstr-1a/ | Table 12 B2B/B2C split; dropdown Taxmann – HSN dropdown & Table 13 mandatory in GSTR-1 from May 2025 | https://www.taxmann.com/post/blog/hsn-dropdown-table-13-mandatory-in-gstr-1 | GSTN advisory 01.05.2025; Table 12 B2B/B2C split; Table 13 mandatory from May 2025 return period | AI16: N.78/2020-CT digit table verified only via secondary summaries. Whether the portal blocks or warns on HSN validations, and whether B2C tab requires digits for AATO <= Rs 5 crore, not confirmed. Portal allocation of CDNR/CDNUR between tabs is CA review.
A17: RC-GST-012 | B17: reconciliation_rule | C17: GST – Outward supplies – Document series | D17: GSTR-1 Table 13 documents issued vs sales register document series (gaps, cancelled) | E17: Partially verified | F17: Check that each document series reported in Table 13 (from-to, total, cancelled) agrees with the books, and find gaps, duplicates and unexplained cancellations in invoice numbering. | G17: SALES_REG | H17: GSTR1 | J17: tax period (month) / quarter | K17: CGST Rule 46(b) (consecutive serial number unique for a FY, up to 16 characters); Rule 59 / GSTR-1 Table 13 (documents issued) – mandatory from May 2025 return period per GSTN advisory 01.05.2025. | L17: All GSTR-1 filers. | M17: 2025-05-01 | O17: Sales register with all documents incl. cancelled (status), document nature (invoice, CN, DN, receipt voucher, refund voucher, payment voucher, delivery challan, revised invoice, invoice for RCM inward from unregistered); GSTR-1 doc_issue section (doc_num nature, from, to, totnum, cancel, net_issue). | P17: SALES_REG.doc_nature_code = GSTR1.doc_nature_code; SALES_REG.series_prefix = prefix(GSTR1.doc_from_serial) | Q17: Series parsing (implementation choice): split document no. into prefix + numeric part + suffix using regex ^(.*?)(\d+)(\D*)$; numeric part as integer; same prefix and suffix = same series. | R17: Per (doc nature, series): min no., max no., count issued, count cancelled. | S17: SALES_REG.series_from vs GSTR1.doc_from_serial; SALES_REG.series_to vs GSTR1.doc_to_serial; SALES_REG.count_total vs GSTR1.doc_total_number; SALES_REG.count_cancelled vs GSTR1.doc_cancelled; GSTR1.doc_net_issued vs (totnum − cancel) | T17: Exact (counts). | U17: gaps = set(range(min_no, max_no+1)) − set(issued_nos); net_issue = totnum − cancel; continuity: next period from = previous period to + 1 | V17: 1. Parse series in books. 2. Aggregate. 3. Compare with Table 13. 4. Gaps in numeric sequence not marked cancelled -> GAP. 5. Duplicate numbers in same FY series -> DUPLICATE_NO. 6. Continuity with previous period's 'to' -> SERIES_BREAK. 7. Table 13 net issued vs count of invoices reported in GSTR-1 invoice tables for that series (B2B+B2CL+exports; B2C small not invoice-level so compare only where all invoices are B2B) -> COUNT_DIFF. | W17: MATCHED; RANGE_DIFF: from/to differs; COUNT_DIFF: totals differ; CANCEL_DIFF: cancelled count differs; GAP: missing numbers not marked cancelled; DUPLICATE_NO; SERIES_BREAK: series not continuous across periods; SERIES_MISSING_IN_T13; ARITH_ERROR: net_issue != totnum − cancel | X17: MATCHED=Low; RANGE_DIFF=Medium; COUNT_DIFF=Medium; CANCEL_DIFF=Medium; GAP=High; DUPLICATE_NO=High; SERIES_BREAK=Low; SERIES_MISSING_IN_T13=Medium; ARITH_ERROR=Medium | Y17: check_continuity=true; fy_reset=true | Z17: Each document has a nature; numbers within a series are parseable. | AA17: exception_id; rule_id; client_id; gstin; period; doc_a_ref (file+row); doc_b_ref; match_key; match_pass (exact/fuzzy); category; severity; field_name; value_a; value_b; difference; tolerance_applied; suggested_action; legal_reference; status (Open/Under review/Resolved/Accepted-as-is); reviewer; review_comment; created_at; doc_nature; series_prefix; missing_numbers | AB17: Books Aug-2025 series 'INV/25-26/': 101-150 issued, 112 and 130 cancelled, 141 absent. Table 13: from 101 to 150 total 50 cancelled 2 net 48. Books count total 49 (141 missing) -> COUNT_DIFF (50 vs 49) and GAP [141]. | AC17: Series 1-10, cancelled 1, Table 13 total 10 cancel 1 net 9 -> MATCHED. | AD17: Two series 'A/1..' and 'B/1..' in same nature -> treated separately, no false gaps. | AE17: Cancelled invoices deleted from ERP (gap); manual invoice books; multiple branches with own series; FY reset numbering not followed. | AF17: GAP: obtain explanation (cancelled copy/void) – possible unreported supply; DUPLICATE_NO: violates Rule 46(b). | AG17: def rc_gst_012(books, g1, prev_t13, p): s = books.assign(**parse_series(books.doc_no)) out = [] for (nat, pre, suf), grp in s.groupby(['doc_nature','prefix','suffix']): nums = sorted(grp.num); mn, mx = nums[0], nums[-1] gaps = sorted(set(range(mn, mx+1)) - set(nums)) if gaps: out.append(exc('GAP', key=(nat,pre), missing=gaps)) dups = [n for n, c in Counter(grp.num).items() if c > 1] if dups: out.append(exc('DUPLICATE_NO', key=(nat,pre), dups=dups)) t = find_t13(g1.doc_issue, nat, pre) if not t: out.append(exc('SERIES_MISSING_IN_T13', key=(nat,pre))); continue if t.totnum != len(grp): out.append(exc('COUNT_DIFF', a=len(grp), b=t.totnum)) if t.cancel != (grp.status=='CANCELLED').sum(): out.append(exc('CANCEL_DIFF')) if t.net_issue != t.totnum - t.cancel: out.append(exc('ARITH_ERROR')) if p.check_continuity and prev_t13 and num(t.from_) != num(prev_to(prev_t13, nat, pre)) + 1: out.append(exc('SERIES_BREAK')) return out | AH17: Taxmann – HSN dropdown & Table 13 mandatory in GSTR-1 from May 2025 | https://www.taxmann.com/post/blog/hsn-dropdown-table-13-mandatory-in-gstr-1 | GSTN advisory 01.05.2025; Table 12 B2B/B2C split; Table 13 mandatory from May 2025 return period | AI17: Table 13 mandatory from May 2025 per GSTN advisory 01.05.2025 (Taxmann summary). Rule 46(b) 16-character limit from statute knowledge (GST-007). Series parsing is implementation design.
A18: RC-GST-013 | B18: reconciliation_rule | C18: GST – ITC – Books vs 2B | D18: Purchase register vs GSTR-2B – invoice-level ITC matching | E18: Partially verified | F18: Match every purchase invoice/debit note/credit note in the books with GSTR-2B so that ITC is claimed only on documents communicated in 2B, and find supplier errors and missing documents. | G18: PURCH_REG | H18: GSTR2B | I18: IMS | J18: tax period (month); look-back across FY up to s.16(4) date | K18: CGST Act s.16(2)(aa) (ITC only if supplier has furnished details and they are communicated – N.39/2021-CT w.e.f. 01.01.2022), s.16(2)(a)-(d), s.38 (auto-generated statement; amended FA 2025 w.e.f. 01.10.2025), s.16(4) (time limit); Rule 36(4) as substituted by N.40/2021-CT (w.e.f. 01.01.2022: ITC only on invoices/DNs furnished in GSTR-1/IFF and communicated in GSTR-2B); Rule 60(7)-(9) (GSTR-2B); IMS from Oct 2024 tax period. | L18: All regular taxpayers claiming ITC. | M18: 2022-01-01 | O18: Purchase register (supplier GSTIN, doc type, doc no., date, POS, taxable value, IGST/CGST/SGST/cess, RCM flag, ITC eligibility, books period, GL head); GSTR-2B JSON for the month and earlier/later months of the FY (b2b, b2ba, cdnr, cdnra, isd, impg, impgsez; itcavl Y/N; rsn; diffprcnt; supprd; supfildt). | P18: PURCH_REG.party_gstin = GSTR2B.supplier_gstin; PURCH_REG.doc_type = GSTR2B.doc_type; PURCH_REG.supplier_invoice_no = GSTR2B.invoice_no; PURCH_REG.fy = fy(GSTR2B.invoice_date) | Q18: Implementation choice: (1) Invoice/document number – uppercase, trim, collapse internal spaces, remove characters other than A-Z 0-9 '/' '-'; exact pass on this form. (2) Fuzzy pass key = strip '/', '-', spaces; strip leading zeros of each numeric run; strip common FY tokens (e.g. '2025-26', '25-26', '2526', 'FY26') – only if the remainder is still >= 3 characters. Law (Rule 46(b)) allows up to 16 characters, unique per FY. (3) GSTIN – uppercase, trim, validate 15-char pattern ^[0-9]{2}[A-Z]{5}[0-9]{4}[A-Z][1-9A-Z]Z[0-9A-Z]$ and check digit (see GST-001). (4) Dates – parse DD-MM-YYYY, DD/MM/YYYY, DD-MON-YY, YYYY-MM-DD, Excel serials into ISO date. (5) Amounts – Decimal, 2 dp, negative for credit notes only after doc-type mapping. Supplier invoice nos. are the most error-prone key: run exact, then fuzzy, then 'GSTIN + date ±3 days + total tax ±Re 1' pass (implementation choice). | R18: Document level; purchase lines summed per document. | S18: PURCH_REG.supplier_invoice_date vs GSTR2B.invoice_date; PURCH_REG.taxable_value vs GSTR2B.taxable_value; PURCH_REG.igst vs GSTR2B.igst_amount; PURCH_REG.cgst vs GSTR2B.cgst_amount; PURCH_REG.sgst_utgst vs GSTR2B.sgst_amount; PURCH_REG.cess vs GSTR2B.cess_amount; PURCH_REG.place_of_supply vs GSTR2B.pos; PURCH_REG.reverse_charge vs GSTR2B.reverse_charge; PURCH_REG.books_period vs GSTR2B.return_period; GSTR2B.itc_availability | T18: Implementation choice (law prescribes none): Rs 1 per head per document; optional percentage tolerance 0.1% for large docs. ITC is allowed only up to the amount in 2B – any excess over 2B is not claimable even if within tolerance. | U18: itc_claimable_doc = min(books_tax_h, gstr2b_tax_h) for each head where itcavl=='Y' and not blocked; excess_in_books_h = books_tax_h − gstr2b_tax_h | V18: 1. Load books for period + 2B for same period and all other 2B of the FY (and next FY up to 30 Nov). 2. Validate. 3. Pass 1 exact; pass 2 fuzzy doc no.; pass 3 GSTIN+date window+tax total. 4. For matches compare fields and period (books period vs 2B period). 5. Classify each document (single primary category; secondary flags). 6. RCM documents in books (s.9(3)/9(4)) are not expected in 2B B2B except where supplier reported with rev='Y' -> route to RCM rules. 7. itcavl='N' in 2B (e.g. POS rule, s.16(4) expired, Rule 37A) -> ITC_NOT_AVAILABLE with reason. 8. Summarise: Σ claimable ITC for 3B Table 4A(5). | W18: MATCHED: all fields within tolerance, same period; VALUE_MISMATCH: taxable value differs; TAX_MISMATCH: tax differs (books > 2B = excess claim risk; books < 2B = ITC left); HEAD_MISMATCH: IGST vs CGST+SGST; DATE_MISMATCH: doc date differs, same period; PERIOD_MISMATCH: in 2B of a different month (earlier = ITC available earlier; later = ITC to be deferred); GSTIN_MISMATCH: same doc under another GSTIN (supplier's other registration or wrong GSTIN); INVNO_MISMATCH: matched only by fuzzy/tax pass; MISSING_IN_2B: in books, not in any 2B (supplier not filed / wrong GSTIN / B2C reported); MISSING_IN_BOOKS: in 2B, not in books; DUPLICATE: duplicate in books or 2B; RCM_IN_2B: supplier reported reverse-charge doc (rev=Y) – ITC via RCM rules; ITC_NOT_AVAILABLE: 2B itcavl=N; REVERSE_CHARGE_IN_BOOKS_ONLY: RCM purchase from unregistered/notified service (not expected in 2B) | X18: MATCHED=Low; VALUE_MISMATCH=Medium; TAX_MISMATCH=High; HEAD_MISMATCH=High; DATE_MISMATCH=Low; PERIOD_MISMATCH=Medium; GSTIN_MISMATCH=High; INVNO_MISMATCH=Low; MISSING_IN_2B=Critical; MISSING_IN_BOOKS=Medium; DUPLICATE=Critical; RCM_IN_2B=Medium; ITC_NOT_AVAILABLE=High; REVERSE_CHARGE_IN_BOOKS_ONLY=Low | Y18: value_tolerance_inr=1; pct_tolerance=0; date_window_days=3; fuzzy_match=true; lookback_months=12; lookahead_until=30-Nov-next-FY | Z18: Supplier GSTIN valid & active (if GSTIN status file available); doc date <= books date; ITC heads consistent with POS (supplier state vs client state); same document not booked twice; 2B file period and GSTIN equal the client's. | AA18: exception_id; rule_id; client_id; gstin; period; doc_a_ref (file+row); doc_b_ref; match_key; match_pass (exact/fuzzy); category; severity; field_name; value_a; value_b; difference; tolerance_applied; suggested_action; legal_reference; status (Open/Under review/Resolved/Accepted-as-is); reviewer; review_comment; created_at; supplier_gstin; supplier_name; doc_no_books; doc_no_2b; 2b_period; itcavl; itc_reason; itc_claimable; itc_excess | AB18: Client 27. Books Aug-2025: (1) 27AAAPA1111A1Z1 PI-10 txval 1,00,000 C 9,000 S 9,000; (2) 29BBBPB2222B1Z2 7788 txval 50,000 IGST 9,000; (3) 27CCCPC3333C1Z3 A/55 txval 20,000 C 1,800 S 1,800; (4) 24DDDPD4444D1Z4 X-1 txval 10,000 IGST 1,800; (5) PI-10 booked twice. 2B Aug-2025: PI10 (fuzzy) same values -> INVNO_MISMATCH (ITC 18,000 OK); 7788 IGST 8,100 -> TAX_MISMATCH excess 900 (claimable 8,100); A/55 absent in Aug but in Sep-2025 2B -> PERIOD_MISMATCH (defer 3,600 to Sep); X-1 not in any 2B -> MISSING_IN_2B (1,800 not claimable); 2B has 27EEEPE5555E1Z5 INV-9 txval 5,000 C 450 S 450 -> MISSING_IN_BOOKS; second PI-10 -> DUPLICATE. Claimable Aug = 18,000 + 8,100 = 26,100 vs books 34,200 -> excess 8,100. | AC18: Books IGST 9,000.60 vs 2B 9,000 -> MATCHED (diff 0.60); claimable = 9,000. | AD18: Purchase from unregistered GTA under RCM -> REVERSE_CHARGE_IN_BOOKS_ONLY, not MISSING_IN_2B. Import of goods -> routed to RC-GST-027. | AE18: Supplier filed GSTR-1 late (period shift); supplier used wrong GSTIN (client's other branch); supplier reported as B2C; invoice no. typed differently; freight/rounding differences; supplier CN not booked; capital goods booked in FAR not purchase register; duplicate booking from GRN and invoice. | AF18: MISSING_IN_2B: do not claim; follow up with supplier; if already claimed, reverse in 4B(2) (temporary) and re-claim when appears. TAX_MISMATCH (books > 2B): claim 2B amount only. MISSING_IN_BOOKS: book invoice or reject in IMS (RC-GST-015). DUPLICATE: reverse duplicate ITC immediately, s.50(3) interest if utilised. | AG18: def rc_gst_013(pr, g2b_fy, p): b = agg(pr[~pr.is_import], ['supplier_gstin','doc_type','doc_n','fy'], SUM_HEADS) r = agg(concat(g2b_fy.b2b, g2b_fy.cdnr, overlay_amend(g2b_fy)), ['ctin','typ','inum_n','fy'], SUM_HEADS+['ret_period','itcavl','rsn','rev']) out = duplicates(b,'DUPLICATE') + duplicates(r,'DUPLICATE') b, r = dedupe(b), dedupe(r) p1, ub, ur = match_exact(b, r, [('supplier_gstin','ctin'),('doc_type','typ'),('doc_n','inum_n'),('fy','fy')]) p2, ub, ur = match_fuzzy(ub, ur, gstin_equal=True, key='doc_fz') if p.fuzzy_match else ([], ub, ur) p3, ub, ur = match_window(ub, ur, gstin_equal=True, days=p.date_window_days, tax_tol=p.value_tolerance_inr) p4, ub, ur = match_on(ub, ur, ['doc_n','dt','total_tax']) # GSTIN_MISMATCH for a, x, tag in [(a,x,'') for a,x in p1] + [(a,x,'INVNO_MISMATCH') for a,x in p2+p3]: cats = classify(a, x, p) # TAX/VALUE/HEAD/DATE/PERIOD/RCM_IN_2B/ITC_NOT_AVAILABLE out.append(exc(cats or tag or 'MATCHED', a, x, itc_claimable=claimable(a, x))) out += [exc('GSTIN_MISMATCH', a, x) for a, x in p4] out += [exc('REVERSE_CHARGE_IN_BOOKS_ONLY' if a.rcm_flag else 'MISSING_IN_2B', a) for a in ub] out += [exc('MISSING_IN_BOOKS', None, x) for x in ur] return out | AH18: TaxGuru – ITC only as per GSTR-2B w.e.f. 01.01.2022 | https://taxguru.in/goods-and-service-tax/claim-itc-gstr-2b-mandatory-w-e-f-01-01-2022.html | N.39/2021-CT (s.16(2)(aa)), N.40/2021-CT (Rule 36(4)) ClearTax – FAQs on IMS | https://cleartax.in/s/faqs-on-invoice-management-system-ims-gst | IMS from 01.10.2024; deemed acceptance EY alert – GSTN advisory on IMS changes (23.09.2025) | https://www.ey.com/en_in/technical/alerts-hub/2025/09/gstn-issues-advisory-on-the-changes-introduced-in-the-invoice-management-system | pending CN one period; ITC reversal declaration; from Oct 2025 period TaxGuru – Finance Act 2025 GST amendments effective 01.10.2025 | https://taxguru.in/goods-and-service-tax/gst-amendments-finance-act-2025-effective-oct-1-2025-notified.html | N.16/2025-CT; s.34(2) proviso; s.38; s.39(1) | AI18: Legal basis (s.16(2)(aa), Rule 36(4) N.40/2021) verified via secondary (TaxGuru). Matching passes, tolerances and categories are implementation design. GSTR-2B JSON field names (ctin, inum, dt, val, pos, rev, itcavl, rsn, txval, igst, cgst, sgst, cess, supprd, supfildt) as commonly published – confirm against current API version.
A19: RC-GST-014 | B19: reconciliation_rule | C19: GST – ITC – Return vs return | D19: GSTR-2B ITC available vs GSTR-3B Table 4A ITC claimed (Rule 88D / DRC-01C) | E19: Partially verified | F19: Check that ITC claimed in GSTR-3B Table 4A does not exceed ITC available in GSTR-2B (plus valid re-claims, RCM and imports), month-wise and cumulatively, and anticipate DRC-01C. | G19: GSTR2B | H19: GSTR3B | I19: ECRRS | J19: tax period (month) and FY cumulative | K19: CGST Act s.16(2)(aa), s.39(1) (FA 2025); Rule 36(4); Rule 88D inserted by N.38/2023-CT dt 04.08.2023 (DRC-01C intimation where ITC in GSTR-3B exceeds ITC in GSTR-2B by amount/percentage recommended by Council; reply or pay via DRC-03 within 7 days; non-reply -> subsequent GSTR-1/IFF blocked); Circular 170/02/2022-GST (Table 4 reporting); GSTR-3B Table 4 auto-populated from 2B/IMS. Hard-lock of Table 4 – reported as targeted (July 2026) but not officially confirmed. | L19: All regular taxpayers. | M19: 2023-08-04 | O19: GSTR-2B summary (ITC available by section and head; ITC not available; ITC reversal section); GSTR-3B Table 4 (4A(1) import goods, 4A(2) import services, 4A(3) RCM, 4A(4) ISD, 4A(5) all other; 4B(1), 4B(2); 4C; 4D(1), 4D(2)); ECRRS closing balance. | P19: GSTR2B.gstin = GSTR3B.gstin; GSTR2B.return_period = GSTR3B.return_period | Q19: Return period MMYYYY. | R19: Per period per head; FY cumulative per head. | S19: GSTR2B.b2b_net_itc (B2B + B2BA − CDNR) vs GSTR3B.4A5 − GSTR3B.4D1_reclaim_part; GSTR2B.isd_itc vs GSTR3B.4A4; GSTR2B.impg_itc vs GSTR3B.4A1; GSTR3B.4A2+4A3 vs GSTR3B.3_1_d (RCM rule RC-GST-020); GSTR3B.4C vs 4A − 4B1 − 4B2 | T19: Rs 1 per head (implementation choice). Rule 88D system threshold – Council-recommended amount/percentage not publicly notified; secondary sources cite ~Rs 25 lakh and 20% – param for risk flag only. | U19: excess_h = GSTR3B.4A5_h − (GSTR2B.b2b_net_h + reclaim_allowed_h); reclaim_allowed_h = min(GSTR3B.4D1_h, ECRRS.opening_h + GSTR3B.4B2_h); drc01c_risk = Σ excess_h > drc01c_amount_inr and Σ excess_h / Σ GSTR2B_h * 100 > drc01c_pct; net_itc_check = 4C − (4A_total − 4B1 − 4B2) | V19: 1. Load 2B summary and 3B Table 4 per period. 2. Compute expected 4A(5), 4A(4), 4A(1). 3. Compare; positive excess -> EXCESS_ITC_CLAIMED; negative -> ITC_NOT_CLAIMED (may be legit due to IMS pending, blocked credit, Rule 42 – check 4B). 4. Arithmetic check of 4C. 5. Cumulative FY excess (claims shifted between months). 6. DRC01C_RISK flag. 7. For periods where 2B section 'ITC reversal' is present, check it appears in 4B(2). | W19: MATCHED; EXCESS_ITC_CLAIMED: 3B 4A exceeds 2B (+reclaim); ITC_NOT_CLAIMED: 3B less than 2B; ISD_DIFF; IMPORT_DIFF; NET_ITC_ARITH: 4C != 4A − 4B; CUMULATIVE_EXCESS: FY-to-date excess; DRC01C_RISK; MANUAL_EDIT: 3B Table 4 differs from system-generated auto-populated values | X19: MATCHED=Low; EXCESS_ITC_CLAIMED=Critical; ITC_NOT_CLAIMED=Medium; ISD_DIFF=High; IMPORT_DIFF=High; NET_ITC_ARITH=High; CUMULATIVE_EXCESS=Critical; DRC01C_RISK=Critical; MANUAL_EDIT=Medium | Y19: tax_tolerance_inr=1; drc01c_amount_inr=2500000; drc01c_pct=20 | Z19: Both files for same GSTIN/period; 3B filed (not draft). | AA19: exception_id; rule_id; client_id; gstin; period; doc_a_ref (file+row); doc_b_ref; match_key; match_pass (exact/fuzzy); category; severity; field_name; value_a; value_b; difference; tolerance_applied; suggested_action; legal_reference; status (Open/Under review/Resolved/Accepted-as-is); reviewer; review_comment; created_at; head; gstr3b_cell; gstr2b_value; gstr3b_value; excess | AB19: Sep-2025 IGST. 2B B2B 4,00,000, CDNR −20,000 -> net 3,80,000. ECRRS opening 15,000; 3B 4B(2) 5,000; 4D(1) 10,000 (<= 20,000 OK). 3B 4A(5) 4,10,000 -> expected 3,80,000 + 10,000 = 3,90,000 -> EXCESS_ITC_CLAIMED 20,000 (5.1%, below 20% -> no DRC01C_RISK). 4C reported 4,05,000 vs 4,10,000 − 0 − 5,000 = 4,05,000 OK. | AC19: 2B 1,00,000; 3B 4A(5) 1,00,000; no reclaim -> MATCHED. | AD19: 3B 4A(5) 90,000 < 2B 1,00,000 because IMS invoices 'pending' (10,000) -> ITC_NOT_CLAIMED, Medium, with note to check IMS pending list (2B regenerated only after IMS action). | AE19: ITC claimed on books basis; re-claims shown in 4A(5) instead of 4D(1); ITC of previous year claimed; RCM ITC put in 4A(5); IMS rejected documents still claimed; 2B regenerated after IMS action but 3B based on original 2B. | AF19: EXCESS_ITC_CLAIMED: reverse in next 3B 4B(2) or pay via DRC-03 with s.50(3) interest if utilised (Rule 88B(3)); prepare DRC-01C Part B reply within 7 days if intimation received. | AG19: def rc_gst_014(g2b, g3b, ecrrs, p): out = [] for h in ['igst','cgst','sgst','cess']: reclaim_ok = min(g3b['4D1'][h], ecrrs.opening[h] + g3b['4B2'][h]) exp5 = g2b.b2b_net[h] + reclaim_ok d = g3b['4A5'][h] - exp5 if d > p.tax_tolerance_inr: out.append(exc('EXCESS_ITC_CLAIMED', head=h, diff=d)) elif d < -p.tax_tolerance_inr: out.append(exc('ITC_NOT_CLAIMED', head=h, diff=d)) if abs(g3b['4A4'][h]-g2b.isd[h]) > p.tax_tolerance_inr: out.append(exc('ISD_DIFF', head=h)) if abs(g3b['4A1'][h]-g2b.impg[h]) > p.tax_tolerance_inr: out.append(exc('IMPORT_DIFF', head=h)) if abs(g3b['4C'][h] - (sum(g3b[c][h] for c in A_ROWS) - g3b['4B1'][h] - g3b['4B2'][h])) > p.tax_tolerance_inr: out.append(exc('NET_ITC_ARITH', head=h)) ex = sum(max(o.diff,0) for o in out if o.cat=='EXCESS_ITC_CLAIMED') if ex > p.drc01c_amount_inr and ex/ max(g2b.total,1)*100 > p.drc01c_pct: out.append(exc('DRC01C_RISK', diff=ex)) return out | AH19: ClearTax – Rule 88D DRC-01C | https://cleartax.in/s/rule-88d-cgst-itc-mismatch-gstr-2b-vs-gstr-3b | N.38/2023-CT dt 04.08.2023; 7 days; DRC-03; GSTR-1/IFF blocking Taxo – GSTN advisory 06.10.2023 on DRC-01C | https://taxo.online/latest-news/06-10-2023-gstn-issued-advisory-in-respect-of-introduction-of-compliance-pertaining-to-drc-01c/ | 2B vs 3B per return period; 'predefined limits'; subsequent GSTR-1/IFF blocked Razorpay – DRC-01B guide | https://razorpay.com/learn/drc-01b-gst-liability-mismatch-guide/ | thresholds not publicly disclosed; DRC-01C 'around Rs 25 lakh / 20%' Circular 170/02/2022-GST | https://www.gstcouncil.gov.in/sites/default/files/2024-06/cir-170-02-2022-cgst.pdf | GSTR-3B Table 4 and 3.2 reporting CompuTax – GSTR-3B ITC locking status (09.07.2026) | https://www.computaxonline.com/blog/post/2026/07/09/gst-itc-auto-restriction-gstr-2b-gstr-3b-hard-locking | 3.1/3.2 locked from July 2025 (Advisory 606); Table 4 lock not officially confirmed TaxGuru – ITC reclaim ledger & RCM ledger hard validations | https://taxguru.in/goods-and-service-tax/gstn-itc-reclaim-ledger-rcm-ledger-hard-validations-block-gstr-3b-filing.html | advisory 29.12.2025: 4D(1) <= reclaim balance + 4B(2) current; 4A(2)+4A(3) <= 3.1(d) + RCM ledger balance | AI19: Rule 88D notification (N.38/2023-CT dt 04.08.2023), 7-day reply and GSTR-1/IFF blocking verified via ClearTax and Taxo reproduction of GSTN advisory 06.10.2023; threshold not published officially. Table 4 hard-lock status as of Oct 2026 unconfirmed (CompuTax July 2026). Reclaim formula follows GSTN advisory 29.12.2025 hard-validation logic (TaxGuru).
A20: RC-GST-015 | B20: reconciliation_rule | C20: GST – ITC – IMS | D20: IMS actions (accept/reject/pending) vs purchase register | E20: Partially verified | F20: Check that IMS actions agree with the books: accepted documents are booked, rejected documents are not booked (or are disputed), pending documents are tracked, and credit-note actions reflect ITC actually availed. | G20: IMS | H20: PURCH_REG | I20: GSTR2B | J20: tax period (month) | K20: Invoice Management System on GST portal from 01.10.2024 (Accept/Reject/Pending; no action = deemed accepted at GSTR-2B generation); GSTN advisory 23.09.2025 (from Oct 2025 tax period: credit notes/upward CN amendments/certain downward amendments may be kept pending only for one tax period; recipient can declare ITC reversal amount actually availed on CNs); advisory 18.12.2025 on IMS credit notes; CGST s.34(2) proviso (FA 2025) – supplier's tax reduction depends on recipient reversal; s.38 (FA 2025, w.e.f. 01.10.2025). | L20: All recipients with inward B2B documents on IMS. | M20: 2024-10-01 | O20: IMS download with action status (Accepted/Rejected/Pending/No action), remarks, declared ITC reversal for CNs; purchase register incl. dispute/hold flags; GSTR-2B (regenerated) for the period. | P20: IMS.supplier_gstin = PURCH_REG.party_gstin; IMS.doc_type = PURCH_REG.doc_type; IMS.document_no = PURCH_REG.supplier_invoice_no; IMS.fy = PURCH_REG.fy | Q20: Implementation choice: (1) Invoice/document number – uppercase, trim, collapse internal spaces, remove characters other than A-Z 0-9 '/' '-'; exact pass on this form. (2) Fuzzy pass key = strip '/', '-', spaces; strip leading zeros of each numeric run; strip common FY tokens (e.g. '2025-26', '25-26', '2526', 'FY26') – only if the remainder is still >= 3 characters. Law (Rule 46(b)) allows up to 16 characters, unique per FY. (3) GSTIN – uppercase, trim, validate 15-char pattern ^[0-9]{2}[A-Z]{5}[0-9]{4}[A-Z][1-9A-Z]Z[0-9A-Z]$ and check digit (see GST-001). (4) Dates – parse DD-MM-YYYY, DD/MM/YYYY, DD-MON-YY, YYYY-MM-DD, Excel serials into ISO date. (5) Amounts – Decimal, 2 dp, negative for credit notes only after doc-type mapping. | R20: Document level. | S20: IMS.ims_action vs PURCH_REG.booking_status; IMS.taxable_value vs PURCH_REG.taxable_value; IMS.tax_heads vs PURCH_REG.tax_heads; IMS.declared_igst vs PURCH_REG.cn_itc_reversed; IMS.pending_since vs current period | T20: Rs 1 per head (implementation choice). | U20: pending_age_periods = periods_between(IMS.supplier_period, current_period); cn_pending_breach = doc_type=='CN' and action=='Pending' and pending_age_periods > max_cn_pending_periods | V20: 1. Match IMS docs to books. 2. Accepted (or deemed accepted) but not in books -> ACCEPTED_NOT_BOOKED. 3. Rejected but booked with ITC -> REJECTED_BUT_ITC_CLAIMED. 4. Pending but ITC claimed -> PENDING_ITC_CLAIMED (pending docs are not in 2B). 5. CN accepted: compare declared reversal with ITC actually availed on original invoice in books -> CN_REVERSAL_DIFF. 6. CN pending beyond one period (Oct 2025 onward) -> CN_PENDING_LIMIT. 7. Books docs whose IMS status 'No action' -> NO_ACTION_DEEMED_ACCEPT (info). 8. Rejected documents with no books entry -> REJECT_OK. | W20: CONSISTENT; ACCEPTED_NOT_BOOKED; REJECTED_BUT_ITC_CLAIMED; PENDING_ITC_CLAIMED; CN_REVERSAL_DIFF; CN_PENDING_LIMIT; NO_ACTION_DEEMED_ACCEPT; REJECT_OK; VALUE_DIFF | X20: CONSISTENT=Low; ACCEPTED_NOT_BOOKED=High; REJECTED_BUT_ITC_CLAIMED=Critical; PENDING_ITC_CLAIMED=Critical; CN_REVERSAL_DIFF=High; CN_PENDING_LIMIT=Medium; NO_ACTION_DEEMED_ACCEPT=Low; REJECT_OK=Low; VALUE_DIFF=Medium | Y20: max_cn_pending_periods=1; cn_rule_from_period=102025; value_tolerance_inr=1 | Z20: IMS file period equals reconciliation period; statuses in allowed set. | AA20: exception_id; rule_id; client_id; gstin; period; doc_a_ref (file+row); doc_b_ref; match_key; match_pass (exact/fuzzy); category; severity; field_name; value_a; value_b; difference; tolerance_applied; suggested_action; legal_reference; status (Open/Under review/Resolved/Accepted-as-is); reviewer; review_comment; created_at; ims_action; ims_remark; declared_reversal; books_itc | AB20: Oct-2025 IMS: INV-1 accepted 18,000 tax, booked -> CONSISTENT; INV-2 rejected 9,000, booked and ITC claimed -> REJECTED_BUT_ITC_CLAIMED; INV-3 pending 3,600, ITC claimed -> PENDING_ITC_CLAIMED; CN-1 accepted, declared reversal 0 but books show original ITC 1,800 claimed -> CN_REVERSAL_DIFF 1,800. | AC20: Accepted invoice booked with equal values -> CONSISTENT. | AD20: Invoice pending in Sept-2024 (before IMS) -> rule not applicable (effective_from). | AE20: Bulk 'accept all'; rejection without informing supplier; CN pending to avoid reversal; IMS action after 2B generation without recomputing 2B; ITC claimed from books not from regenerated 2B. | AF20: REJECTED_BUT_ITC_CLAIMED / PENDING_ITC_CLAIMED: reverse ITC or change IMS action before 3B; CN_REVERSAL_DIFF: declare correct reversal in IMS (supplier liability depends on it). | AG20: def rc_gst_015(ims, pr, p): pairs, ui, ub = match_exact(ims, agg(pr, DOCKEY, SUM_HEADS+['itc_claimed']), DOCKEY_PAIRS) out = [] for i, b in pairs: if i.action=='REJECTED' and b.itc_claimed>0: out.append(exc('REJECTED_BUT_ITC_CLAIMED', i, b)) elif i.action=='PENDING' and b.itc_claimed>0: out.append(exc('PENDING_ITC_CLAIMED', i, b)) elif i.doc_type=='CN' and i.action=='ACCEPTED' and abs(i.declared_reversal - orig_itc(pr, i)) > p.value_tolerance_inr: out.append(exc('CN_REVERSAL_DIFF', i, b)) else: out.append(exc('CONSISTENT', i, b)) if i.doc_type=='CN' and i.action=='PENDING' and period_ge(p.period, p.cn_rule_from_period) and periods_between(i.supplier_period, p.period) > p.max_cn_pending_periods: out.append(exc('CN_PENDING_LIMIT', i)) out += [exc('ACCEPTED_NOT_BOOKED' if i.action in ('ACCEPTED','NO_ACTION') else 'REJECT_OK', i) for i in ui] return out | AH20: ClearTax – FAQs on IMS | https://cleartax.in/s/faqs-on-invoice-management-system-ims-gst | IMS from 01.10.2024; deemed acceptance EY alert – GSTN advisory on IMS changes (23.09.2025) | https://www.ey.com/en_in/technical/alerts-hub/2025/09/gstn-issues-advisory-on-the-changes-introduced-in-the-invoice-management-system | pending CN one period; ITC reversal declaration; from Oct 2025 period TaxGuru – GSTN 4 advisories December 2025 | https://taxguru.in/goods-and-service-tax/gstn-issues-4-advisories-december-2025-clarify-key-compliance-procedures.html | 05.12.2025 Table 3.2 lock; 18.12.2025 IMS CN; 29.12.2025 ECRRS/RCM TaxGuru – Finance Act 2025 GST amendments effective 01.10.2025 | https://taxguru.in/goods-and-service-tax/gst-amendments-finance-act-2025-effective-oct-1-2025-notified.html | N.16/2025-CT; s.34(2) proviso; s.38; s.39(1) | AI20: IMS rules verified via EY and ClearTax secondary summaries of GSTN advisories. Exact list of document types that can/cannot be kept pending (and whether CN pending limit is one tax period from supplier filing) to be confirmed from GSTN advisory text.
A21: RC-GST-016 | B21: reconciliation_rule | C21: GST – ITC – Return vs return | D21: GSTR-2A vs GSTR-2B – late-filed supplier documents and period shift | E21: Unverified – needs CA review | F21: Identify documents visible in dynamic GSTR-2A but not in the period's GSTR-2B (supplier filed after cut-off, or IMS pending), so ITC is claimed in the correct later period. | G21: GSTR2A | H21: GSTR2B | I21: PURCH_REG | J21: tax period (month), FY | K21: Rule 60 (GSTR-2A dynamic) and Rule 60(7)-(9) (GSTR-2B static, generated on 14th of following month – cut-off of supplier GSTR-1/IFF filing); Rule 36(4) (ITC only per 2B); s.16(4). | L21: All recipients. | M21: 2022-01-01 | O21: GSTR-2A (with supplier filing date 'cfs'/filing period) and all GSTR-2B files of the FY. | P21: GSTR2A.supplier_gstin = GSTR2B.supplier_gstin; GSTR2A.invoice_no = GSTR2B.invoice_no; GSTR2A.doc_type = GSTR2B.doc_type | Q21: Implementation choice: (1) Invoice/document number – uppercase, trim, collapse internal spaces, remove characters other than A-Z 0-9 '/' '-'; exact pass on this form. (2) Fuzzy pass key = strip '/', '-', spaces; strip leading zeros of each numeric run; strip common FY tokens (e.g. '2025-26', '25-26', '2526', 'FY26') – only if the remainder is still >= 3 characters. Law (Rule 46(b)) allows up to 16 characters, unique per FY. (3) GSTIN – uppercase, trim, validate 15-char pattern ^[0-9]{2}[A-Z]{5}[0-9]{4}[A-Z][1-9A-Z]Z[0-9A-Z]$ and check digit (see GST-001). (4) Dates – parse DD-MM-YYYY, DD/MM/YYYY, DD-MON-YY, YYYY-MM-DD, Excel serials into ISO date. (5) Amounts – Decimal, 2 dp, negative for credit notes only after doc-type mapping. | R21: Document level. | S21: GSTR2A.gstr1_period vs GSTR2B.return_period; GSTR2A.tax_heads vs GSTR2B.tax_heads; GSTR2A.gstr1_filing_date vs 2B cut-off date | T21: Exact on presence; Rs 1 on values. | U21: expected_2b_period = first 2B period whose cut-off >= supplier filing date (and IMS action not pending) | V21: 1. Match 2A docs to any 2B of the FY. 2. Present in 2A for period P but in 2B of P+k -> LATE_FILED_SHIFT (ITC claimable in P+k). 3. Present in 2A, absent in all 2B -> IN_2A_NOT_2B (pending IMS / post cut-off / ITC not available). 4. Values differ (supplier amended) -> AMENDED_VALUE. 5. Link to books (RC-GST-013) to show which books entries are affected. | W21: SAME_PERIOD; LATE_FILED_SHIFT; IN_2A_NOT_2B; AMENDED_VALUE; IN_2B_NOT_2A | X21: SAME_PERIOD=Low; LATE_FILED_SHIFT=Medium; IN_2A_NOT_2B=High; AMENDED_VALUE=Medium; IN_2B_NOT_2A=Low | Y21: value_tolerance_inr=1 | Z21: 2A downloaded after the latest 2B to be compared. | AA21: exception_id; rule_id; client_id; gstin; period; doc_a_ref (file+row); doc_b_ref; match_key; match_pass (exact/fuzzy); category; severity; field_name; value_a; value_b; difference; tolerance_applied; suggested_action; legal_reference; status (Open/Under review/Resolved/Accepted-as-is); reviewer; review_comment; created_at; 2a_period; 2b_period; supplier_filing_date | AB21: Invoice INV-9 dated 25-08-2025, supplier filed Aug GSTR-1 on 20-09-2025 (after 2B cut-off 14-09). 2A Aug shows INV-9; 2B Aug lacks it; 2B Sep has it -> LATE_FILED_SHIFT (claim in Sep 3B). INV-10 in 2A Aug, not in any 2B (pending in IMS) -> IN_2A_NOT_2B. | AC21: Doc in 2A Aug and 2B Aug -> SAME_PERIOD. | AD21: 2A downloaded before supplier amendment -> run flagged stale if 2A date < last 2B generation date. | AE21: Supplier QRMP filing IFF late; supplier GSTR-1 after the 13th; documents kept pending in IMS. | AF21: LATE_FILED_SHIFT: claim in later period's 3B; check s.16(4) deadline (RC-GST-031). | AG21: def rc_gst_016(g2a, g2b_all, p): allb = concat_with_period(g2b_all) pairs, ua, ub = match_exact(g2a, allb, DOCKEY_PAIRS) out = [] for a, b in pairs: cat = 'SAME_PERIOD' if a.supplier_period == b.ret_period else 'LATE_FILED_SHIFT' out.append(exc(cat, a, b)) if any(abs(a[h]-b[h])>p.value_tolerance_inr for h in TAXH): out.append(exc('AMENDED_VALUE', a, b)) out += [exc('IN_2A_NOT_2B', a) for a in ua] + [exc('IN_2B_NOT_2A', None, b) for b in ub] return out | AH21: TaxGuru – ITC only as per GSTR-2B w.e.f. 01.01.2022 | https://taxguru.in/goods-and-service-tax/claim-itc-gstr-2b-mandatory-w-e-f-01-01-2022.html | N.39/2021-CT (s.16(2)(aa)), N.40/2021-CT (Rule 36(4)) | AI21: Rule 60(7)-(9) and 14th cut-off from statute knowledge / GST-012 – not re-opened here. Implementation design.
A22: RC-GST-017 | B22: reconciliation_rule | C22: GST – ITC – Payment condition | D22: Purchase register payment dates vs 180-day rule (Rule 37) – reversal, interest, re-claim | E22: Partially verified | F22: Find purchase invoices on which ITC was claimed but value plus tax has not been paid to the supplier within 180 days of invoice date, compute ITC to be reversed and interest, and track re-availment on payment. | G22: PURCH_REG | H22: BANK_BOOK | I22: GSTR3B | J22: tax period (month) in which 180th day falls | K22: CGST Act s.16(2) second proviso (pay value + tax within 180 days, else ITC added to output tax with interest) and third proviso (re-availment on payment); Rule 37(1), (2), (4) as substituted by N.19/2022-CT w.e.f. 01.10.2022 (reverse proportionate ITC in return for the period in which 180 days end; interest u/s 50; time limit u/s 16(4) not applicable to re-availment); Rule 88B; reported in GSTR-3B 4B(2) and re-claim in 4D(1)/4A(5) via ECRRS. | L22: All recipients; excludes (per Rule 37(1)) supplies on which tax payable under reverse charge, deemed supplies without consideration (Schedule I), and additions to value under s.15(2)(b) – exclusions as per Rule 37 text. | M22: 2022-10-01 | O22: Purchase register with invoice date, value incl. tax, ITC claimed and period of claim; payments to supplier (bank book / creditor ledger) with dates and allocation to invoices (FIFO if not allocated – implementation choice); GSTR-3B 4B(2) and 4D(1) values. | P22: PURCH_REG.party_gstin = BANK_BOOK.party_gstin; PURCH_REG.supplier_invoice_no = BANK_BOOK.bill_ref (or FIFO allocation) | Q22: Implementation choice: (1) Invoice/document number – uppercase, trim, collapse internal spaces, remove characters other than A-Z 0-9 '/' '-'; exact pass on this form. (2) Fuzzy pass key = strip '/', '-', spaces; strip leading zeros of each numeric run; strip common FY tokens (e.g. '2025-26', '25-26', '2526', 'FY26') – only if the remainder is still >= 3 characters. Law (Rule 46(b)) allows up to 16 characters, unique per FY. (3) GSTIN – uppercase, trim, validate 15-char pattern ^[0-9]{2}[A-Z]{5}[0-9]{4}[A-Z][1-9A-Z]Z[0-9A-Z]$ and check digit (see GST-001). (4) Dates – parse DD-MM-YYYY, DD/MM/YYYY, DD-MON-YY, YYYY-MM-DD, Excel serials into ISO date. (5) Amounts – Decimal, 2 dp, negative for credit notes only after doc-type mapping. Party matching on GSTIN or ledger code via PARTY_MASTER. | R22: Invoice level; payments allocated to invoices. | S22: PURCH_REG.invoice_value vs Σ payments within 180 days; PURCH_REG.itc_claimed vs required_reversal; required_reversal vs GSTR3B.4B2 of the trigger period | T22: Rs 1 (implementation choice). | U22: day180 = invoice_date + 180 days (Rule says 'within a period of 180 days from the date of issue of invoice'); paid_by_180 = Σ payments dated <= day180; unpaid_ratio = (invoice_value − paid_by_180) / invoice_value; reversal = itc_claimed × unpaid_ratio; interest = reversal × 18% × days(from date ITC availed/utilised to date of reversal or payment)/365 (start date per CA – see notes) | V22: 1. Allocate payments to invoices (by reference; else FIFO by invoice date). 2. Compute day180 and paid_by_180 (include TDS/TCS deducted and book adjustments as 'paid' only if CA param allows). 3. If unpaid > 0 and ITC claimed, compute proportionate reversal due in the period containing day180. 4. Compare with 3B 4B(2) for that period (aggregate). 5. On later payment, compute re-claim (4D(1)) and check it is not before payment date. 6. Compute interest per param. | W22: PAID_IN_TIME; REVERSAL_DUE: unpaid at day180, ITC to reverse; REVERSAL_NOT_DONE: 3B 4B(2) lower than required; REVERSED_OK; RECLAIM_DUE: paid after reversal, re-claim available; RECLAIM_BEFORE_PAYMENT: re-claim taken before payment; PARTIAL_PAYMENT: proportionate reversal; EXCLUDED: RCM/deemed supply | X22: PAID_IN_TIME=Low; REVERSAL_DUE=High; REVERSAL_NOT_DONE=Critical; REVERSED_OK=Low; RECLAIM_DUE=Medium; RECLAIM_BEFORE_PAYMENT=High; PARTIAL_PAYMENT=High; EXCLUDED=Low | Y22: days_limit=180; interest_rate_pct=18; interest_start=availment_date; count_tds_as_paid=true; allocation=reference_else_fifo | Z22: Payment dates >= invoice date (warn advances); invoice value incl. tax present; ITC claim period known. | AA22: exception_id; rule_id; client_id; gstin; period; doc_a_ref (file+row); doc_b_ref; match_key; match_pass (exact/fuzzy); category; severity; field_name; value_a; value_b; difference; tolerance_applied; suggested_action; legal_reference; status (Open/Under review/Resolved/Accepted-as-is); reviewer; review_comment; created_at; invoice_date; day180; paid_by_180; unpaid_amount; reversal_itc; interest; reclaim_period | AB22: INV-500 dt 01-02-2025 value 1,18,000 (ITC 18,000 claimed Feb-2025). Payments: 50,000 on 15-03-2025; 68,000 on 10-09-2025. day180 = 31-07-2025. paid_by_180 = 50,000; unpaid ratio = 68,000/1,18,000 = 0.5763; reversal = 18,000 × 0.5763 = 10,373 in Jul-2025 3B 4B(2). 3B Jul 4B(2) = 0 -> REVERSAL_NOT_DONE. Re-claim 10,373 available Sep-2025 (payment 10-09-2025). Interest at 18% from 20-03-2025 (Feb 3B due date, availment) to 20-08-2025 (153 days) = 10,373 × 0.18 × 153/365 = 782.65 -> 783 (s.170) – if CA chooses availment start date. | AC22: Invoice paid in full on day 179 -> PAID_IN_TIME. | AD22: RCM invoice from unregistered GTA unpaid at 200 days -> EXCLUDED (Rule 37 does not apply to RCM supplies). | AE22: Payments booked against on-account without invoice allocation; disputes/retention money; netting with receivables (journal set-off – whether 'payment' is a CA judgment); MSME vendors; foreign-currency adjustments. | AF22: REVERSAL_NOT_DONE: reverse in next 3B 4B(2) (shows in ECRRS) and pay interest via DRC-03; RECLAIM_DUE: re-claim in 4A(5) and report in 4D(1) after payment. | AG22: def rc_gst_017(pr, pay, g3b_by_period, p): alloc = allocate(pay, pr, method=p.allocation) out = [] for inv in pr[(pr.itc_claimed>0) & (~pr.rcm_flag)]: d180 = inv.invoice_date + timedelta(days=p.days_limit) paid = alloc.paid_by(inv.id, d180, include_tds=p.count_tds_as_paid) if paid >= inv.invoice_value - 1: out.append(exc('PAID_IN_TIME', inv)); continue ratio = (inv.invoice_value - paid) / inv.invoice_value rev = round(inv.itc_claimed * ratio, 2) per = period_of(d180) out.append(exc('REVERSAL_DUE' if ratio == 1 else 'PARTIAL_PAYMENT', inv, reversal=rev, period=per)) later = alloc.payment_dates_after(inv.id, d180) if later: out.append(exc('RECLAIM_DUE', inv, reclaim_period=period_of(later[-1]))) # aggregate check per period for per, rev_sum in group_sum(out, 'period', 'reversal').items(): if g3b_by_period[per]['4B2_total'] + 1 < rev_sum: out.append(exc('REVERSAL_NOT_DONE', period=per, diff=rev_sum - g3b_by_period[per]['4B2_total'])) return out | AH22: Rule 37 CGST Rules (Chhattisgarh GST dept copy) | https://www.cggst.com/uploads/document/1755064447-rule-37.pdf | Rule 37(1),(2),(4) as substituted by N.19/2022-CT Rule 88B CGST Rules (Chhattisgarh GST dept copy) | https://www.cggst.com/uploads/document/1754119329-rule-88b.pdf | Rule 88B(1)-(3) Circular 170/02/2022-GST | https://www.gstcouncil.gov.in/sites/default/files/2024-06/cir-170-02-2022-cgst.pdf | GSTR-3B Table 4 and 3.2 reporting GSTHero – ECRRS | https://gsthero.com/blog/electronic-credit-reversal-and-reclaimed-statement/ | from Aug 2023 return period | AI22: Rule 37 text verified from state GST department copy. Interest start date and rate (s.50(1) vs s.50(3); 18%) are open – see gst.json open questions; default param uses availment date and 18%, CA to decide. Whether netting/set-off counts as payment is a CA judgment.
A23: RC-GST-018 | B23: reconciliation_rule | C23: GST – ITC – Reversal & re-claim | D23: GSTR-3B Table 4B(2)/4D(1) reversals and re-claims vs ECRRS (incl. opening balance) | E23: Partially verified | F23: Roll forward the Electronic Credit Reversal and Re-claimed Statement from 3B data and books, and flag re-claims exceeding the reclaimable balance (negative ledger), and opening-balance errors. | G23: GSTR3B | H23: ECRRS | I23: PURCH_REG | J23: tax period (month), running balance | K23: Circular 170/02/2022-GST (temporary reversals in 4B(2), re-claim in 4A(5) and 4D(1)); GSTN ECRRS from August 2023 return period (monthly) / Jul-Sep 2023 quarter (QRMP) with one-time opening balance; GSTN advisory No. 643 dt 29.12.2025 – hard validation: 4D(1) re-claim <= ECRRS closing balance + current 4B(2) (activation date not confirmed). | L23: All regular taxpayers. | M23: 2023-08-01 | O23: ECRRS download (opening balance, reversal, re-claim, closing per head per period); GSTR-3B 4B(2), 4D(1); books register of temporary reversals (Rule 37, 2B missing, IMS, s.16(2)(b)/(c)). | P23: GSTR3B.return_period = ECRRS.return_period; GSTR3B.gstin = ECRRS.gstin | Q23: Return period MMYYYY. | R23: Per period per head; and per-document books register summed per period. | S23: GSTR3B.4B2_h vs ECRRS.reversal_igst; GSTR3B.4D1_h vs ECRRS.reclaim_igst; ECRRS.opening_igst + 4B2_h − 4D1_h vs ECRRS.closing_igst; ECRRS.closing_igst vs books_temp_reversal_balance_h | T23: Rs 1 per head (implementation choice). Negative balance – zero tolerance (portal validation). | U23: closing_h = opening_h + rev_4B2_h − reclaim_4D1_h; negative if closing_h < 0; books_gap_h = ECRRS.closing_h − books_open_items_h | V23: 1. Load ECRRS; start from opening balance declared (Aug 2023). 2. Recompute closing each period from 3B values. 3. Compare with portal closing. 4. Negative closing -> NEGATIVE_BALANCE (3B may be blocked). 5. Compare closing with books open temporary reversals (documents reversed and not yet re-claimed) -> BOOKS_GAP. 6. Permanent reversals (Rule 42/43/17(5)/38) found in 4B(2) instead of 4B(1) -> WRONG_ROW (from books classification). | W23: MATCHED; ROLLFORWARD_DIFF: recomputed closing != portal; NEGATIVE_BALANCE; RECLAIM_EXCEEDS: 4D(1) > opening + 4B(2); BOOKS_GAP: ECRRS balance differs from books open reversals; WRONG_ROW: permanent reversal in 4B(2) or temporary in 4B(1); OPENING_BALANCE_SUSPECT: opening balance not supported by books | X23: MATCHED=Low; ROLLFORWARD_DIFF=Medium; NEGATIVE_BALANCE=Critical; RECLAIM_EXCEEDS=Critical; BOOKS_GAP=High; WRONG_ROW=High; OPENING_BALANCE_SUSPECT=High | Y23: tax_tolerance_inr=1; ecrrs_start_period=082023 | Z23: Periods continuous; heads IGST/CGST/SGST/cess. | AA23: exception_id; rule_id; client_id; gstin; period; doc_a_ref (file+row); doc_b_ref; match_key; match_pass (exact/fuzzy); category; severity; field_name; value_a; value_b; difference; tolerance_applied; suggested_action; legal_reference; status (Open/Under review/Resolved/Accepted-as-is); reviewer; review_comment; created_at; head; opening; reversal; reclaim; closing_recomputed; closing_portal | AB23: IGST: opening Jul-2025 12,000; Jul 4B(2) 10,373; Jul 4D(1) 0 -> closing 22,373. Aug 4B(2) 0; Aug 4D(1) 25,000 -> 22,373 − 25,000 = −2,627 -> RECLAIM_EXCEEDS and NEGATIVE_BALANCE. Books open items Aug-end: 0 -> BOOKS_GAP vs portal. | AC23: opening 5,000 + reversal 2,000 − reclaim 7,000 = 0 -> MATCHED. | AD23: QRMP taxpayer: periods quarterly from Jul-Sep 2023 – monthly comparisons skipped. | AE23: Opening balance not declared or wrong; re-claims of ITC never reversed via 4B(2) (e.g. ITC reversed by not claiming); Rule 42 reversals put in 4B(2) and later 're-claimed'. | AF23: NEGATIVE_BALANCE / RECLAIM_EXCEEDS: reverse excess in 4B(2) of next 3B (adds to liability if ITC insufficient) and pay s.50(3) interest if utilised; correct opening balance via portal facility if still open. | AG23: def rc_gst_018(g3b_series, ecrrs, books_open, p): out = []; bal = dict(ecrrs.opening_at(p.ecrrs_start_period)) for per in periods(g3b_series): for h in HEADS4: if g3b_series[per]['4D1'][h] > bal[h] + g3b_series[per]['4B2'][h] + p.tax_tolerance_inr: out.append(exc('RECLAIM_EXCEEDS', period=per, head=h)) bal[h] += g3b_series[per]['4B2'][h] - g3b_series[per]['4D1'][h] if bal[h] < 0: out.append(exc('NEGATIVE_BALANCE', period=per, head=h, value=bal[h])) if abs(bal[h] - ecrrs.closing(per, h)) > p.tax_tolerance_inr: out.append(exc('ROLLFORWARD_DIFF', period=per, head=h)) if abs(ecrrs.closing(per, h) - books_open.balance(per, h)) > p.tax_tolerance_inr: out.append(exc('BOOKS_GAP', period=per, head=h)) return out | AH23: Circular 170/02/2022-GST | https://www.gstcouncil.gov.in/sites/default/files/2024-06/cir-170-02-2022-cgst.pdf | GSTR-3B Table 4 and 3.2 reporting GSTHero – ECRRS | https://gsthero.com/blog/electronic-credit-reversal-and-reclaimed-statement/ | from Aug 2023 return period TaxGuru – ITC reclaim ledger & RCM ledger hard validations | https://taxguru.in/goods-and-service-tax/gstn-itc-reclaim-ledger-rcm-ledger-hard-validations-block-gstr-3b-filing.html | advisory 29.12.2025: 4D(1) <= reclaim balance + 4B(2) current; 4A(2)+4A(3) <= 3.1(d) + RCM ledger balance Busy – GSTR-3B hard block survival guide (July 2026) | https://busy.in/business-updates/how-to-fix-gstr-3b-hard-block/ | Advisory No. 643 dt 29.12.2025; activation date not stated TaxGuru – GSTN 4 advisories December 2025 | https://taxguru.in/goods-and-service-tax/gstn-issues-4-advisories-december-2025-clarify-key-compliance-procedures.html | 05.12.2025 Table 3.2 lock; 18.12.2025 IMS CN; 29.12.2025 ECRRS/RCM | AI23: Hard-validation formula verified via TaxGuru summary of GSTN advisory 29.12.2025 (Advisory No. 643 per Busy). Activation date of blocking not confirmed as of July 2026 (Busy). ECRRS start periods verified via TaxGuru/GSTHero (secondary).
A24: RC-GST-019 | B24: reconciliation_rule | C24: GST – Reverse charge | D24: RCM: GL expense heads vs GSTR-3B 3.1(d) liability and 4A(2)/4A(3) ITC | E24: Partially verified | F24: Identify expenses in the general ledger that attract reverse charge (GTA, legal, director fees, security, rent of commercial property from unregistered, import of services, etc.), compute expected RCM tax, and compare with liability paid in 3B 3.1(d) and ITC taken in 4A(2)/(3). | G24: GL | H24: GSTR3B | I24: PURCH_REG | J24: tax period (month) based on time of supply | K24: CGST Act s.9(3) / IGST Act s.5(3) – Notification 13/2017-CT(Rate) (services) as amended incl. 9/2024-CT(Rate) (renting of non-residential property by unregistered person to registered person, from 10.10.2024) and 7/2025-CT(Rate) (composition recipients excluded from that entry, from 16.01.2025); Notification 4/2017-CT(Rate) (goods); IGST s.5(3) + N.10/2017-IT(Rate) (import of services); s.9(4) (notified classes); s.13(3) time of supply; s.31(3)(f) self-invoice; s.49(4) RCM to be paid in cash; GTA from 22.09.2025: 5% (RCM default) or 18% forward charge option (Council FAQ). | L24: Registered recipients of notified goods/services. | M24: 2017-07-01 | O24: GL with expense head, party, party GSTIN/registration status, PAN, nature (body corporate/individual/firm), invoice date, payment date, amount; RCM mapping master (GL head -> RCM entry, rate, conditions); GSTR-3B 3.1(d), 4A(2), 4A(3); self-invoices. | P24: GL.ledger_name = RCM_MASTER.gl_head; GL.period_tos = GSTR3B.return_period | Q24: GL head names mapped via master (implementation choice); party constitution from PARTY_MASTER; month of time of supply = month(min(payment_date, invoice_date + 60 days)) per s.13(3) for services. | R24: Per period per RCM entry per head (IGST if supplier state != recipient state or import of services; else CGST+SGST). | S24: Σ expected_rcm_tax_h vs GSTR3B.3_1_d_h; Σ expected_rcm_itc_eligible_h vs GSTR3B.4A3_h (domestic) and 4A2_h (import of services); GSTR3B.4A2+4A3 vs GSTR3B.3_1_d (RC-GST-020) | T24: Rs 10 per head per period (implementation choice – rounding of many small bills). | U24: rcm_tax = taxable_value × rate; tos_services = min(payment_date, invoice_date + 60 days); expected_itc = rcm_tax where eligible (not blocked u/s 17(5), business use) | V24: 1. Filter GL lines whose head maps to an RCM entry. 2. Apply conditions per entry (e.g. legal services by individual advocate/firm to business entity; security by non-body-corporate to registered person; renting of commercial property by unregistered person; director sitting fees by director to company; GTA not opting forward charge; import of services from non-resident). 3. Compute RCM tax and time of supply period. 4. Aggregate per period. 5. Compare to 3B 3.1(d). 6. Compare eligible ITC to 4A(2)/(3). 7. Lines where supplier charged GST on invoice for an RCM entry -> SUPPLIER_CHARGED_GST. | W24: MATCHED; RCM_SHORT_PAID: 3.1(d) below expected; RCM_EXCESS_PAID; RCM_ITC_SHORT: ITC not taken; RCM_ITC_EXCESS: ITC above liability/eligible; PERIOD_SHIFT: paid in another period; SUPPLIER_CHARGED_GST: forward-charge GST on RCM service; UNMAPPED_HEAD: GL head likely RCM but not in master; SELF_INVOICE_MISSING: unregistered supplier without self-invoice | X24: MATCHED=Low; RCM_SHORT_PAID=Critical; RCM_EXCESS_PAID=Medium; RCM_ITC_SHORT=Medium; RCM_ITC_EXCESS=Critical; PERIOD_SHIFT=Medium; SUPPLIER_CHARGED_GST=High; UNMAPPED_HEAD=Medium; SELF_INVOICE_MISSING=High | Y24: tolerance_inr=10; rcm_master_version=; gta_default_rate_pct=5; tos_days=60 | Z24: Party GSTIN status and constitution present; rates as per master by date; import of services flagged by foreign party. | AA24: exception_id; rule_id; client_id; gstin; period; doc_a_ref (file+row); doc_b_ref; match_key; match_pass (exact/fuzzy); category; severity; field_name; value_a; value_b; difference; tolerance_applied; suggested_action; legal_reference; status (Open/Under review/Resolved/Accepted-as-is); reviewer; review_comment; created_at; gl_head; rcm_entry; expected_tax; reported_tax; tos_period | AB24: Client 27, Aug-2025. GL: Freight (GTA, individual unregistered) 1,00,000 paid 10-08-2025 -> RCM 5% = 5,000 (CGST 2,500 SGST 2,500); Legal fees (advocate, 27) 50,000 -> 18% = 9,000 (4,500+4,500); Director sitting fees 30,000 -> 5,400; Rent of shop from unregistered owner 40,000 -> 7,200; AWS (non-resident) 2,00,000 -> IGST 36,000. Expected: CGST 4,500+... -> CGST 2,500+4,500+2,700+3,600 = 13,300; SGST 13,300; IGST 36,000. 3B 3.1(d): CGST 10,000 SGST 10,000 IGST 36,000 -> RCM_SHORT_PAID CGST 3,300, SGST 3,300 (rent entry missed). | AC24: GTA that opted forward charge (declaration on file) charging 18% on invoice -> not RCM, no exception. | AD24: Legal fees paid to advocate by an individual (non-business entity client) -> not RCM; rule only runs where client is a business entity (params). | AE24: Rent of commercial property from unregistered landlord missed (new from 10.10.2024); GTA rate confusion after 22.09.2025; director remuneration (employees – not RCM) vs sitting fees; import of software subscriptions; time of supply 60-day rule ignored; RCM paid via ITC (not allowed). | AF24: RCM_SHORT_PAID: pay in cash via next 3B 3.1(d) with s.50 interest from due date of original period; claim ITC in same return if eligible; issue self-invoice for unregistered suppliers. | AG24: def rc_gst_019(gl, g3b, master, p): lines = gl.merge(master, on='gl_head') lines = lines[lines.apply(lambda r: master_conditions_ok(r), axis=1)] lines['tos'] = np.minimum(lines.payment_date.fillna(date.max), lines.invoice_date + timedelta(days=p.tos_days)) lines['period'] = lines.tos.map(period_of) lines[['igst','cgst','sgst']] = lines.apply(split_heads_by_state, axis=1) exp = lines[lines.period==p.period][['igst','cgst','sgst']].sum() out = [] for h in ['igst','cgst','sgst']: d = exp[h] - g3b['3_1_d'][h] if d > p.tolerance_inr: out.append(exc('RCM_SHORT_PAID', head=h, diff=d)) elif d < -p.tolerance_inr: out.append(exc('RCM_EXCESS_PAID', head=h, diff=d)) out += [exc('SUPPLIER_CHARGED_GST', r) for r in lines if r.gst_charged_on_invoice > 0] out += [exc('UNMAPPED_HEAD', h) for h in suspect_heads(gl, master)] return out | AH24: TaxRoutine – RCM services notification consolidated | https://taxroutine.com/repository/gst-notifications/rcm-services/ | N.13/2017-CT(Rate) as amended (9/2024, 7/2025) ClearTax – RCM on renting of commercial property | https://cleartax.in/s/rcm-on-rent-of-commercial-property-under-gst | from 10.10.2024; composition excluded 16.01.2025 GST Council FAQ on GST 2.0 rate changes | https://gstcouncil.gov.in/sites/default/files/2025-09/faq.pdf | FAQ 60 (GTA 5%/18%) | AI24: RCM entry list from secondary consolidation (TaxRoutine) and gst.json GST-021; specific conditions (e.g., legal services exemption for small business entities, security services exclusions) need CA confirmation. Rate per entry must be taken from the rate master as on time of supply. Time of supply 60-day rule (s.13(3)) from statute knowledge.
A25: RC-GST-020 | B25: reconciliation_rule | C25: GST – Reverse charge | D25: RCM liability/ITC statement: 3B 3.1(d) paid vs 4A(2)+4A(3) ITC claimed (ledger validation) | E25: Verified – secondary source only | F25: Check RCM ITC claimed never exceeds RCM tax actually paid (cumulative, by head), as enforced by GSTN's RCM Liability/ITC Statement. | G25: GSTR3B | H25: RCM_STMT | J25: tax period (month), running balance | K25: GSTN RCM Liability/ITC Statement – monthly filers from August 2024, QRMP from Jul-Sep 2024 quarter (advisory 23.08.2024; opening balance facility); GSTN advisory No. 643 dt 29.12.2025 – hard validation: 4A(2)+4A(3) ITC <= 3.1(d) RCM liability of the period + RCM ledger closing balance (activation date not confirmed); CGST s.16, s.49(4). | L25: All taxpayers paying RCM. | M25: 2024-08-01 | O25: GSTR-3B series 3.1(d), 4A(2), 4A(3); RCM Liability/ITC Statement download (opening, liability paid, ITC claimed, closing). | P25: GSTR3B.return_period = RCM_STMT.ret_period | Q25: Period MMYYYY. | R25: Per period per head. | S25: GSTR3B.3_1_d_h vs RCM_STMT.liability_h; GSTR3B.4A2_h + GSTR3B.4A3_h vs RCM_STMT.itc_h; recomputed closing vs RCM_STMT.closing_h | T25: Rs 1 per head (implementation choice); negative closing – zero tolerance. | U25: closing_h = opening_h + liability_3_1_d_h − itc_4A2_4A3_h; negative if closing_h < 0 (ITC claimed exceeds RCM paid) | V25: 1. Start with opening balance (declared). 2. Roll forward. 3. Negative -> RCM_ITC_EXCEEDS_PAID. 4. Compare with portal statement. 5. Positive closing persisting > 12 months -> ITC_NOT_CLAIMED_STALE (may lapse u/s 16(4)). | W25: MATCHED; RCM_ITC_EXCEEDS_PAID; ROLLFORWARD_DIFF; ITC_NOT_CLAIMED_STALE | X25: MATCHED=Low; RCM_ITC_EXCEEDS_PAID=Critical; ROLLFORWARD_DIFF=Medium; ITC_NOT_CLAIMED_STALE=Medium | Y25: tax_tolerance_inr=1; stale_months=12 | Z25: Periods continuous from statement start. | AA25: exception_id; rule_id; client_id; gstin; period; doc_a_ref (file+row); doc_b_ref; match_key; match_pass (exact/fuzzy); category; severity; field_name; value_a; value_b; difference; tolerance_applied; suggested_action; legal_reference; status (Open/Under review/Resolved/Accepted-as-is); reviewer; review_comment; created_at; head; opening; liability; itc; closing | AB25: CGST: opening 0; Aug 3.1(d) 10,000, 4A(3) 13,300 -> closing −3,300 -> RCM_ITC_EXCEEDS_PAID (ITC on unpaid rent RCM). | AC25: 3.1(d) 5,000; ITC 5,000 -> closing 0 MATCHED. | AD25: ITC on RCM paid in previous month claimed this month: opening 2,000 + 0 − 2,000 = 0 -> OK. | AE25: ITC claimed on RCM entries before payment; import-of-services IGST put in 4A(3) instead of 4A(2) (head ok but row wrong); opening balance not declared. | AF25: Pay additional RCM in 3.1(d) or reduce RCM ITC; interest under s.50(3) if excess ITC utilised. | AG25: def rc_gst_020(g3b_series, stmt, p): out = []; bal = dict(stmt.opening) for per in periods(g3b_series): for h in ['igst','cgst','sgst','cess']: bal[h] += g3b_series[per]['3_1_d'][h] - g3b_series[per]['4A2'][h] - g3b_series[per]['4A3'][h] if bal[h] < -p.tax_tolerance_inr: out.append(exc('RCM_ITC_EXCEEDS_PAID', period=per, head=h, value=bal[h])) if abs(bal[h] - stmt.closing(per, h)) > p.tax_tolerance_inr: out.append(exc('ROLLFORWARD_DIFF', period=per, head=h)) return out | AH25: TaxGuru – ITC reclaim ledger & RCM ledger hard validations | https://taxguru.in/goods-and-service-tax/gstn-itc-reclaim-ledger-rcm-ledger-hard-validations-block-gstr-3b-filing.html | advisory 29.12.2025: 4D(1) <= reclaim balance + 4B(2) current; 4A(2)+4A(3) <= 3.1(d) + RCM ledger balance Busy – GSTR-3B hard block survival guide (July 2026) | https://busy.in/business-updates/how-to-fix-gstr-3b-hard-block/ | Advisory No. 643 dt 29.12.2025; activation date not stated Taxo – GSTN advisory 29.12.2025 on ECRRS & RCM liability/ITC statement | https://taxo.online/latest-news/29-12-2025-gstn-has-issued-an-advisory-on-electronic-credit-reversal-and-re-claimed-statement-rcm-liability-itc-statement/ | seen in search results | AI25: NEW DOC CODE: RCM_STMT (GST portal RCM Liability/ITC Statement) – added because no fixed code represents it (ELL is the liability ledger). Activation of hard blocking not confirmed.
A26: RC-GST-021 | B26: reconciliation_rule | C26: GST – Payment & ledgers | D26: GSTR-3B tax paid (Table 6.1) vs ECL/ECRL/ELL – cash vs credit utilisation and order (s.49, Rule 88A) | E26: Verified – secondary source only | F26: Check that the tax paid in GSTR-3B by cash and by each ITC head ties to debits in the cash and credit ledgers and the liability ledger, that cash-only items (RCM, interest, late fee) were paid in cash, and that the cross-utilisation order was followed. | G26: GSTR3B | H26: ECL | I26: ECRL | J26: tax period (month) | K26: CGST Act s.49(2)-(5) (ITC utilisation; IGST credit first for IGST then CGST/SGST; CGST credit not for SGST and vice versa), s.49(4) and s.49(1) (cash ledger), s.49A (IGST credit to be fully utilised before CGST/SGST credit), s.49B; Rule 88A (inserted N.16/2019-CT: IGST credit may be used for CGST/SGST in any order/proportion but must be exhausted first); Circular 98/17/2019-GST; Rule 86 (ECRL), Rule 87 (ECL), Rule 85 (ELL); RCM liability payable only in cash (s.49(4) read with definition of output tax). | L26: All regular taxpayers. | M26: 2019-03-29 | O26: GSTR-3B Table 6.1 (tax payable, paid through ITC by head, paid in cash, interest, late fee); ECL, ECRL, ELL downloads for the period (debit entries with reference to return ARN/date). | P26: GSTR3B.return_period = ECL.tax_period; GSTR3B.arn = ECL.reference_no; GSTR3B.arn = ECRL.reference_no; GSTR3B.arn = ELL.reference_no | Q26: ARN uppercase; ledger debit description parsed for return period (implementation choice). | R26: Per period per head and per payment mode (cash/ITC by source head). | S26: GSTR3B.6_1.paid_cash_h vs ECL.debit_tax_h (tax); GSTR3B.6_1.paid_itc_from_x_to_y vs ECRL.debit_h; GSTR3B.6_1.interest_h vs ECL.debit_interest_h; GSTR3B.6_1.latefee_h vs ECL.debit_fee_h; GSTR3B.6_1.tax_payable_h vs ELL.liability_created_h (liability created) | T26: Rs 0 (system ledgers) – any difference indicates wrong file/period; Rs 1 for rounding in manual inputs (implementation choice). | U26: rcm_cash_check: paid_cash_h >= rcm_liability_h (3.1(d)) + interest_h + latefee_h; order_check: if IGST ITC closing balance > 0 after set-off while CGST/SGST credit was used for any liability -> s.49A breach; ledger_check: ECRL.opening_h − debits_h + credits_h = ECRL.closing_h | V26: 1. Read 6.1 per head. 2. Match to ledger debits by ARN. 3. Compare amounts. 4. Check RCM + interest + late fee paid only in cash. 5. Check IGST credit exhausted before CGST/SGST credit used (s.49A, Rule 88A). 6. Check CGST credit never used for SGST/UTGST and vice versa. 7. Check ledger arithmetic. 8. Optimisation note: compute minimum cash outflow possible (GST-029 algorithm) and report saving (info). | W26: MATCHED; CASH_DEBIT_DIFF; CREDIT_DEBIT_DIFF; LIABILITY_DIFF; RCM_PAID_BY_ITC: cash paid < RCM liability; ORDER_BREACH: s.49A/Rule 88A order not followed; CROSS_HEAD_BREACH: CGST<->SGST cross use; LEDGER_ARITH: ledger balance does not roll; SUBOPTIMAL_CASH: more cash paid than needed (info) | X26: MATCHED=Low; CASH_DEBIT_DIFF=High; CREDIT_DEBIT_DIFF=High; LIABILITY_DIFF=High; RCM_PAID_BY_ITC=Critical; ORDER_BREACH=High; CROSS_HEAD_BREACH=Critical; LEDGER_ARITH=Medium; SUBOPTIMAL_CASH=Low | Y26: tolerance_inr=0 | Z26: Ledgers cover the 3B filing date; heads mapped (tax/interest/penalty/fee/others in ECL). | AA26: exception_id; rule_id; client_id; gstin; period; doc_a_ref (file+row); doc_b_ref; match_key; match_pass (exact/fuzzy); category; severity; field_name; value_a; value_b; difference; tolerance_applied; suggested_action; legal_reference; status (Open/Under review/Resolved/Accepted-as-is); reviewer; review_comment; created_at; head; payment_mode; source_head; ledger_ref | AB26: Aug-2025 liability: IGST 50,000, CGST 40,000, SGST 40,000; RCM CGST 3,000 SGST 3,000 (included). ITC: IGST 60,000, CGST 10,000, SGST 10,000. Correct: IGST credit -> IGST 50,000, balance 10,000 -> CGST/SGST (e.g. CGST 10,000); CGST credit 10,000 -> CGST (forward charge 37,000 − 10,000 IGST −10,000 = 17,000 left after RCM 3,000 cash); 3B shows CGST credit used 10,000 while IGST credit 10,000 still unused -> ORDER_BREACH. RCM 3,000 paid from CGST credit -> RCM_PAID_BY_ITC. | AC26: Cash debit 25,000 CGST equals 6.1 paid in cash 25,000 -> MATCHED. | AD26: Ledger file from a different GSTIN -> abort INPUT_ERROR. | AE26: Manual set-off on older portal versions; DRC-03 payments mixed with 3B debits; interest paid under wrong head; cash ledger balance in 'others' minor head. | AF26: RCM_PAID_BY_ITC: pay RCM again in cash, re-credit ITC is not automatic – CA review (refund/adjustment). ORDER_BREACH: note – generally portal enforces; review for older periods. | AG26: def rc_gst_021(g3b, ecl, ecrl, ell, p): out = [] for h in ['igst','cgst','sgst','cess']: if abs(g3b.t6_1.cash[h] - ecl.debits(g3b.arn, h, minor='tax')) > p.tolerance_inr: out.append(exc('CASH_DEBIT_DIFF', head=h)) if abs(sum(g3b.t6_1.itc[(s,h)] for s in SRC) - ecrl.debits_for_liability(g3b.arn, h)) > p.tolerance_inr: out.append(exc('CREDIT_DEBIT_DIFF', head=h)) if g3b.t6_1.cash[h] + 1 < g3b['3_1_d'][h]: out.append(exc('RCM_PAID_BY_ITC', head=h)) if g3b.t6_1.itc[('cgst','sgst')] > 0 or g3b.t6_1.itc[('sgst','cgst')] > 0: out.append(exc('CROSS_HEAD_BREACH')) if igst_credit_left_after(g3b, ecrl) > 0 and (g3b.t6_1.itc_used('cgst') + g3b.t6_1.itc_used('sgst')) > 0: out.append(exc('ORDER_BREACH')) opt = optimise_cash(g3b.liability, ecrl.opening_plus_current) if g3b.t6_1.cash_total - opt > 1: out.append(exc('SUBOPTIMAL_CASH', diff=g3b.t6_1.cash_total - opt)) return out | AH26: Taxmann – ITC utilisation guide | https://www.taxmann.com/post/blog/guide-to-maximizing-the-utilization-of-gst-input-tax-credit/ | s.49(5), 49A, 49B, Rule 88A, Circ 98/17/2019 | AI26: Utilisation order verified via Taxmann (GST-029). Ledger field names are implementation mapping of portal downloads. Rule 86B restriction (from 01.02.2026 limited to pan masala/tobacco manufacturers per N.20/2025-CT) not modelled here.
A27: RC-GST-022 | B27: reconciliation_rule | C27: GST – Interest | D27: Interest u/s 50 – computed (late 3B cash portion, short payment, wrong ITC utilised) vs paid (ELL/DRC-03) | E27: Partially verified | F27: Recompute interest on delayed returns, short-paid tax and wrongly availed & utilised ITC, and compare with interest actually paid via GSTR-3B 5.1/DRC-03 and recorded in the liability ledger. | G27: GSTR3B | H27: ELL | I27: DRC03 | J27: tax period (month) of the liability; payment date | K27: CGST Act s.50(1) and proviso (interest on delayed tax; for return filed after due date, only on tax paid by debiting cash ledger – w.e.f. 01.07.2017 per FA 2021 / N.16/2021-CT – not re-verified), s.50(3) (substituted by FA 2022 retrospectively from 01.07.2017 – interest only where ITC wrongly availed and utilised; N.9/2022-CT); Notification 13/2017-CT (rates: 18% s.50(1); s.50(3) rate 24% originally, substituted to 18% retrospectively by FA 2022 per secondary – conflicting); Rule 88B (manner of computing interest, N.14/2022-CT); s.170 rounding. | L27: All taxpayers with late filing, short payment or wrong ITC utilisation. | M27: 2017-07-01 | O27: 3B filing dates and 6.1 cash payments; due dates master (GST-025 incl. QRMP 22nd/24th); ECL deposits with dates (for proviso – cash balance before due date); DRC-03 list (cause, period, interest paid); outputs of RC-GST-007/014/017/018 for short payment and excess ITC. | P27: GSTR3B.return_period = ELL.tax_period; DRC03.period_from..period_to covers GSTR3B.return_period | Q27: Periods MMYYYY; DRC-03 period range expanded to months (implementation choice). | R27: Per period per head; DRC-03 interest per period per head. | S27: computed_interest_h vs GSTR3B.5_1_interest_h + DRC03.interest (+ ELL interest debits) | T27: Rs 1 per head (s.170 rounding to nearest rupee) – then Rs 10 implementation tolerance for day-count convention. | U27: late_return: base_h = cash_paid_h − ecl_balance_h_available_on_due_date_held_till_debit; days = filing_date − due_date; interest = base_h × 18% × days/365. short_payment: interest = short_h × 18% × days(due_date → payment_date)/365. wrong_itc (Rule 88B(3)): utilised_h = max(0, wrong_itc_h − ecrl_balance_h(t)) tracked; interest = utilised × rate_503 × days(utilisation → reversal)/365; round each final figure per s.170. | V27: 1. For each 3B: compute delay days. 2. Determine cash portion; exclude cash ledger balance credited on/before due date that remained till debit (Rule 88B(1) proviso). 3. Compute interest. 4. Add short payment interest from RC-GST-007 timing/short items. 5. Add s.50(3) interest from RC-GST-014/018 excess ITC where utilised (ECRL balance fell below wrong ITC). 6. Sum paid interest from 3B 5.1 and DRC-03. 7. Compare. | W27: MATCHED; INTEREST_SHORT_PAID; INTEREST_EXCESS_PAID; INTEREST_NOT_PAID: due but zero paid; RATE_POLICY: s.50(3) rate assumption applied (info) | X27: MATCHED=Low; INTEREST_SHORT_PAID=High; INTEREST_EXCESS_PAID=Low; INTEREST_NOT_PAID=High; RATE_POLICY=Low | Y27: rate_50_1_pct=18; rate_50_3_pct=18; day_count=exclusive_due_inclusive_payment; year_days=365; tolerance_inr=10 | Z27: Due date per period and per QRMP group; filing date present; cash deposit dates present for proviso. | AA27: exception_id; rule_id; client_id; gstin; period; doc_a_ref (file+row); doc_b_ref; match_key; match_pass (exact/fuzzy); category; severity; field_name; value_a; value_b; difference; tolerance_applied; suggested_action; legal_reference; status (Open/Under review/Resolved/Accepted-as-is); reviewer; review_comment; created_at; head; base; days; rate; computed; paid; diff | AB27: Aug-2025 3B due 20-09-2025, filed 05-10-2025 (15 days). Cash paid CGST 20,000, SGST 20,000; ECL had CGST 5,000 deposited 15-09-2025 held till debit -> base CGST 15,000. Interest CGST = 15,000 × 18% × 15/365 = 110.96 -> 111; SGST base 20,000 -> 147.95 -> 148. Paid in 3B 5.1: CGST 100, SGST 148 -> INTEREST_SHORT_PAID CGST 11. | AC27: 3B filed on due date -> no interest; paid 0 -> MATCHED. | AD27: ITC wrongly availed 50,000 IGST but ECRL balance never fell below 50,000 until reversal -> utilised 0 -> no s.50(3) interest. | AE27: Portal-computed interest is system-calculated for late 3B (auto-populated) – manual DRC-03 interest for short payments often missed; QRMP state group due date wrong; interest computed on gross liability not cash portion. | AF27: Pay shortfall via DRC-03 (cause: voluntary – interest) and record; keep working papers. | AG27: def rc_gst_022(g3b_series, ecl, drc03, extras, p): out = [] for g in g3b_series: due = due_date(g.ret_period, p.client_qrmp_state_group) days = max(0, (g.filing_date - due).days) comp = {} for h in TAXH: base = max(0, g.t6_1.cash[h] - ecl.balance_held(h, from_=due, till=g.filing_date)) comp[h] = base * p.rate_50_1_pct/100 * days/p.year_days comp[h] += extras.short_payment_interest(g.ret_period, h, p) + extras.wrong_itc_interest(g.ret_period, h, p) paid = g.t5_1.interest[h] + drc03.interest(g.ret_period, h) d = round_s170(comp[h]) - paid if d > p.tolerance_inr: out.append(exc('INTEREST_NOT_PAID' if paid==0 else 'INTEREST_SHORT_PAID', period=g.ret_period, head=h, diff=d)) elif d < -p.tolerance_inr: out.append(exc('INTEREST_EXCESS_PAID', period=g.ret_period, head=h, diff=d)) return out | AH27: Rule 88B CGST Rules (Chhattisgarh GST dept copy) | https://www.cggst.com/uploads/document/1754119329-rule-88b.pdf | Rule 88B(1)-(3) Masters India – interest on wrongly availed ITC s.50(3) | https://www.mastersindia.co/blog/interest-on-wrongly-availed-itc-under-section-503-gst/ | N.9/2022-CT; retrospective 01.07.2017 TaxTMI forum – FA 2022 substitution of 18% for 24% | https://www.taxtmi.com/forum/issue?id=118761 | Finance Act 2022 s.116 & Sixth Schedule (secondary) Section 170 CGST Act (Chhattisgarh GST dept copy) | https://www.cggst.com/uploads/document/1752824769-section-170.pdf | rounding to nearest rupee TaxHeal – GSTR-3B QRMP due dates 22nd/24th | https://www.taxheal.com/?p=89244 | N.82/2020-CT state groups | AI27: s.50(3) rate (18% vs 24%) conflicting across sources (see gst.json GST-022) – default 18% param, CA to confirm. Day-count convention is implementation choice. s.50(1) proviso retrospective amendment notification not re-verified. s.50(3) rate resolved to 18% (see GST-022, verification 13-10-2026).
A28: RC-GST-023 | B28: reconciliation_rule | C28: GST – Late fee | D28: Late fee u/s 47 computed vs paid (GSTR-3B, GSTR-1, GSTR-9) | E28: Partially verified | F28: Recompute late fee for late GSTR-3B/GSTR-1/GSTR-9 and compare with fee actually paid (cash ledger / return). | G28: GSTR3B | H28: ECL | I28: GSTR9 | J28: tax period / FY | K28: CGST Act s.47(1) (Rs 100/day per Act, capped), s.47(2) (annual return: Rs 100/day, max 0.25% of turnover in State/UT); N.19/2021-CT (GSTR-3B from June 2021 period) and N.20/2021-CT (GSTR-1): Rs 25+25/day (nil: 10+10), caps Rs 500 (nil), 2,000 (AATO up to Rs 1.5 cr), 5,000 (Rs 1.5–5 cr), 10,000 (> Rs 5 cr) total; N.7/2023-CT (GSTR-9 from FY 2022-23: AATO <= Rs 5 cr Rs 25+25/day cap 0.02%+0.02%; Rs 5–20 cr Rs 50+50/day cap 0.02%+0.02%; > Rs 20 cr statutory). | L28: Taxpayers filing returns after due date. | M28: 2021-06-01 | O28: Due dates master; filing dates (GSTR-1, 3B, 9, 9C); nil-return flag; AATO of preceding FY; turnover in State for GSTR-9; ECL late fee debits. | P28: GSTR3B.return_period = ECL.tax_period (and fy(tax_period) when matched to GSTR9.financial_year) (minor head 'fee'); GSTR9.financial_year = ECL.tax_period (and fy(tax_period) when matched to GSTR9.financial_year) | Q28: Period MMYYYY / FY YYYY-YY. | R28: Per return per period per head (CGST, SGST). | S28: computed_fee_h vs paid_fee_h | T28: Exact (Rs 0) – fee is in whole rupees. | U28: fee_total = min(days_late × per_day_total, cap_total); split 50:50 CGST/SGST; GSTR-9: fee_head = min(days × per_day_head, cap_pct_head × state_turnover) | V28: 1. days_late = filing_date − due_date (>0). 2. Select slab (nil / AATO band). 3. Compute and cap. 4. GSTR-1 late fee is collected via the next GSTR-3B (portal practice) – compare against 3B 5.1 fee field of the next period. 5. Compare paid. 6. 57th Council late-fee waiver recommendation (08.10.2026) not applied unless notified. | W28: MATCHED; FEE_SHORT_PAID; FEE_EXCESS_PAID; FEE_NOT_PAID | X28: MATCHED=Low; FEE_SHORT_PAID=Medium; FEE_EXCESS_PAID=Low; FEE_NOT_PAID=Medium | Y28: aato_prev_fy_inr=; per_day_3b_total=50; per_day_nil_total=20; caps_total=500/2000/5000/10000; gstr9_bands=per N.7/2023 | Z28: Due date master present; filing date >= period end. | AA28: exception_id; rule_id; client_id; gstin; period; doc_a_ref (file+row); doc_b_ref; match_key; match_pass (exact/fuzzy); category; severity; field_name; value_a; value_b; difference; tolerance_applied; suggested_action; legal_reference; status (Open/Under review/Resolved/Accepted-as-is); reviewer; review_comment; created_at; return_type; days_late; slab; computed; paid | AB28: GSTR-3B Aug-2025 due 20-09-2025 filed 30-10-2025: 40 days × Rs 50 = 2,000; AATO Rs 1 cr -> cap 2,000 -> fee 2,000 (1,000+1,000). Paid 1,000 total -> FEE_SHORT_PAID 1,000. | AC28: Nil 3B filed 60 days late: 60 × 20 = 1,200 -> cap 500 -> fee 500; paid 500 -> MATCHED. | AD28: AATO up to Rs 2 crore and GSTR-9 not filed for FY 2024-25 -> exempt (N.15/2025-CT) -> no fee. | AE28: Late fee waived by amnesty for older periods; GSTR-1 late fee missed; wrong AATO band. | AF28: Short-paid fee: pay via DRC-03/next return; note CA review if amnesty applies. | AG28: def rc_gst_023(filings, ecl, p): out = [] for f in filings: days = max(0, (f.filing_date - f.due_date).days) if f.type in ('GSTR3B','GSTR1'): per = p.per_day_nil_total if f.nil else p.per_day_3b_total cap = 500 if f.nil else cap_by_aato(p.aato_prev_fy_inr) fee = min(days*per, cap) else: fee = gstr9_fee(days, p.aato_prev_fy_inr, f.state_turnover) paid = ecl.fee_debits(f) if fee - paid > 0: out.append(exc('FEE_NOT_PAID' if paid==0 else 'FEE_SHORT_PAID', f, diff=fee-paid)) elif paid - fee > 0: out.append(exc('FEE_EXCESS_PAID', f, diff=paid-fee)) return out | AH28: TaxHeal – N.19/2021-CT late fee caps GSTR-3B | https://www.taxheal.com/?p=89438 | caps from June 2021 period Lexplosion – GSTR-9 late fee reduced (N.7/2023-CT) | https://lexplosion.in/late-fees-for-filing-annual-return-in-form-gstr-9-reduced-from-fy-2022-23-onwards/ | N.7/2023-CT dt 31.03.2023 CalcGuru – GST late fee calculator | https://calcguru.in/gst-late-fee-calculator/ | secondary summary of caps TaxHeal – N.15/2025-CT annual return exemption | https://www.taxheal.com/?p=105269 | AATO up to Rs 2 crore exempt from GSTR-9 from FY 2024-25 | AI28: Caps from secondary reproductions (GST-023/024). Whether GSTR-9 late fee runs until GSTR-9C filed is open (gst.json). GSTR-1 late fee collection route via 3B is portal practice – CA to confirm.
A29: RC-GST-024 | B29: reconciliation_rule | C29: GST – Annual return | D29: GSTR-9 Tables 4, 5, 9, 10, 11 vs sum of GSTR-1/1A and GSTR-3B for the FY | E29: Partially verified | F29: Tie the annual return outward-supply and tax-payable tables to the sum of the year's GSTR-1/1A/IFF and GSTR-3B, including next-year amendments reported in Tables 10/11. | G29: GSTR9 | H29: GSTR1 | I29: GSTR3B | J29: financial year | K29: CGST Act s.44; Rule 80; FORM GSTR-9 (Tables 4, 5 auto-populated from GSTR-1/1A/IFF; Table 9 from GSTR-3B Table 6.1 net liability – auto-populated if positive, editable); GSTR-9 for FY 2024-25 onward includes GSTR-1A data (GSTN FAQ); N.15/2025-CT (AATO up to Rs 2 crore exempt from FY 2024-25). | L29: Taxpayers required to file GSTR-9 (AATO > Rs 2 crore from FY 2024-25). | M29: 2017-07-01 | O29: All GSTR-1/1A/IFF and GSTR-3B of the FY; GSTR-1 amendments of next FY up to the cut-off pertaining to the FY; GSTR-9 JSON/PDF. | P29: GSTR9.financial_year = fy(GSTR1.return_period); GSTR9.financial_year = fy(GSTR3B.return_period) | Q29: FY YYYY-YY. | R29: FY totals per table row per head. | S29: GSTR9.4A..4L vs Σ GSTR1 (B2C, B2B, zero-rated, deemed, advances, CN/DN, amendments); GSTR9.5 (exempt/nil/non-GST, zero-rated without tax) vs Σ GSTR1 Table 8 & 6A WOPAY; GSTR9.9.tax_payable_h vs Σ GSTR3B.6_1 payable_h; GSTR9.9.paid_cash_h vs Σ GSTR3B cash; GSTR9.9.paid_itc_h vs Σ GSTR3B ITC; GSTR9.10/11 vs GSTR1 amendments in next FY | T29: Rs 1 per head per row (implementation choice). | U29: diff_row_h = GSTR9_row_h − Σ_source_row_h; total_turnover_9 = 4N + 5N; tax_gap = Σ GSTR9.4_tax − Σ GSTR9.9_paid | V29: 1. Aggregate GSTR-1/1A/IFF by table for FY. 2. Compare Table 4 rows and Table 5 rows. 3. Aggregate 3B 6.1. 4. Compare Table 9. 5. Table 4 tax (liability declared) vs Table 9 paid -> if 4 > 9 then additional liability (pay via DRC-03 – Table 14). 6. Tables 10/11 vs next-FY amendments. 7. HSN Table 17 vs Σ GSTR-1 Table 12 (download facility). | W29: MATCHED; ROW_DIFF: row differs from source returns; LIABILITY_UNPAID: Table 4 tax > Table 9 paid; EXCESS_PAID: paid > declared; AMENDMENT_DIFF: Tables 10/11 differ from next-year amendments; HSN_DIFF: Table 17 differs | X29: MATCHED=Low; ROW_DIFF=Medium; LIABILITY_UNPAID=Critical; EXCESS_PAID=Medium; AMENDMENT_DIFF=Medium; HSN_DIFF=Low | Y29: tax_tolerance_inr=1; aato_inr= | Z29: All 12 months (or 4 quarters) present; GSTR-9 is for same GSTIN. | AA29: exception_id; rule_id; client_id; gstin; period; doc_a_ref (file+row); doc_b_ref; match_key; match_pass (exact/fuzzy); category; severity; field_name; value_a; value_b; difference; tolerance_applied; suggested_action; legal_reference; status (Open/Under review/Resolved/Accepted-as-is); reviewer; review_comment; created_at; gstr9_table; row; head | AB29: FY 2024-25: Σ GSTR-1 B2B IGST 12,00,000; GSTR-9 4B IGST 12,00,000 -> MATCHED. GSTR-9 Table 4 total CGST 8,00,000; Σ 3B paid CGST 7,85,000 -> LIABILITY_UNPAID 15,000 (pay via DRC-03 with interest). | AC29: All rows equal -> MATCHED. | AD29: AATO Rs 1.8 crore FY 2024-25 -> GSTR-9 not required; rule returns NOT_APPLICABLE. | AE29: Next-year amendments not included; GSTR-1A not included for FY 2024-25+; advances adjusted; ECO supplies; Table 9 auto-populates only if positive. | AF29: LIABILITY_UNPAID: pay via DRC-03 before filing GSTR-9; report in Table 14. | AG29: def rc_gst_024(g9, g1_fy, g3b_fy, g1_next, p): if p.aato_inr <= 2e7 and fy_ge(g9.fy, '2024-25'): return [exc('NOT_APPLICABLE')] src4 = map_gstr1_to_g9_t4(g1_fy, g1_next) out = compare_rows(g9.t4, src4, p.tax_tolerance_inr, 'ROW_DIFF') + compare_rows(g9.t5, map_gstr1_to_g9_t5(g1_fy), p.tax_tolerance_inr, 'ROW_DIFF') out += compare_rows(g9.t9, sum_3b_6_1(g3b_fy), p.tax_tolerance_inr, 'ROW_DIFF') for h in TAXH: d = g9.t4.tax_total[h] - g9.t9.paid_total[h] if d > p.tax_tolerance_inr: out.append(exc('LIABILITY_UNPAID', head=h, diff=d)) return out | AH29: VJM Global – GSTN FAQs on GSTR-9/9C FY 2024-25 | https://www.vjmglobal.com/blog/gstn-issued-faqs-on-newly-released-form-gstr-9-9c-for-fy-2024-25 | 8A from 2B; 8C; 6A1; 8H1; Table 4/5 from GSTR-1/1A/IFF; Table 9 from 3B 6.1 GSTZen – FAQs on GSTR-9/9C changes FY 2024-25 | https://gstzen.in/a/faqs-on-gstr-9-9c-changes-fy-2024-25.html | Tables 6A1, 8H1; advisory 15.10.2025 TaxHeal – N.15/2025-CT annual return exemption | https://www.taxheal.com/?p=105269 | AATO up to Rs 2 crore exempt from GSTR-9 from FY 2024-25 | AI29: Auto-population sources verified via VJM summary of GSTN FAQ (FY 2024-25). Detailed row mapping (4A-4L, 5A-5N) from form knowledge – CA to confirm with current form version.
A30: RC-GST-025 | B30: reconciliation_rule | C30: GST – Annual return – ITC | D30: GSTR-9 ITC tables (6, 7, 8A–8K, 13) vs GSTR-2B, GSTR-3B and books | E30: Partially verified | F30: Tie ITC claimed in Table 6 to the year's GSTR-3B, Table 8A to GSTR-2B, and explain the 8A–8B difference (8D) and lapsed credits (8E/8F), including next-year claims (8C, 6A1, 8H1). | G30: GSTR9 | H30: GSTR2B | I30: GSTR3B | J30: financial year | K30: CGST Act s.44, s.16(4); FORM GSTR-9 Tables 6, 7, 8, 13; GSTN FAQ for FY 2024-25: Table 8A auto-populated from GSTR-2B (FY invoices appearing in 2B April–October of next year; excludes previous-FY invoices), Table 8C = current-FY ITC claimed in next FY's 3B 4A(5) within time; Table 6A1 = previous-year ITC claimed in current year; Table 8H1 = import IGST of FY claimed next FY; Rule 37/37A re-claims not in 6A1. | L30: GSTR-9 filers. | M30: 2024-04-01 | O30: GSTR-9 Table 6/7/8/13; all GSTR-2B of FY and Apr–Oct next FY ('Table 8A document details' Excel); all 3B of FY and next FY up to 30 Nov; books ITC register. | P30: GSTR9.financial_year = fy(GSTR3B.return_period); GSTR9.8A document list = GSTR2B documents (ctin, inum, dt) | Q30: Implementation choice: (1) Invoice/document number – uppercase, trim, collapse internal spaces, remove characters other than A-Z 0-9 '/' '-'; exact pass on this form. (2) Fuzzy pass key = strip '/', '-', spaces; strip leading zeros of each numeric run; strip common FY tokens (e.g. '2025-26', '25-26', '2526', 'FY26') – only if the remainder is still >= 3 characters. Law (Rule 46(b)) allows up to 16 characters, unique per FY. (3) GSTIN – uppercase, trim, validate 15-char pattern ^[0-9]{2}[A-Z]{5}[0-9]{4}[A-Z][1-9A-Z]Z[0-9A-Z]$ and check digit (see GST-001). (4) Dates – parse DD-MM-YYYY, DD/MM/YYYY, DD-MON-YY, YYYY-MM-DD, Excel serials into ISO date. (5) Amounts – Decimal, 2 dp, negative for credit notes only after doc-type mapping. | R30: FY per head; document level for 8A detail. | S30: GSTR9.6A_h vs Σ GSTR3B.4A_h (FY); GSTR9.6B..6H split vs books classification (inputs/capital goods/input services); GSTR9.7_h (reversals) vs Σ GSTR3B.4B_h; GSTR9.8A_h vs Σ GSTR2B ITC (FY docs); GSTR9.8B_h vs 6B+6H; GSTR9.8C_h vs next-FY 3B claims of FY docs; GSTR9.8D = 8A − (8B + 8C); GSTR9.8G vs Σ BoE IGST (imports); GSTR9.13 vs next-FY claims | T30: Rs 1 per head (implementation choice). | U30: 8D_h = 8A_h − (8B_h + 8C_h); 8E (ITC available but not availed) + 8F (ineligible) should explain positive 8D; lapse_h = 8E_h (ITC lost after s.16(4)); 6J (difference) = 6I − 6A (should be 0) | V30: 1. Sum 3B 4A for FY -> compare 6A. 2. Sum 3B 4B -> compare Table 7. 3. Build 8A from 2B documents with doc date in FY (2B periods Apr FY – Oct next FY). 4. 8C from next-FY 3B claims for FY documents (from RC-GST-013 period mapping). 5. Compute 8D; positive 8D must be explained by 8E/8F; negative 8D (claimed more than 2B) -> EXCESS_OVER_2B. 6. Compare 8G with BoE (RC-GST-027). | W30: MATCHED; T6A_DIFF; T7_DIFF; T8A_DIFF; EXCESS_OVER_2B: 8D negative; UNEXPLAINED_8D: positive 8D not explained by 8E/8F; ITC_LAPSED: 8E amount (info); IMPORT_DIFF: 8G vs BoE; SPLIT_DIFF: 6B/6C/6D/6E split differs from books | X30: MATCHED=Low; T6A_DIFF=High; T7_DIFF=High; T8A_DIFF=Medium; EXCESS_OVER_2B=Critical; UNEXPLAINED_8D=Medium; ITC_LAPSED=Medium; IMPORT_DIFF=High; SPLIT_DIFF=Low | Y30: tax_tolerance_inr=1 | Z30: 2B files April FY to October next FY present. | AA30: exception_id; rule_id; client_id; gstin; period; doc_a_ref (file+row); doc_b_ref; match_key; match_pass (exact/fuzzy); category; severity; field_name; value_a; value_b; difference; tolerance_applied; suggested_action; legal_reference; status (Open/Under review/Resolved/Accepted-as-is); reviewer; review_comment; created_at; gstr9_table; head; values | AB30: FY 2024-25 IGST: 8A 10,00,000; 8B (6B+6H) 9,40,000; 8C 30,000 -> 8D = 10,00,000 − 9,70,000 = 30,000; 8E 0, 8F 20,000 -> UNEXPLAINED_8D 10,000. | AC30: 8A 5,00,000 = 8B 4,90,000 + 8C 10,000 -> 8D 0 MATCHED. | AD30: Previous-year (FY 2023-24) invoices claimed in FY 2024-25 -> 6A1, excluded from 8A, no exception. | AE30: RCM and import ITC wrongly in 6B; ITC on 2B documents never claimed (lapsed); next-year claims missed in 8C; Rule 37 re-claims put in 6A1. | AF30: EXCESS_OVER_2B: reverse with interest via DRC-03 (Table 14); UNEXPLAINED_8D: document reasons (blocked credit, IMS rejections). | AG30: def rc_gst_025(g9, g2b_span, g3b_fy, g3b_next, books, p): out = [] for h in HEADS4: if abs(g9.t6A[h] - sum(x['4A'][h] for x in g3b_fy)) > p.tax_tolerance_inr: out.append(exc('T6A_DIFF', head=h)) if abs(g9.t7_total[h] - sum(x['4B1'][h]+x['4B2'][h] for x in g3b_fy)) > p.tax_tolerance_inr: out.append(exc('T7_DIFF', head=h)) a8 = sum_itc(docs_with_fy(g2b_span, g9.fy), h) if abs(g9.t8A[h] - a8) > p.tax_tolerance_inr: out.append(exc('T8A_DIFF', head=h)) d8 = g9.t8A[h] - (g9.t8B[h] + g9.t8C[h]) if d8 < -p.tax_tolerance_inr: out.append(exc('EXCESS_OVER_2B', head=h, diff=d8)) elif d8 - (g9.t8E[h] + g9.t8F[h]) > p.tax_tolerance_inr: out.append(exc('UNEXPLAINED_8D', head=h, diff=d8 - g9.t8E[h] - g9.t8F[h])) return out | AH30: VJM Global – GSTN FAQs on GSTR-9/9C FY 2024-25 | https://www.vjmglobal.com/blog/gstn-issued-faqs-on-newly-released-form-gstr-9-9c-for-fy-2024-25 | 8A from 2B; 8C; 6A1; 8H1; Table 4/5 from GSTR-1/1A/IFF; Table 9 from 3B 6.1 GSTZen – FAQs on GSTR-9/9C changes FY 2024-25 | https://gstzen.in/a/faqs-on-gstr-9-9c-changes-fy-2024-25.html | Tables 6A1, 8H1; advisory 15.10.2025 | AI30: FY 2024-25 Table 8A/8C/6A1/8H1 logic verified via VJM summary of GSTN FAQs. FY 2025-26 GSTR-9 (due 31.12.2026) assumed same – not checked.
A31: RC-GST-026 | B31: reconciliation_rule | C31: GST – Reconciliation statement | D31: GSTR-9C turnover reconciliation: financial statements / trial balance vs GSTR-9 (Table 5–7) | E31: Partially verified | F31: Reconcile turnover in the audited financial statements (per GSTIN) with turnover declared in GSTR-9, listing each adjustment (unbilled revenue, advances, deemed supplies, credit notes, Schedule III items, foreign exchange, etc.). | G31: FS | H31: GSTR9 | I31: TB | J31: financial year | K31: CGST Act s.44 (annual return including self-certified reconciliation statement); Rule 80(3) as amended by N.30/2021-CT (GSTR-9C self-certified, for AATO > Rs 5 crore); FORM GSTR-9C Part II Table 5 (5A turnover per audited FS; adjustments 5B–5N optional for FY 2020-21 per N.30/2021; 5O; 5P; 5Q), Table 6 reasons, Table 7 (taxable turnover), Table 8 reasons. | L31: Taxpayers with AATO > Rs 5 crore (per GSTIN reconciliation). | M31: 2021-08-01 | O31: Audited FS / TB with revenue ledgers mapped to GSTIN (multi-state entities: branch-wise TB); GSTR-9 Tables 4N, 5N, 5M; adjustment schedules (unbilled revenue opening/closing, advances, credit notes post year-end, deemed supply, Schedule III). | P31: FS.entity_pan = GSTR9.gstin[2:12]; FS.fy = GSTR9.financial_year; TB.gstin_branch = GSTR9.gstin | Q31: PAN from GSTIN chars 3-12; GL mapping master (revenue heads -> GST category) – implementation choice. | R31: FY totals per GSTIN; adjustment lines. | S31: FS.turnover_gstin (5A) ± adjustments (5B–5O) vs GSTR9.total_turnover (5Q = 4N + 5N + 10 − 11 per form logic); TB.taxable_turnover_by_rate vs GSTR9 taxable turnover (Table 7) | T31: Rs 1 for arithmetic; unexplained difference reported at Re 1 (implementation choice); CA may set materiality. | U31: unreconciled = FS_turnover_5A + Σ adjustments(signed) − GSTR9_turnover; adjustments examples: + unbilled revenue at beginning, − unbilled revenue at end, + unadjusted advances at end, − unadjusted advances at beginning, + deemed supply (Schedule I), − credit notes accounted after year-end but reported in GSTR-9, − trade discounts not permissible? (CA), ± turnover April–June 2017 n/a, − Schedule III / non-GST items not in GSTR-9 turnover | V31: 1. Derive FS turnover for the GSTIN (TB revenue heads). 2. Load adjustment schedules; compute each adjustment from TB/GL (unbilled revenue, advances). 3. Compute reconciled turnover. 4. Compare with GSTR-9 turnover; residual -> UNRECONCILED. 5. Taxable turnover by rate (Table 7/9) vs GSTR-9 tax: compute tax at rates and compare with paid (Table 9 vs 11 additional liability). | W31: RECONCILED; UNRECONCILED_TURNOVER; ADJ_UNSUPPORTED: adjustment without GL backing; TAXABLE_DIFF: taxable turnover mismatch; ADDITIONAL_LIABILITY: tax on unreconciled taxable turnover (Table 11) | X31: RECONCILED=Low; UNRECONCILED_TURNOVER=High; ADJ_UNSUPPORTED=Medium; TAXABLE_DIFF=High; ADDITIONAL_LIABILITY=Critical | Y31: materiality_inr=1; aato_threshold_inr=50000000 | Z31: FS figures audited/final; multi-GSTIN split totals equal entity FS. | AA31: exception_id; rule_id; client_id; gstin; period; doc_a_ref (file+row); doc_b_ref; match_key; match_pass (exact/fuzzy); category; severity; field_name; value_a; value_b; difference; tolerance_applied; suggested_action; legal_reference; status (Open/Under review/Resolved/Accepted-as-is); reviewer; review_comment; created_at; adjustment_code; amount; gl_reference | AB31: FS revenue (GSTIN 27) 50,00,00,000; unbilled revenue opening 20,00,000, closing 35,00,000; advances closing 10,00,000, opening 5,00,000; CN after year-end 2,00,000 in GSTR-9. Reconciled = 50,00,00,000 + 20,00,000 − 35,00,000 + 10,00,000 − 5,00,000 − 2,00,000 = 49,88,00,000. GSTR-9 turnover 49,80,00,000 -> UNRECONCILED_TURNOVER 8,00,000 (if taxable @18%, ADDITIONAL_LIABILITY 1,44,000). | AC31: Residual 0 -> RECONCILED. | AD31: AATO Rs 4 crore -> 9C not required -> NOT_APPLICABLE. | AE31: Inter-branch supplies (distinct persons) not in FS revenue; other income (scrap, asset sale, rent) taxable but not in revenue from operations; Ind AS adjustments (fair value, significant financing); export incentives; foreign exchange gains. | AF31: Pay additional liability via DRC-03 (Table 11); document adjustments for 9C Table 5/6. | AG31: def rc_gst_026(fs_tb, g9, adj, p): if p.aato_inr <= p.aato_threshold_inr: return [exc('NOT_APPLICABLE')] t5a = revenue_for_gstin(fs_tb, g9.gstin) rec = t5a + sum(a.signed_amount for a in adj) out = [exc('ADJ_UNSUPPORTED', a) for a in adj if not a.gl_ref] d = rec - g9.total_turnover out.append(exc('RECONCILED' if abs(d) <= p.materiality_inr else 'UNRECONCILED_TURNOVER', diff=d)) return out | AH31: ClearTax – revised GSTR-9C from FY 2020-21 | https://cleartax.in/s/revised-gstr-9c-fy-2020-21 | self-certification; N.29/30/2021-CT; Table 5, 9, 11, 12, 14 ClearTax – GSTR-9C reconciliation statement | https://cleartax.in/s/gst-reconciliation-statement-gstr-9c | N.30/2021-CT; > Rs 5 crore | AI31: Self-certification and optional rows verified via ClearTax (N.29/30/2021). Adjustment list is professional practice – CA must confirm sign conventions and current form rows. Ind AS items require judgment.
A32: RC-GST-027 | B32: reconciliation_rule | C32: GST – Reconciliation statement | D32: GSTR-9C ITC reconciliation: books ITC (GL) vs GSTR-9 Table 7J (Table 12) and expense-wise (Table 14) | E32: Partially verified | F32: Reconcile ITC as per audited books with net ITC per GSTR-9, and (optionally) expense-head-wise ITC. | G32: TB | H32: GSTR9 | I32: GL | J32: financial year | K32: Rule 80(3) / FORM GSTR-9C Part IV Table 12 (12A ITC per audited FS/books, 12B ITC booked in earlier FY claimed in current FY, 12C ITC booked in current FY to be claimed in subsequent FY, 12D, 12E ITC per GSTR-9 7J, 12F unreconciled) and Table 14 (optional from FY 2020-21 per N.30/2021-CT). | L32: Taxpayers with AATO > Rs 5 crore. | M32: 2021-08-01 | O32: TB / GL input credit ledgers (IGST/CGST/SGST/cess input), ITC on capital goods, ITC reversal ledgers; GSTR-9 Table 7J (net ITC available for utilisation). | P32: TB.gstin_branch = GSTR9.gstin; TB.fy = GSTR9.financial_year | Q32: GL head mapping master – implementation choice. | R32: FY per head; expense-head-wise for Table 14. | S32: (TB.itc_booked_h + 12B_h − 12C_h) vs GSTR9.7J_h | T32: Rs 1 per head (implementation choice). | U32: 12D = 12A + 12B − 12C; 12F (unreconciled) = 12D − 12E | V32: 1. 12A = Σ debits to input credit ledgers in FY (net of reversals as booked). 2. 12B = earlier-FY books ITC claimed this FY (from 6A1 / RC-GST-025). 3. 12C = current-FY books ITC claimed next FY (8C/13). 4. 12E = GSTR-9 7J. 5. 12F residual; positive = books > return (ITC lost?); negative = return > books (excess claim). | W32: RECONCILED; BOOKS_MORE_THAN_RETURN: possible unclaimed ITC; RETURN_MORE_THAN_BOOKS: ITC claimed not in books (high risk); HEAD_SPLIT_DIFF | X32: RECONCILED=Low; BOOKS_MORE_THAN_RETURN=Medium; RETURN_MORE_THAN_BOOKS=Critical; HEAD_SPLIT_DIFF=Medium | Y32: tolerance_inr=1 | Z32: Input ledgers identified; TB balances final. | AA32: exception_id; rule_id; client_id; gstin; period; doc_a_ref (file+row); doc_b_ref; match_key; match_pass (exact/fuzzy); category; severity; field_name; value_a; value_b; difference; tolerance_applied; suggested_action; legal_reference; status (Open/Under review/Resolved/Accepted-as-is); reviewer; review_comment; created_at; head; t12A; t12B; t12C; t12D; t12E; t12F | AB32: CGST: 12A 40,00,000; 12B 50,000; 12C 1,00,000 -> 12D 39,50,000; 12E 39,80,000 -> 12F −30,000 -> RETURN_MORE_THAN_BOOKS. | AC32: 12D = 12E -> RECONCILED. | AD32: Branch without separate TB -> INPUT_ERROR (cannot compute per GSTIN). | AE32: ITC expensed in P&L (blocked credit) but claimed; capital goods ITC capitalised; ISD credits; RCM ITC; reversals booked at year-end only. | AF32: RETURN_MORE_THAN_BOOKS: verify and reverse via DRC-03 with interest; record in 9C Part V. | AG32: def rc_gst_027(tb, g9, p): out = [] for h in HEADS4: t12d = tb.itc_booked[h] + g9.t6A1[h] - (g9.t8C[h] + g9.t13[h]) f = t12d - g9.t7J[h] if f > p.tolerance_inr: out.append(exc('BOOKS_MORE_THAN_RETURN', head=h, diff=f)) elif f < -p.tolerance_inr: out.append(exc('RETURN_MORE_THAN_BOOKS', head=h, diff=f)) return out or [exc('RECONCILED')] | AH32: ClearTax – revised GSTR-9C from FY 2020-21 | https://cleartax.in/s/revised-gstr-9c-fy-2020-21 | self-certification; N.29/30/2021-CT; Table 5, 9, 11, 12, 14 VJM Global – GSTN FAQs on GSTR-9/9C FY 2024-25 | https://www.vjmglobal.com/blog/gstn-issued-faqs-on-newly-released-form-gstr-9-9c-for-fy-2024-25 | 8A from 2B; 8C; 6A1; 8H1; Table 4/5 from GSTR-1/1A/IFF; Table 9 from 3B 6.1 | AI32: Table 12 row meanings from form knowledge; ClearTax confirms 12B, 12C and 14 optional (FY 2020-21). Mapping 12B/12C to GSTR-9 6A1/8C/13 is an implementation approximation – CA to confirm.
A33: RC-GST-028 | B33: reconciliation_rule | C33: GST – Books vs return | D33: Trial balance GST ledgers (output, input, RCM payable, cash ledger) vs GSTR-3B | E33: Unverified – needs CA review | F33: Tie monthly movements in the books' GST ledgers to GSTR-3B: output tax credited, input credit debited, RCM payable, set-off entries and cash payments; flag ledger balances that should be nil. | G33: TB | H33: GSTR3B | I33: GL | J33: tax period (month) | K33: CGST Act s.35 (accounts), Rule 56 (books to show tax payable, ITC, RCM); s.39 (GSTR-3B). Mapping is an accounting reconciliation – no specific provision. | L33: All regular taxpayers. | M33: 2017-07-01 | O33: TB/GL monthly movement by GST ledger (Output IGST/CGST/SGST/cess; Input IGST/CGST/SGST/cess; RCM payable; ITC reversal; GST cash ledger/electronic cash ledger asset; GST payable); ledger mapping master. | P33: TB.gstin_branch = GSTR3B.gstin; TB.month = GSTR3B.return_period | Q33: Ledger names mapped via master (implementation choice). | R33: Per month per head. | S33: TB.output_credit_h (net of CN debits) vs GSTR3B.3_1_a+3_1_b tax_h; TB.rcm_payable_credit_h vs GSTR3B.3_1_d_h; TB.input_debit_h vs GSTR3B.4A_h; TB.itc_reversal_h vs GSTR3B.4B_h; TB.setoff_entries_h vs GSTR3B.6_1 ITC used_h; TB.cash_paid_h vs GSTR3B.6_1 cash_h; TB.closing_output_h (after set-off) vs 0 | T33: Rs 1 per head per month (implementation choice). | U33: diff_h = books_movement_h − gstr3b_value_h; closing_payable_check = opening + credits − setoff − cash ≈ 0 after month-end entries | V33: 1. Map ledgers. 2. Compute monthly movements. 3. Compare. 4. Input credit ledger closing vs ECRL closing (cross-check RC-GST-021). 5. Output/RCM payable closing should be nil after set-off – non-zero -> PAYABLE_BALANCE. | W33: MATCHED; OUTPUT_DIFF; RCM_DIFF; INPUT_DIFF; REVERSAL_DIFF; SETOFF_DIFF; CASH_DIFF; PAYABLE_BALANCE; ECRL_BOOKS_DIFF | X33: MATCHED=Low; OUTPUT_DIFF=High; RCM_DIFF=High; INPUT_DIFF=High; REVERSAL_DIFF=Medium; SETOFF_DIFF=Medium; CASH_DIFF=Medium; PAYABLE_BALANCE=Medium; ECRL_BOOKS_DIFF=Medium | Y33: tolerance_inr=1; ledger_map= | Z33: All GST ledgers mapped; TB month-wise available. | AA33: exception_id; rule_id; client_id; gstin; period; doc_a_ref (file+row); doc_b_ref; match_key; match_pass (exact/fuzzy); category; severity; field_name; value_a; value_b; difference; tolerance_applied; suggested_action; legal_reference; status (Open/Under review/Resolved/Accepted-as-is); reviewer; review_comment; created_at; ledger; head; books_value; return_value | AB33: Aug-2025: Output CGST ledger credit 63,000; 3B 3.1(a) CGST 60,000 -> OUTPUT_DIFF 3,000 (also seen in RC-GST-007). Input CGST debit 25,000; 3B 4A CGST 25,000 -> MATCHED. | AC33: All movements equal -> MATCHED. | AD33: Ledger 'GST Payable' combined for all heads -> mapping warning; comparison at total level only. | AE33: Year-end provision entries; GST on advances booked differently; ITC parked in 'ITC pending' ledger; blocked credits expensed. | AF33: Pass rectification JV or correct return in next period; investigate OUTPUT_DIFF jointly with RC-GST-001/007. | AG33: def rc_gst_028(tb, g3b, m, p): mv = monthly_movements(tb, m, p.period) pairs = [('output', lambda h: g3b['3_1_a'][h]+g3b['3_1_b'][h], 'OUTPUT_DIFF'), ('rcm_payable', lambda h: g3b['3_1_d'][h], 'RCM_DIFF'), ('input', lambda h: sum(g3b[r][h] for r in A_ROWS), 'INPUT_DIFF'), ('itc_reversal', lambda h: g3b['4B1'][h]+g3b['4B2'][h], 'REVERSAL_DIFF')] out = [] for led, f, cat in pairs: for h in HEADS4: d = mv[led][h] - f(h) if abs(d) > p.tolerance_inr: out.append(exc(cat, head=h, diff=d)) return out | AH33: Circular 170/02/2022-GST | https://www.gstcouncil.gov.in/sites/default/files/2024-06/cir-170-02-2022-cgst.pdf | GSTR-3B Table 4 and 3.2 reporting | AI33: Accounting reconciliation – implementation design. Rule 56 reference from statute knowledge.
A34: RC-GST-029 | B34: reconciliation_rule | C34: GST – Exempt supplies | D34: Exempt / nil-rated / non-GST turnover in books vs GSTR-1 Table 8 and GSTR-3B 3.1(c)/(e); Rule 42 inputs | E34: Partially verified | F34: Check exempt, nil-rated and non-GST outward supplies in the books are reported in GSTR-1 Table 8 and 3B 3.1(c)/(e), and supply the exempt-turnover figures used in the Rule 42/43 reversal computation. | G34: SALES_REG | H34: GSTR1 | I34: GSTR3B | J34: tax period (month); FY for Rule 42 final | K34: CGST Act s.2(47) (exempt supply), s.17(2)-(3) (value of exempt supply includes reverse-charge supplies, transactions in securities, sale of land and, subject to para 5 Schedule II, building; excludes certain Schedule III items per Explanation); Rule 42, Rule 43, Rule 45 (value for securities – not re-verified); GSTR-1 Table 8 (nil rated, exempted, non-GST by inter/intra and registered/unregistered); GSTR-3B 3.1(c) (nil/exempt) and 3.1(e) (non-GST). | L34: Taxpayers making exempt/nil/non-GST supplies. | M34: 2017-07-01 | O34: Sales register / GL with supply classification (nil-rated, exempt with notification entry, non-GST e.g. petroleum/alcohol for human consumption, Schedule III), registered/unregistered and intra/inter; GSTR-1 nil section; GSTR-3B 3.1(c),(e); Rule 42 working (E, F, T4, C2) from GST-019. | P34: SALES_REG.supply_class = GSTR1.nil_category; SALES_REG.nil_supply_type = GSTR1.nil_supply_type | Q34: Category map: NIL / EXEMPT / NON_GST; sply_ty INTRB2B, INTRB2C, INTRAB2B, INTRAB2C (GSTR-1 nil JSON – implementation mapping). | R34: Per category per supply type per month; FY for Rule 42. | S34: SALES_REG.nil_value vs GSTR1.nil_rated_amount; SALES_REG.exempt_value vs GSTR1.exempted_amount; SALES_REG.non_gst_value vs GSTR1.non_gst_amount; Σ(nil+exempt) vs GSTR3B.3_1_c.txval; Σ non_gst vs GSTR3B.3_1_e.txval; Rule42.E vs books exempt turnover (incl. s.17(3) items) | T34: Rs 10 per bucket (implementation choice). | U34: E_books = exempt + nil + RCM outward (where supplier not liable) + s.17(3) items; Rule 42 D1 = (E/F) × C2 recomputed and compared with 4B(1) reported | V34: 1. Aggregate books by category. 2. Compare with GSTR-1 Table 8 and 3B. 3. Recompute E and F for Rule 42 (and Te/Tr for Rule 43); compare D1+D2 with 3B 4B(1) reversal (monthly) and annual true-up (by Sept return of next FY). 4. Flag exempt supplies with ITC fully claimed and no reversal. | W34: MATCHED; TABLE8_DIFF; 3B_EXEMPT_DIFF; NONGST_DIFF; RULE42_SHORT_REVERSAL; RULE42_EXCESS_REVERSAL; NO_REVERSAL_WITH_EXEMPT: exempt turnover but 4B(1) nil; MISCLASSIFIED: exempt reported as nil/non-GST or vice versa | X34: MATCHED=Low; TABLE8_DIFF=Medium; 3B_EXEMPT_DIFF=Medium; NONGST_DIFF=Low; RULE42_SHORT_REVERSAL=High; RULE42_EXCESS_REVERSAL=Low; NO_REVERSAL_WITH_EXEMPT=Critical; MISCLASSIFIED=Low | Y34: bucket_tolerance_inr=10; d2_pct=5 | Z34: Each exempt line has classification; F > 0 for Rule 42. | AA34: exception_id; rule_id; client_id; gstin; period; doc_a_ref (file+row); doc_b_ref; match_key; match_pass (exact/fuzzy); category; severity; field_name; value_a; value_b; difference; tolerance_applied; suggested_action; legal_reference; status (Open/Under review/Resolved/Accepted-as-is); reviewer; review_comment; created_at; category; sply_ty; E; F; C2; D1; D2; reported_4B1 | AB34: Aug-2025: books exempt (interest income? excluded – CA) 2,00,000; taxable 18,00,000 -> F 20,00,000; common credit C2 50,000 -> D1 = 2,00,000/20,00,000 × 50,000 = 5,000; D2 (if non-business use) 2,500. 3B 4B(1) 0 -> NO_REVERSAL_WITH_EXEMPT 5,000 (+2,500 if applicable). GSTR-1 Table 8 exempt 2,00,000 = books -> MATCHED. | AC34: Only taxable supplies -> E=0, no reversal needed. | AD34: Interest on deposits/loans (exempt under notification) – whether included in E is per s.17(3) Explanation and CA judgment (param list of excluded GL heads). | AE34: Interest income, rent of residential dwelling, sale of land/old assets not classified; non-GST petroleum supplies; Schedule III items wrongly included in E; no reversal by service companies with exempt income. | AF34: Reverse D1+D2 in 4B(1); annual recomputation with s.50(1) interest on excess (Rule 42(2)). | AG34: def rc_gst_029(books, g1, g3b, r42, p): b = agg(books[books.supply_class.isin(['NIL','EXEMPT','NON_GST'])], ['supply_class','sply_ty'], ['value']) out = compare_outer(b, g1.nil_flat, keys=[('supply_class','cat'),('sply_ty','sply_ty')], tol=p.bucket_tolerance_inr, cats=('TABLE8_DIFF',)*3) if abs(b[b.supply_class.isin(['NIL','EXEMPT'])].value.sum() - g3b['3_1_c'].txval) > p.bucket_tolerance_inr: out.append(exc('3B_EXEMPT_DIFF')) E, F = r42.E_books, r42.F_books d1 = E/F * r42.C2 if F else 0; d2 = p.d2_pct/100 * r42.C2 if r42.non_business_use else 0 rep = g3b['4B1'].total if E > 0 and rep == 0: out.append(exc('NO_REVERSAL_WITH_EXEMPT', diff=d1+d2)) elif d1 + d2 - rep > p.bucket_tolerance_inr: out.append(exc('RULE42_SHORT_REVERSAL', diff=d1+d2-rep)) return out | AH34: Rule 42 CGST Rules (Chhattisgarh GST dept copy) | https://www.cggst.com/uploads/document/1755064648-rule-42.pdf | Rule 42(1)-(2) Circular 170/02/2022-GST | https://www.gstcouncil.gov.in/sites/default/files/2024-06/cir-170-02-2022-cgst.pdf | GSTR-3B Table 4 and 3.2 reporting | AI34: Rule 42 verified from state department copy (GST-019). s.17(3) Explanation inclusions/exclusions and Rule 45 not re-verified. 4B(1) may also include Rule 38/43/17(5) reversals – separate them via books classification.
